Workbook
Name SegmentaciónDeDatos_CIUDAD: #N/A
Name SegmentaciónDeDatos_NOMBRE_COMERCIAL: #N/A

Sheet INFORME
A1: INFORME MYSTERY FEBRERO
D3: EJECUCION DEL PLAN
D4: CIUDAD | E4: #PDV Obj. | F4: #PDV Eje. | G4: .% Ejecucion | H4: Obj Mystery | I4: Mystery Eje. | J4: % Efectividad.
D5: CARTAGENA | E5: 1 | F5: 1 | G5: 1 | H5: 1 | I5: 1 | J5: 1
D6: CALI | E6: 2 | F6: 2 | G6: 1 | H6: 2 | I6: 2 | J6: 1
D7: BARRANQUILLA | E7: 1 | F7: 1 | G7: 1 | H7: 1 | I7: 1 | J7: 1
D8: BOGOTA | E8: 1 | F8: 1 | G8: 1 | H8: 1 | I8: 1 | J8: 1
D9: Total general | E9: 5 | F9: 5 | G9: 1 | H9: 5 | I9: 5 | J9: 1
D15: MYSTERY POR CLUSTER
D16: Suma de % MYSTERY | E16: Etiquetas de columna
D17: CLUSTER | E17: MODERNO | F17: ESPECIALIZADO | G17: TRADICIONAL | H17: % MYSTERY
D18: LABOR DE VENTA | E18: 1 | F18: 1 | G18: 1 | H18: 1
D19: HORARIO | E19: 1 | F19: 1 | G19: 1 | H19: 1
D20: UNIFORME | E20: 1 | F20: 1 | G20: 1 | H20: 1
D21: ABORDAJE | E21: 1 | F21: 1 | G21: 1 | H21: 1
D22: PORTAFOLIO Y MANEJO DE OBJECIONES | E22: 0.95 | F22: 0.96666667 | G22: 0.8 | H22: 0.93
D23: % MYSTERY | E23: 0.985 | F23: 0.99 | G23: 0.94 | H23: 0.979
D29: MYSTERY POR CLUSTER - CIUDAD
D30: Suma de % MYSTERY | E30: Etiquetas de columna
D31: CLUSTER | E31: BOGOTA | F31: CALI | G31: CARTAGENA | H31: BARRANQUILLA | I31: % MYSTERY
D32: LABOR DE VENTA | E32: 1 | F32: 1 | G32: 1 | H32: 1 | I32: 1
D33: HORARIO | E33: 1 | F33: 1 | G33: 1 | H33: 1 | I33: 1
D34: UNIFORME | E34: 1 | F34: 1 | G34: 1 | H34: 1 | I34: 1
D35: ABORDAJE | E35: 1 | F35: 1 | G35: 1 | H35: 1 | I35: 1
D36: PORTAFOLIO Y MANEJO DE OBJECIONES | E36: 0.9 | F36: 0.9 | G36: 0.95 | H36: 1 | I36: 0.93
D37: % MYSTERY | E37: 0.97 | F37: 0.97 | G37: 0.985 | H37: 1 | I37: 0.979
D43: MYSTERY EFECTIVO | E43: SI
D44: MYSTERY POR PDV
D45: Suma de % MYSTERY | G45: CLUSTER
D46: CIUDAD | E46: CANAL | F46: NOMBRE COMERCIAL | G46: ABORDAJE | H46: HORARIO | I46: LABOR DE VENTA | J46: PORTAFOLIO Y MANEJO DE OBJECIONES | K46: UNIFORME | L46: % MYSTERY
D47: BOGOTA | E47: ESPECIALIZADO | F47: 424858 - AGROCAMPO S.A.S. | G47: 1 | H47: 1 | I47: 1 | J47: 0.9 | K47: 1 | L47: 0.97
D48: CALI | E48: ESPECIALIZADO | F48: 424808 - HOLANDA NORTE | G48: 1 | H48: 1 | I48: 1 | J48: 1 | K48: 1 | L48: 1
D49: CALI | E49: TRADICIONAL | F49: LA CASA DE LOS TENDEROS | G49: 1 | H49: 1 | I49: 1 | J49: 0.8 | K49: 1 | L49: 0.94
D50: CARTAGENA | E50: MODERNO | F50: 424810 - HOMECENTER CARTAGENA | G50: 1 | H50: 1 | I50: 1 | J50: 0.95 | K50: 1 | L50: 0.985
D51: BARRANQUILLA | E51: ESPECIALIZADO | F51: 421609 - LA FAVORITA DE LA 14 | G51: 1 | H51: 1 | I51: 1 | J51: 1 | K51: 1 | L51: 1
D52: % MYSTERY | G52: 1 | H52: 1 | I52: 1 | J52: 0.93 | K52: 1 | L52: 0.979

Sheet Videos
A1: CIUDAD | B1: NOMBRE COMERCIAL | C1: VIDEO 1 | D1: VIDEO 2 | E1: VIDEO 3 | F1: VIDEO 4 | G1: VIDEO 5 | H1: VIDEO 6
A2: BARRANQUILLA | B2: 421609 - LA FAVORITA DE LA 14 | C2: https://drive.google.com/file/d/1xTD_FOrp9xtvriAa06FlOXCv68XCzmiX/view | D2: - | E2: - | F2: - | G2: - | H2: -
A3: BOGOTA | B3: 424858 - AGROCAMPO S.A.S. | C3: https://drive.google.com/file/d/1XwWPqfXlZvb88B3cSTKLog57F9yO7lr7/view | D3: - | E3: - | F3: - | G3: - | H3: -
A4: CALI | B4: LA CASA DE LOS TENDEROS | C4: https://drive.google.com/file/d/1X-s8H1oACzvA35fty4K9UX9b91Xfq0SH/view | D4: - | E4: - | F4: - | G4: - | H4: -
A5: CALI | B5: 424808 - HOLANDA NORTE | C5: https://drive.google.com/file/d/1d05UXeDeoqZnEk22-rnJUqOPPo2LWPzt/view | D5: - | E5: - | F5: - | G5: - | H5: -
A6: CARTAGENA | B6: 424810 - HOMECENTER CARTAGENA | C6: https://drive.google.com/file/d/1abCvezGqCU1ZmOXb2u7xi19jBsQPGJxb/view | D6: - | E6: - | F6: - | G6: - | H6: -

Sheet PUNTAJES
A1: ACTIVIDAD | B1: CIUDAD | C1: CANAL | D1: CADENA | E1: CODIGO PDV | F1: NOMBRE COMERCIAL | G1: PREGUNTA | H1: RTA | I1: FECHA VISITA | J1: CODIGO RUTA | K1: USUARIO | L1: MYSTERY EFECTIVO | M1: CLUSTER | N1: TOTAL PUNTAJE | O1: RTA CORRECTA | P1: PUNTAJE OBTENIDO | Q1: Columna1 | R1: Columna2 | T1: SI(O(G17="Dog Chow";G17="Cat Chow";G17="Alpo";G17="Gatsy";G17="Feliz");N17;0) | U1: SI(O(G29="Dog Chow húmedo";G29="Cat Chow húmedo";G29="Fancy Feast";G29="Felix";G29="Proplan húmedo";G29="One húmedo";G29="Snack Abrazzos";G29="Snak Dentalife";G29="Arenilla Tidy Cat");N29;0)
A2: NESTLE PURINA | B2: BOGOTA | C2: ESPECIALIZADO | D2: JUMBO | E2: 424858 | F2: 424858 - AGROCAMPO S.A.S. | G2: SE LOGRA REALIZAR EL MYSTERY? | H2: SI | J2: 30182843 | K2: NestleP.1 | L2: =_xlfn.XLOOKUP(Tabla2__2[[#This Row],[CODIGO RUTA]],'DATA INFORME'!I:I,'DATA INFORME'!K:K) -> SI | M2: =IF(Tabla2__2[[#This Row],[MYSTERY EFECTIVO]]="SI",_xlfn.XLOOKUP(Tabla2__2[[#This Row],[PREGUNTA]],ENCUESTA!G:G,ENCUESTA!D:D),"N/A") -> N/A | N2: =IF(Tabla2__2[[#This Row],[MYSTERY EFECTIVO]]="SI",(IF(Tabla2__2[[#This Row],[CANAL]]="TRADICIONAL",_xlfn.XLOOKUP(Tabla2__2[[#This Row],[PREGUNTA]],ENCUESTA!G:G,ENCUESTA!A:A),IF(Tabla2__2[[#This Row],[CANAL]]="ESPECIALIZADO",_xlfn.XLOOKUP(Tabla2__2[[#This Row],[PREGUNTA]],ENCUESTA!G:G,ENCUESTA!B:B),IF(Tabla2__2[[#This Row],[CANAL]]="MODERNO",_xlfn.XLOOKUP(Tabla2__2[[#This Row],[PREGUNTA]],ENCUESTA!G:G,ENCUESTA!C:C))))),0) -> 0 | O2: =_xlfn.XLOOKUP(Tabla2__2[[#This Row],[PREGUNTA]],ENCUESTA!G:G,ENCUESTA!H:H) -> 0 | P2: =IF(Tabla2__2[[#This Row],[RTA]]=Tabla2__2[[#This Row],[RTA CORRECTA]],Tabla2__2[[#This Row],[TOTAL PUNTAJE]],0) -> 0 | Q2: =IF(OR(H2="Dog Chow húmedo",H2="Cat Chow húmedo",H2="Fancy Feast",H2="Felix",H2="Proplan húmedo",H2="One húmedo",H2="Snack Abrazzos",H2="Snak Dentalife",H2="Arenilla Tidy Cat"),N2,0) -> 0
A3: NESTLE PURINA | B3: CARTAGENA | C3: MODERNO | D3: OLIMPICA | E3: 424810 | F3: 424810 - HOMECENTER CARTAGENA | G3: SE PRODUCE ABORDAJE PROACTIVO (antes de 1 min) | H3: SI | J3: 30249632 | K3: NestleP.5 | L3: =_xlfn.XLOOKUP(Tabla2__2[[#This Row],[CODIGO RUTA]],'DATA INFORME'!I:I,'DATA INFORME'!K:K) -> SI | M3: =IF(Tabla2__2[[#This Row],[MYSTERY EFECTIVO]]="SI",_xlfn.XLOOKUP(Tabla2__2[[#This Row],[PREGUNTA]],ENCUESTA!G:G,ENCUESTA!D:D),"N/A") -> ABORDAJE | N3: =IF(Tabla2__2[[#This Row],[MYSTERY EFECTIVO]]="SI",(IF(Tabla2__2[[#This Row],[CANAL]]="TRADICIONAL",_xlfn.XLOOKUP(Tabla2__2[[#This Row],[PREGUNTA]],ENCUESTA!G:G,ENCUESTA!A:A),IF(Tabla2__2[[#This Row],[CANAL]]="ESPECIALIZADO",_xlfn.XLOOKUP(Tabla2__2[[#This Row],[PREGUNTA]],ENCUESTA!G:G,ENCUESTA!B:B),IF(Tabla2__2[[#This Row],[CANAL]]="MODERNO",_xlfn.XLOOKUP(Tabla2__2[[#This Row],[PREGUNTA]],ENCUESTA!G:G,ENCUESTA!C:C))))),0) -> 20 | O3: =_xlfn.XLOOKUP(Tabla2__2[[#This Row],[PREGUNTA]],ENCUESTA!G:G,ENCUESTA!H:H) -> SI | P3: =IF(Tabla2__2[[#This Row],[RTA]]=Tabla2__2[[#This Row],[RTA CORRECTA]],Tabla2__2[[#This Row],[TOTAL PUNTAJE]],0) -> 20 | Q3: =IF(OR(H3="Dog Chow húmedo",H3="Cat Chow húmedo",H3="Fancy Feast",H3="Felix",H3="Proplan húmedo",H3="One húmedo",H3="Snack Abrazzos",H3="Snak Dentalife",H3="Arenilla Tidy Cat"),N3,0) -> 0
A4: NESTLE PURINA | B4: CARTAGENA | C4: MODERNO | D4: OLIMPICA | E4: 424810 | F4: 424810 - HOMECENTER CARTAGENA | G4: INDAGA SOBRE LAS NECESIDADES DEL CLIENTE CON RESPECTO A SU CONSUMO HABITUAL " MARCAS COMPETENCIA O PROPIAS" - OBJECIÓN DE PRECIOS. | H4: SI | J4: 30249632 | K4: NestleP.5 | L4: =_xlfn.XLOOKUP(Tabla2__2[[#This Row],[CODIGO RUTA]],'DATA INFORME'!I:I,'DATA INFORME'!K:K) -> SI | M4: =IF(Tabla2__2[[#This Row],[MYSTERY EFECTIVO]]="SI",_xlfn.XLOOKUP(Tabla2__2[[#This Row],[PREGUNTA]],ENCUESTA!G:G,ENCUESTA!D:D),"N/A") -> PORTAFOLIO Y MANEJO DE OBJECIONES | N4: =IF(Tabla2__2[[#This Row],[MYSTERY EFECTIVO]]="SI",(IF(Tabla2__2[[#This Row],[CANAL]]="TRADICIONAL",_xlfn.XLOOKUP(Tabla2__2[[#This Row],[PREGUNTA]],ENCUESTA!G:G,ENCUESTA!A:A),IF(Tabla2__2[[#This Row],[CANAL]]="ESPECIALIZADO",_xlfn.XLOOKUP(Tabla2__2[[#This Row],[PREGUNTA]],ENCUESTA!G:G,ENCUESTA!B:B),IF(Tabla2__2[[#This Row],[CANAL]]="MODERNO",_xlfn.XLOOKUP(Tabla2__2[[#This Row],[PREGUNTA]],ENCUESTA!G:G,ENCUESTA!C:C))))),0) -> 1.5 | O4: =_xlfn.XLOOKUP(Tabla2__2[[#This Row],[PREGUNTA]],ENCUESTA!G:G,ENCUESTA!H:H) -> SI | P4: =IF(Tabla2__2[[#This Row],[RTA]]=Tabla2__2[[#This Row],[RTA CORRECTA]],Tabla2__2[[#This Row],[TOTAL PUNTAJE]],0) -> 1.5 | Q4: =IF(OR(H4="Dog Chow húmedo",H4="Cat Chow húmedo",H4="Fancy Feast",H4="Felix",H4="Proplan húmedo",H4="One húmedo",H4="Snack Abrazzos",H4="Snak Dentalife",H4="Arenilla Tidy Cat"),N4,0) -> 0
A5: NESTLE PURINA | B5: CARTAGENA | C5: MODERNO | D5: OLIMPICA | E5: 424810 | F5: 424810 - HOMECENTER CARTAGENA | G5: OFRECE PURINA ONE: (APLICA SOLO EN CANAL MODERNO, CADENAS, SI EL PRODUCTO ESTA EN EL PDV) | H5: NO | J5: 30249632 | K5: NestleP.5 | L5: =_xlfn.XLOOKUP(Tabla2__2[[#This Row],[CODIGO RUTA]],'DATA INFORME'!I:I,'DATA INFORME'!K:K) -> SI | M5: =IF(Tabla2__2[[#This Row],[MYSTERY EFECTIVO]]="SI",_xlfn.XLOOKUP(Tabla2__2[[#This Row],[PREGUNTA]],ENCUESTA!G:G,ENCUESTA!D:D),"N/A") -> PORTAFOLIO Y MANEJO DE OBJECIONES | N5: =IF(Tabla2__2[[#This Row],[MYSTERY EFECTIVO]]="SI",(IF(Tabla2__2[[#This Row],[CANAL]]="TRADICIONAL",_xlfn.XLOOKUP(Tabla2__2[[#This Row],[PREGUNTA]],ENCUESTA!G:G,ENCUESTA!A:A),IF(Tabla2__2[[#This Row],[CANAL]]="ESPECIALIZADO",_xlfn.XLOOKUP(Tabla2__2[[#This Row],[PREGUNTA]],ENCUESTA!G:G,ENCUESTA!B:B),IF(Tabla2__2[[#This Row],[CANAL]]="MODERNO",_xlfn.XLOOKUP(Tabla2__2[[#This Row],[PREGUNTA]],ENCUESTA!G:G,ENCUESTA!C:C))))),0) -> 1.5 | O5: =_xlfn.XLOOKUP(Tabla2__2[[#This Row],[PREGUNTA]],ENCUESTA!G:G,ENCUESTA!H:H) -> SI | P5: =IF(Tabla2__2[[#This Row],[RTA]]=Tabla2__2[[#This Row],[RTA CORRECTA]],Tabla2__2[[#This Row],[TOTAL PUNTAJE]],0) -> 0 | Q5: =IF(OR(H5="Dog Chow húmedo",H5="Cat Chow húmedo",H5="Fancy Feast",H5="Felix",H5="Proplan húmedo",H5="One húmedo",H5="Snack Abrazzos",H5="Snak Dentalife",H5="Arenilla Tidy Cat"),N5,0) -> 0
A6: NESTLE PURINA | B6: CARTAGENA | C6: MODERNO | D6: OLIMPICA | E6: 424810 | F6: 424810 - HOMECENTER CARTAGENA | G6: MENCIONA QUE LOS RESULTADOS SON VISIBLES EN 28 DIAS? | H6: SI | J6: 30249632 | K6: NestleP.5 | L6: =_xlfn.XLOOKUP(Tabla2__2[[#This Row],[CODIGO RUTA]],'DATA INFORME'!I:I,'DATA INFORME'!K:K) -> SI | M6: =IF(Tabla2__2[[#This Row],[MYSTERY EFECTIVO]]="SI",_xlfn.XLOOKUP(Tabla2__2[[#This Row],[PREGUNTA]],ENCUESTA!G:G,ENCUESTA!D:D),"N/A") -> PORTAFOLIO Y MANEJO DE OBJECIONES | N6: =IF(Tabla2__2[[#This Row],[MYSTERY EFECTIVO]]="SI",(IF(Tabla2__2[[#This Row],[CANAL]]="TRADICIONAL",_xlfn.XLOOKUP(Tabla2__2[[#This Row],[PREGUNTA]],ENCUESTA!G:G,ENCUESTA!A:A),IF(Tabla2__2[[#This Row],[CANAL]]="ESPECIALIZADO",_xlfn.XLOOKUP(Tabla2__2[[#This Row],[PREGUNTA]],ENCUESTA!G:G,ENCUESTA!B:B),IF(Tabla2__2[[#This Row],[CANAL]]="MODERNO",_xlfn.XLOOKUP(Tabla2__2[[#This Row],[PREGUNTA]],ENCUESTA!G:G,ENCUESTA!C:C))))),0) -> 1.5 | O6: =_xlfn.XLOOKUP(Tabla2__2[[#This Row],[PREGUNTA]],ENCUESTA!G:G,ENCUESTA!H:H) -> SI | P6: =IF(Tabla2__2[[#This Row],[RTA]]=Tabla2__2[[#This Row],[RTA CORRECTA]],Tabla2__2[[#This Row],[TOTAL PUNTAJE]],0) -> 1.5 | Q6: =IF(OR(H6="Dog Chow húmedo",H6="Cat Chow húmedo",H6="Fancy Feast",H6="Felix",H6="Proplan húmedo",H6="One húmedo",H6="Snack Abrazzos",H6="Snak Dentalife",H6="Arenilla Tidy Cat"),N6,0) -> 0
A7: NESTLE PURINA | B7: CARTAGENA | C7: MODERNO | D7: OLIMPICA | E7: 424810 | F7: 424810 - HOMECENTER CARTAGENA | G7: MENCIONA QUE TIENE CARNE DE VERDAD COMO INGREDIENTE NO.1 E INGREDIENTES NATURALES Y FUNCIONALES? | H7: SI | J7: 30249632 | K7: NestleP.5 | L7: =_xlfn.XLOOKUP(Tabla2__2[[#This Row],[CODIGO RUTA]],'DATA INFORME'!I:I,'DATA INFORME'!K:K) -> SI | M7: =IF(Tabla2__2[[#This Row],[MYSTERY EFECTIVO]]="SI",_xlfn.XLOOKUP(Tabla2__2[[#This Row],[PREGUNTA]],ENCUESTA!G:G,ENCUESTA!D:D),"N/A") -> PORTAFOLIO Y MANEJO DE OBJECIONES | N7: =IF(Tabla2__2[[#This Row],[MYSTERY EFECTIVO]]="SI",(IF(Tabla2__2[[#This Row],[CANAL]]="TRADICIONAL",_xlfn.XLOOKUP(Tabla2__2[[#This Row],[PREGUNTA]],ENCUESTA!G:G,ENCUESTA!A:A),IF(Tabla2__2[[#This Row],[CANAL]]="ESPECIALIZADO",_xlfn.XLOOKUP(Tabla2__2[[#This Row],[PREGUNTA]],ENCUESTA!G:G,ENCUESTA!B:B),IF(Tabla2__2[[#This Row],[CANAL]]="MODERNO",_xlfn.XLOOKUP(Tabla2__2[[#This Row],[PREGUNTA]],ENCUESTA!G:G,ENCUESTA!C:C))))),0) -> 1.5 | O7: =_xlfn.XLOOKUP(Tabla2__2[[#This Row],[PREGUNTA]],ENCUESTA!G:G,ENCUESTA!H:H) -> SI | P7: =IF(Tabla2__2[[#This Row],[RTA]]=Tabla2__2[[#This Row],[RTA CORRECTA]],Tabla2__2[[#This Row],[TOTAL PUNTAJE]],0) -> 1.5 | Q7: =IF(OR(H7="Dog Chow húmedo",H7="Cat Chow húmedo",H7="Fancy Feast",H7="Felix",H7="Proplan húmedo",H7="One húmedo",H7="Snack Abrazzos",H7="Snak Dentalife",H7="Arenilla Tidy Cat"),N7,0) -> 0
A8: NESTLE PURINA | B8: CARTAGENA | C8: MODERNO | D8: OLIMPICA | E8: 424810 | F8: 424810 - HOMECENTER CARTAGENA | G8: MENCIONA QUE PURINA ONE CUENTA CON ALIMENTO HUMEDO Y MENCIONA LAS 3 VARIADADES QUE TIENE ( SUPER FOODS, SUPER NUTRIENTES Y MULTI PROTEINAS); APLICA TANTO PARA PERRO COMO PARA GATO? | H8: SI | J8: 30249632 | K8: NestleP.5 | L8: =_xlfn.XLOOKUP(Tabla2__2[[#This Row],[CODIGO RUTA]],'DATA INFORME'!I:I,'DATA INFORME'!K:K) -> SI | M8: =IF(Tabla2__2[[#This Row],[MYSTERY EFECTIVO]]="SI",_xlfn.XLOOKUP(Tabla2__2[[#This Row],[PREGUNTA]],ENCUESTA!G:G,ENCUESTA!D:D),"N/A") -> PORTAFOLIO Y MANEJO DE OBJECIONES | N8: =IF(Tabla2__2[[#This Row],[MYSTERY EFECTIVO]]="SI",(IF(Tabla2__2[[#This Row],[CANAL]]="TRADICIONAL",_xlfn.XLOOKUP(Tabla2__2[[#This Row],[PREGUNTA]],ENCUESTA!G:G,ENCUESTA!A:A),IF(Tabla2__2[[#This Row],[CANAL]]="ESPECIALIZADO",_xlfn.XLOOKUP(Tabla2__2[[#This Row],[PREGUNTA]],ENCUESTA!G:G,ENCUESTA!B:B),IF(Tabla2__2[[#This Row],[CANAL]]="MODERNO",_xlfn.XLOOKUP(Tabla2__2[[#This Row],[PREGUNTA]],ENCUESTA!G:G,ENCUESTA!C:C))))),0) -> 1.5 | O8: =_xlfn.XLOOKUP(Tabla2__2[[#This Row],[PREGUNTA]],ENCUESTA!G:G,ENCUESTA!H:H) -> SI | P8: =IF(Tabla2__2[[#This Row],[RTA]]=Tabla2__2[[#This Row],[RTA CORRECTA]],Tabla2__2[[#This Row],[TOTAL PUNTAJE]],0) -> 1.5 | Q8: =IF(OR(H8="Dog Chow húmedo",H8="Cat Chow húmedo",H8="Fancy Feast",H8="Felix",H8="Proplan húmedo",H8="One húmedo",H8="Snack Abrazzos",H8="Snak Dentalife",H8="Arenilla Tidy Cat"),N8,0) -> 0
A9: NESTLE PURINA | B9: CARTAGENA | C9: MODERNO | D9: OLIMPICA | E9: 424810 | F9: 424810 - HOMECENTER CARTAGENA | G9: USA ACCESORIOS QUE NO CUMPLE CON EL CODIGO DE VESTIMENTA | H9: NO | J9: 30249632 | K9: NestleP.5 | L9: =_xlfn.XLOOKUP(Tabla2__2[[#This Row],[CODIGO RUTA]],'DATA INFORME'!I:I,'DATA INFORME'!K:K) -> SI | M9: =IF(Tabla2__2[[#This Row],[MYSTERY EFECTIVO]]="SI",_xlfn.XLOOKUP(Tabla2__2[[#This Row],[PREGUNTA]],ENCUESTA!G:G,ENCUESTA!D:D),"N/A") -> UNIFORME | N9: =IF(Tabla2__2[[#This Row],[MYSTERY EFECTIVO]]="SI",(IF(Tabla2__2[[#This Row],[CANAL]]="TRADICIONAL",_xlfn.XLOOKUP(Tabla2__2[[#This Row],[PREGUNTA]],ENCUESTA!G:G,ENCUESTA!A:A),IF(Tabla2__2[[#This Row],[CANAL]]="ESPECIALIZADO",_xlfn.XLOOKUP(Tabla2__2[[#This Row],[PREGUNTA]],ENCUESTA!G:G,ENCUESTA!B:B),IF(Tabla2__2[[#This Row],[CANAL]]="MODERNO",_xlfn.XLOOKUP(Tabla2__2[[#This Row],[PREGUNTA]],ENCUESTA!G:G,ENCUESTA!C:C))))),0) -> 1.5 | O9: =_xlfn.XLOOKUP(Tabla2__2[[#This Row],[PREGUNTA]],ENCUESTA!G:G,ENCUESTA!H:H) -> NO | P9: =IF(Tabla2__2[[#This Row],[RTA]]=Tabla2__2[[#This Row],[RTA CORRECTA]],Tabla2__2[[#This Row],[TOTAL PUNTAJE]],0) -> 1.5 | Q9: =IF(OR(H9="Dog Chow húmedo",H9="Cat Chow húmedo",H9="Fancy Feast",H9="Felix",H9="Proplan húmedo",H9="One húmedo",H9="Snack Abrazzos",H9="Snak Dentalife",H9="Arenilla Tidy Cat"),N9,0) -> 0
A10: NESTLE PURINA | B10: CARTAGENA | C10: MODERNO | D10: OLIMPICA | E10: 424810 | F10: 424810 - HOMECENTER CARTAGENA | G10: ABORDA AL SHOPPER CON EL VERBATIM Y MANEJA LAS OBJECIONES SEGÚN COMUNICADO ENVIADO. | H10: SI | J10: 30249632 | K10: NestleP.5 | L10: =_xlfn.XLOOKUP(Tabla2__2[[#This Row],[CODIGO RUTA]],'DATA INFORME'!I:I,'DATA INFORME'!K:K) -> SI | M10: =IF(Tabla2__2[[#This Row],[MYSTERY EFECTIVO]]="SI",_xlfn.XLOOKUP(Tabla2__2[[#This Row],[PREGUNTA]],ENCUESTA!G:G,ENCUESTA!D:D),"N/A") -> PORTAFOLIO Y MANEJO DE OBJECIONES | N10: =IF(Tabla2__2[[#This Row],[MYSTERY EFECTIVO]]="SI",(IF(Tabla2__2[[#This Row],[CANAL]]="TRADICIONAL",_xlfn.XLOOKUP(Tabla2__2[[#This Row],[PREGUNTA]],ENCUESTA!G:G,ENCUESTA!A:A),IF(Tabla2__2[[#This Row],[CANAL]]="ESPECIALIZADO",_xlfn.XLOOKUP(Tabla2__2[[#This Row],[PREGUNTA]],ENCUESTA!G:G,ENCUESTA!B:B),IF(Tabla2__2[[#This Row],[CANAL]]="MODERNO",_xlfn.XLOOKUP(Tabla2__2[[#This Row],[PREGUNTA]],ENCUESTA!G:G,ENCUESTA!C:C))))),0) -> 1.5 | O10: =_xlfn.XLOOKUP(Tabla2__2[[#This Row],[PREGUNTA]],ENCUESTA!G:G,ENCUESTA!H:H) -> SI | P10: =IF(Tabla2__2[[#This Row],[RTA]]=Tabla2__2[[#This Row],[RTA CORRECTA]],Tabla2__2[[#This Row],[TOTAL PUNTAJE]],0) -> 1.5 | Q10: =IF(OR(H10="Dog Chow húmedo",H10="Cat Chow húmedo",H10="Fancy Feast",H10="Felix",H10="Proplan húmedo",H10="One húmedo",H10="Snack Abrazzos",H10="Snak Dentalife",H10="Arenilla Tidy Cat"),N10,0) -> 0
A11: NESTLE PURINA | B11: CARTAGENA | C11: MODERNO | D11: OLIMPICA | E11: 424810 | F11: 424810 - HOMECENTER CARTAGENA | G11: (OFRECE EL OBSEQUIO APLICA VIERNES, SABADO Y DOMINGO) Y EXPLICA COMO HACER LA TRANSICIÓN DEL PRODUCTO Y BENEFICIOS? | H11: SI | J11: 30249632 | K11: NestleP.5 | L11: =_xlfn.XLOOKUP(Tabla2__2[[#This Row],[CODIGO RUTA]],'DATA INFORME'!I:I,'DATA INFORME'!K:K) -> SI | M11: =IF(Tabla2__2[[#This Row],[MYSTERY EFECTIVO]]="SI",_xlfn.XLOOKUP(Tabla2__2[[#This Row],[PREGUNTA]],ENCUESTA!G:G,ENCUESTA!D:D),"N/A") -> PORTAFOLIO Y MANEJO DE OBJECIONES | N11: =IF(Tabla2__2[[#This Row],[MYSTERY EFECTIVO]]="SI",(IF(Tabla2__2[[#This Row],[CANAL]]="TRADICIONAL",_xlfn.XLOOKUP(Tabla2__2[[#This Row],[PREGUNTA]],ENCUESTA!G:G,ENCUESTA!A:A),IF(Tabla2__2[[#This Row],[CANAL]]="ESPECIALIZADO",_xlfn.XLOOKUP(Tabla2__2[[#This Row],[PREGUNTA]],ENCUESTA!G:G,ENCUESTA!B:B),IF(Tabla2__2[[#This Row],[CANAL]]="MODERNO",_xlfn.XLOOKUP(Tabla2__2[[#This Row],[PREGUNTA]],ENCUESTA!G:G,ENCUESTA!C:C))))),0) -> 1.5 | O11: =_xlfn.XLOOKUP(Tabla2__2[[#This Row],[PREGUNTA]],ENCUESTA!G:G,ENCUESTA!H:H) -> SI | P11: =IF(Tabla2__2[[#This Row],[RTA]]=Tabla2__2[[#This Row],[RTA CORRECTA]],Tabla2__2[[#This Row],[TOTAL PUNTAJE]],0) -> 1.5 | Q11: =IF(OR(H11="Dog Chow húmedo",H11="Cat Chow húmedo",H11="Fancy Feast",H11="Felix",H11="Proplan húmedo",H11="One húmedo",H11="Snack Abrazzos",H11="Snak Dentalife",H11="Arenilla Tidy Cat"),N11,0) -> 0
A12: NESTLE PURINA | B12: CARTAGENA | C12: MODERNO | D12: OLIMPICA | E12: 424810 | F12: 424810 - HOMECENTER CARTAGENA | G12: SELECCIONE EL CANAL DEL PDV QUE EVALUA | H12: MODERNO | J12: 30249632 | K12: NestleP.5 | L12: =_xlfn.XLOOKUP(Tabla2__2[[#This Row],[CODIGO RUTA]],'DATA INFORME'!I:I,'DATA INFORME'!K:K) -> SI | M12: =IF(Tabla2__2[[#This Row],[MYSTERY EFECTIVO]]="SI",_xlfn.XLOOKUP(Tabla2__2[[#This Row],[PREGUNTA]],ENCUESTA!G:G,ENCUESTA!D:D),"N/A") -> N/A | N12: =IF(Tabla2__2[[#This Row],[MYSTERY EFECTIVO]]="SI",(IF(Tabla2__2[[#This Row],[CANAL]]="TRADICIONAL",_xlfn.XLOOKUP(Tabla2__2[[#This Row],[PREGUNTA]],ENCUESTA!G:G,ENCUESTA!A:A),IF(Tabla2__2[[#This Row],[CANAL]]="ESPECIALIZADO",_xlfn.XLOOKUP(Tabla2__2[[#This Row],[PREGUNTA]],ENCUESTA!G:G,ENCUESTA!B:B),IF(Tabla2__2[[#This Row],[CANAL]]="MODERNO",_xlfn.XLOOKUP(Tabla2__2[[#This Row],[PREGUNTA]],ENCUESTA!G:G,ENCUESTA!C:C))))),0) -> 0 | O12: =_xlfn.XLOOKUP(Tabla2__2[[#This Row],[PREGUNTA]],ENCUESTA!G:G,ENCUESTA!H:H) -> 0 | P12: =IF(Tabla2__2[[#This Row],[RTA]]=Tabla2__2[[#This Row],[RTA CORRECTA]],Tabla2__2[[#This Row],[TOTAL PUNTAJE]],0) -> 0 | Q12: =IF(OR(H12="Dog Chow húmedo",H12="Cat Chow húmedo",H12="Fancy Feast",H12="Felix",H12="Proplan húmedo",H12="One húmedo",H12="Snack Abrazzos",H12="Snak Dentalife",H12="Arenilla Tidy Cat"),N12,0) -> 0
A13: NESTLE PURINA | B13: CARTAGENA | C13: MODERNO | D13: OLIMPICA | E13: 424810 | F13: 424810 - HOMECENTER CARTAGENA | G13: CM - OFRECE DOG CHOW O CAT CHOW COMO PRIMERA OPCION | H13: SI | J13: 30249632 | K13: NestleP.5 | L13: =_xlfn.XLOOKUP(Tabla2__2[[#This Row],[CODIGO RUTA]],'DATA INFORME'!I:I,'DATA INFORME'!K:K) -> SI | M13: =IF(Tabla2__2[[#This Row],[MYSTERY EFECTIVO]]="SI",_xlfn.XLOOKUP(Tabla2__2[[#This Row],[PREGUNTA]],ENCUESTA!G:G,ENCUESTA!D:D),"N/A") -> PORTAFOLIO Y MANEJO DE OBJECIONES | N13: =IF(Tabla2__2[[#This Row],[MYSTERY EFECTIVO]]="SI",(IF(Tabla2__2[[#This Row],[CANAL]]="TRADICIONAL",_xlfn.XLOOKUP(Tabla2__2[[#This Row],[PREGUNTA]],ENCUESTA!G:G,ENCUESTA!A:A),IF(Tabla2__2[[#This Row],[CANAL]]="ESPECIALIZADO",_xlfn.XLOOKUP(Tabla2__2[[#This Row],[PREGUNTA]],ENCUESTA!G:G,ENCUESTA!B:B),IF(Tabla2__2[[#This Row],[CANAL]]="MODERNO",_xlfn.XLOOKUP(Tabla2__2[[#This Row],[PREGUNTA]],ENCUESTA!G:G,ENCUESTA!C:C))))),0) -> 6 | O13: =_xlfn.XLOOKUP(Tabla2__2[[#This Row],[PREGUNTA]],ENCUESTA!G:G,ENCUESTA!H:H) -> SI | P13: =IF(Tabla2__2[[#This Row],[RTA]]=Tabla2__2[[#This Row],[RTA CORRECTA]],Tabla2__2[[#This Row],[TOTAL PUNTAJE]],0) -> 6 | Q13: =IF(OR(H13="Dog Chow húmedo",H13="Cat Chow húmedo",H13="Fancy Feast",H13="Felix",H13="Proplan húmedo",H13="One húmedo",H13="Snack Abrazzos",H13="Snak Dentalife",H13="Arenilla Tidy Cat"),N13,0) -> 0
... A147: NESTLE PURINA | B147: BARRANQUILLA | C147: ESPECIALIZADO | D147: OLIMPICA | E147: 421609 | F147: 421609 - LA FAVORITA DE LA 14 | G147: DESEA AÑADIR ALGUNA OBSERVACION Y/O NOVEDAD DEL MYSTERY REALIZADO? | H147: NO | J147: 30281524 | K147: NestleP.5 | L147: =_xlfn.XLOOKUP(Tabla2__2[[#This Row],[CODIGO RUTA]],'DATA INFORME'!I:I,'DATA INFORME'!K:K) -> SI | M147: =IF(Tabla2__2[[#This Row],[MYSTERY EFECTIVO]]="SI",_xlfn.XLOOKUP(Tabla2__2[[#This Row],[PREGUNTA]],ENCUESTA!G:G,ENCUESTA!D:D),"N/A") -> N/A | N147: =IF(Tabla2__2[[#This Row],[MYSTERY EFECTIVO]]="SI",(IF(Tabla2__2[[#This Row],[CANAL]]="TRADICIONAL",_xlfn.XLOOKUP(Tabla2__2[[#This Row],[PREGUNTA]],ENCUESTA!G:G,ENCUESTA!A:A),IF(Tabla2__2[[#This Row],[CANAL]]="ESPECIALIZADO",_xlfn.XLOOKUP(Tabla2__2[[#This Row],[PREGUNTA]],ENCUESTA!G:G,ENCUESTA!B:B),IF(Tabla2__2[[#This Row],[CANAL]]="MODERNO",_xlfn.XLOOKUP(Tabla2__2[[#This Row],[PREGUNTA]],ENCUESTA!G:G,ENCUESTA!C:C))))),0) -> 0 | O147: =_xlfn.XLOOKUP(Tabla2__2[[#This Row],[PREGUNTA]],ENCUESTA!G:G,ENCUESTA!H:H) -> 0 | P147: =IF(Tabla2__2[[#This Row],[RTA]]=Tabla2__2[[#This Row],[RTA CORRECTA]],Tabla2__2[[#This Row],[TOTAL PUNTAJE]],0) -> 0 | Q147: =IF(OR(H147="Dog Chow húmedo",H147="Cat Chow húmedo",H147="Fancy Feast",H147="Felix",H147="Proplan húmedo",H147="One húmedo",H147="Snack Abrazzos",H147="Snak Dentalife",H147="Arenilla Tidy Cat"),N147,0) -> 0

Sheet Panel
A1: CANAL | B1: CIUDAD | C1: CODIGO PDV | D1: NOMBRE COMERCIAL | E1: Objetivo Mystery | F1: #PDV Objetivos | G1: #PDV Ejecutados | H1: # Visitas | I1: Mystery Ejecutado
A2: =_xlfn.XLOOKUP(Tabla1[[#This Row],[CODIGO PDV]],Export!H:H,Export!D:D,0) -> ESPECIALIZADO | B2: BARRANQUILLA | C2: 421609 | D2: 421609 - LA FAVORITA DE LA 14 | E2: 1 | F2: 1 | G2: =IF(COUNTIFS(Export!I:I,Tabla1[[#This Row],[CODIGO PDV]])>0,1,0) -> 1 | H2: =COUNTIFS('DATA INFORME'!D:D,Tabla1[[#This Row],[CODIGO PDV]]) -> 1 | I2: =COUNTIFS('DATA INFORME'!D:D,Tabla1[[#This Row],[CODIGO PDV]],'DATA INFORME'!K:K,"SI") -> 1
A3: =_xlfn.XLOOKUP(Tabla1[[#This Row],[CODIGO PDV]],Export!H:H,Export!D:D,0) -> ESPECIALIZADO | B3: BOGOTA | C3: 424858 | D3: 424858 - AGROCAMPO S.A.S. | E3: 1 | F3: 1 | G3: =IF(COUNTIFS(Export!I:I,Tabla1[[#This Row],[CODIGO PDV]])>0,1,0) -> 1 | H3: =COUNTIFS('DATA INFORME'!D:D,Tabla1[[#This Row],[CODIGO PDV]]) -> 1 | I3: =COUNTIFS('DATA INFORME'!D:D,Tabla1[[#This Row],[CODIGO PDV]],'DATA INFORME'!K:K,"SI") -> 1
A4: =_xlfn.XLOOKUP(Tabla1[[#This Row],[CODIGO PDV]],Export!H:H,Export!D:D,0) -> TRADICIONAL | B4: CALI | C4: 66552 | D4: LA CASA DE LOS TENDEROS | E4: 1 | F4: 1 | G4: =IF(COUNTIFS(Export!I:I,Tabla1[[#This Row],[CODIGO PDV]])>0,1,0) -> 1 | H4: =COUNTIFS('DATA INFORME'!D:D,Tabla1[[#This Row],[CODIGO PDV]]) -> 1 | I4: =COUNTIFS('DATA INFORME'!D:D,Tabla1[[#This Row],[CODIGO PDV]],'DATA INFORME'!K:K,"SI") -> 1
A5: =_xlfn.XLOOKUP(Tabla1[[#This Row],[CODIGO PDV]],Export!H:H,Export!D:D,0) -> ESPECIALIZADO | B5: CALI | C5: 424808 | D5: 424808 - HOLANDA NORTE | E5: 1 | F5: 1 | G5: =IF(COUNTIFS(Export!I:I,Tabla1[[#This Row],[CODIGO PDV]])>0,1,0) -> 1 | H5: =COUNTIFS('DATA INFORME'!D:D,Tabla1[[#This Row],[CODIGO PDV]]) -> 1 | I5: =COUNTIFS('DATA INFORME'!D:D,Tabla1[[#This Row],[CODIGO PDV]],'DATA INFORME'!K:K,"SI") -> 1
A6: =_xlfn.XLOOKUP(Tabla1[[#This Row],[CODIGO PDV]],Export!H:H,Export!D:D,0) -> MODERNO | B6: CARTAGENA | C6: 424810 | D6: 424810 - HOMECENTER CARTAGENA | E6: 1 | F6: 1 | G6: =IF(COUNTIFS(Export!I:I,Tabla1[[#This Row],[CODIGO PDV]])>0,1,0) -> 1 | H6: =COUNTIFS('DATA INFORME'!D:D,Tabla1[[#This Row],[CODIGO PDV]]) -> 1 | I6: =COUNTIFS('DATA INFORME'!D:D,Tabla1[[#This Row],[CODIGO PDV]],'DATA INFORME'!K:K,"SI") -> 1

Sheet DATA INFORME
A1: ACTIVIDAD | B1: CIUDAD | C1: CADENA | D1: CODIGO PDV | E1: NOMBRE COMERCIAL | F1: CONSECUTIVO ENCUESTA | G1: NOMBRE ENCUESTA | H1: FECHA VISITA | I1: CODIGO RUTA | J1: USUARIO | K1: SE LOGRA REALIZAR EL MYSTERY? | L1: ¿CUMPLE HORARIO DE ENTRADA O SALIDA DE LA TIENDA? | M1: CUENTA CON PANTALON DEL UNIFORME SEGÚN EL CARGO (NEGRO / ROJO / TURQUESA / JEAN) | N1: CUENTA CON CAMISA DEL UNIFORME Y LOGOS SEGÚN EL CARGO (NEGRA / GRIS / ROJA / TURQUESA) (Es permitido usar debajo de la camisa buso manga larga Negro) | O1: CUENTA CON CALZADO DE ACUERDO AL UNIFORME | P1: POSEE ALGUNA PRENDA ENCIMA DEL UNIFORME NO AUTORIZADA POR LA MARCA (Unicamente esta permitido chaleco de Sodimac y Easy) | Q1: EL UNIFORME Y ZAPATOS SE ENCUENTRAN LIMPIOS Y EN BUEN ESTADO | R1: SU CABELLO LUCE LIMPIO, ORGANIZADO O RECOGIDO | S1: PRESENTA EXCESO DE MAQUILLAJE QUE NO CUMPLE CON EL CODIGO DE VESTIMENTA | T1: TIENE TATUAJES O PIERCINGS VISIBLES QUE NO CUMPLE CON EL CODIGO DE VESTIMENTA | U1: TIENE UÑAS LLAMATIVAS Y/O LARGAS QUE NO CUMPLE CON EL CODIGO DE VESTIMENTA | V1: USA ACCESORIOS QUE NO CUMPLE CON EL CODIGO DE VESTIMENTA | W1: SE PRODUCE ABORDAJE PROACTIVO (antes de 1 min) | X1: INDAGA SOBRE LAS NECESIDADES DEL CLIENTE CON RESPECTO A SU CONSUMO HABITUAL " MARCAS COMPETENCIA O PROPIAS" - OBJECIÓN DE PRECIOS. | Y1: OFRECE PURINA ONE: (APLICA SOLO EN CANAL MODERNO, CADENAS, SI EL PRODUCTO ESTA EN EL PDV) | Z1: SELECCIONE EL CANAL DEL PDV QUE EVALUA | AA1: CE - LO PRIMERO QUE OFRECE EL ASESOR ES LA MARCA PRO PLAN? (ENFOQUE EN GATOS) | AB1: CE - EL ASESOR COMUNICA LOS BENEFICIOS Y CARACTERISTICAS DE LA MARCA PRO PLAN? (ENFOQUE EN GATOS) | AC1: CE - LUEGO DE REALIZAR LA OBJECIÓN DE PRECIO, OFRECE LA MARCA EXCELLENT? (ENFOQUE EN GATOS) | AD1: CE - EL ASESOR COMUNICA QUE LA MARCA EXCELLENT ESTA DENTRO DE LA CATEGORIA SUPERPREMIUM PERO A UN COSTO MAS ACCESIBLE. | AE1: CE - EL ASESOR COMUNICA LOS BENEFICIOS Y CARACTERISTICAS DEL PRODUCTO EXCELLENT? (ENFOQUE EN GATOS) | AF1: CE - OFRECE PRODUCTO HUMEDO Y ENFATIZA EN LOS PACKS POR TEMAS DE PRECIO? (GATOS Y PERROS) | AG1: INDIQUE QUE TIPO DE OBJECION / DUDA MANIFESTÓ | AH1: RESUELVE LA OBJECION SATISFACTORIAMENTE? | AI1: SE ENCUENTRA LIMPIA EL AREA DE DEMOSTRACION "REVISION DE PRODUCTO SIN POLVO Y EN OPTIMAS CONDICIONES" | AJ1: REALIZA CIERRE DE VENTA | AK1: CONSIDERO QUE INDEPENDIENTEMENTE DEL SPEECH, LA LABOR DE VENTA ES BUENA | AL1: DESEA AÑADIR ALGUNA OBSERVACION Y/O NOVEDAD DEL MYSTERY REALIZADO? | AM1: CT - OFRECIO ALGUN PRODUCTO DEL PORTAFOLIO PURINA DE PRODUCTOS SECOS COMUNICANDO LOS BENEFICIOS DEL PRODUCTO (DOG CHOW, CAT CHOW, ALPO, GATSY, FELIX O NINGUNO) | AN1: CT - OFRECIO ALGUN PRODUCTO PORTAFOLIO PURINA DE PRODUCTOS HUMEDOS COMUNICANDO LOS BENEFICIOS DEL PRODUCTO (Dog chow húmedo, Cat chow húmedo, Fancy Feast, Felix, Proplan Húmedo, One Húmedo, Snacks (Abrazzos, Dentalife), Arenilla (Tidy Cat) | AO1: CT - MENCIONA ALGUNA DE LAS INNOVACIONES QUE TENEMOS EN EL CANAL (CAT 200GR FELIX TRIPLE DELI Y MEGA MIX DE WET Y DOG CHOW ALTA PROTEINA DE 350GR 475GR ) | AP1: MENCIONA QUE LOS RESULTADOS SON VISIBLES EN 28 DIAS? | AQ1: MENCIONA QUE TIENE CARNE DE VERDAD COMO INGREDIENTE NO.1 E INGREDIENTES NATURALES Y FUNCIONALES? | AR1: MENCIONA QUE PURINA ONE CUENTA CON ALIMENTO HUMEDO Y MENCIONA LAS 3 VARIADADES QUE TIENE ( SUPER FOODS, SUPER NUTRIENTES Y MULTI PROTEINAS); APLICA TANTO PARA PERRO COMO PARA GATO? | AS1: ABORDA AL SHOPPER CON EL VERBATIM Y MANEJA LAS OBJECIONES SEGÚN COMUNICADO ENVIADO. | AT1: MENCIONA LA REDUCCION DE PRECIOS QUE TENEMOS DESDE EL MES DE DICIEMBRE (la unica referencia que no aplica es Gato adult carne 500gr) | AU1: (OFRECE EL OBSEQUIO APLICA VIERNES, SABADO Y DOMINGO) Y EXPLICA COMO HACER LA TRANSICIÓN DEL PRODUCTO Y BENEFICIOS? | AV1: CM - OFRECE DOG CHOW O CAT CHOW COMO PRIMERA OPCION | AW1: CM - OFRECE ALIMENTO HUMEDO DE DOG CHOW Y FELIX | AX1: CM - CONOCE LAS DINAMICAS COMERCIALES DEL PDV
A2: NESTLE PURINA | B2: BARRANQUILLA | C2: OLIMPICA | D2: 421609 | E2: 421609 - LA FAVORITA DE LA 14 | F2: 1 | G2: GESTION IMPULSO - FEBRERO 2026 | H2: 46079.666 | I2: 30281524 | J2: NestleP.5 | K2: SI | L2: SI | M2: SI | N2: SI | O2: SI | P2: NO | Q2: SI | R2: SI | S2: NO | T2: NO | U2: NO | V2: NO | W2: SI | X2: SI | Y2: SI | Z2: ESPECIALIZADO | AA2: SI | AB2: SI | AC2: SI | AD2: SI | AE2: SI | AF2: SI | AG2: NO TIENE DINERO | AH2: SI | AI2: SI | AJ2: SI | AK2: SI | AL2: NO | AP2: SI | AQ2: SI | AR2: SI | AS2: SI | AT2: SI | AU2: SI
A3: NESTLE PURINA | B3: BOGOTA | C3: JUMBO | D3: 424858 | E3: 424858 - AGROCAMPO S.A.S. | F3: 1 | G3: GESTION IMPULSO - FEBRERO 2026 | H3: 46065 | I3: 30182843 | J3: NestleP.1 | K3: SI | L3: SI | M3: SI | N3: SI | O3: SI | P3: NO | Q3: SI | R3: SI | S3: NO | T3: NO | U3: NO | V3: NO | W3: SI | X3: SI | Y3: SI | Z3: ESPECIALIZADO | AA3: SI | AB3: SI | AC3: SI | AD3: SI | AE3: SI | AF3: NO | AG3: NO TIENE DINERO | AH3: SI | AI3: SI | AJ3: SI | AK3: SI | AL3: NO
A4: NESTLE PURINA | B4: CALI | C4: MERCA Z | D4: 66552 | E4: LA CASA DE LOS TENDEROS | F4: 1 | G4: GESTION IMPULSO - FEBRERO 2026 | H4: 46066 | I4: 30189338 | J4: PREMISEUNP 51 | K4: SI | L4: SI | M4: SI | N4: SI | O4: SI | P4: NO | Q4: SI | R4: SI | S4: NO | T4: NO | U4: NO | V4: NO | W4: SI | X4: SI | Y4: SI | Z4: TRADICIONAL | AG4: NO LE INTERESA EL PRODUCTO | AH4: SI | AI4: SI | AJ4: SI | AK4: SI | AL4: NO | AM4: SI | AN4: NO | AO4: SI
A5: NESTLE PURINA | B5: CALI | C5: MERCA Z | D5: 424808 | E5: 424808 - HOLANDA NORTE | F5: 1 | G5: GESTION IMPULSO - FEBRERO 2026 | H5: 46074 | I5: 30231329 | J5: PREMISEUNP 51 | K5: SI | L5: SI | M5: SI | N5: SI | O5: SI | P5: NO | Q5: SI | R5: SI | S5: NO | T5: NO | U5: NO | V5: NO | W5: SI | X5: SI | Y5: SI | Z5: ESPECIALIZADO | AA5: SI | AB5: SI | AC5: SI | AD5: SI | AE5: SI | AF5: SI | AG5: NO TIENE DINERO | AH5: SI | AI5: SI | AJ5: SI | AK5: SI | AL5: NO
A6: NESTLE PURINA | B6: CARTAGENA | C6: OLIMPICA | D6: 424810 | E6: 424810 - HOMECENTER CARTAGENA | F6: 1 | G6: GESTION IMPULSO - FEBRERO 2026 | H6: 46077 | I6: 30249632 | J6: NestleP.5 | K6: SI | L6: SI | M6: SI | N6: SI | O6: SI | P6: NO | Q6: SI | R6: SI | S6: NO | T6: NO | U6: NO | V6: NO | W6: SI | X6: SI | Y6: NO | Z6: MODERNO | AG6: FALTA DE PRODUCTO | AH6: SI | AI6: SI | AJ6: SI | AK6: SI | AL6: NO | AP6: SI | AQ6: SI | AR6: SI | AS6: SI | AT6: SI | AU6: SI | AV6: SI | AW6: SI | AX6: SI

Sheet Export
A1: ACTIVIDAD | B1: REGIONAL | C1: CIUDAD | D1: CANAL | E1: CADENA | F1: SUBCADENA | G1: ZONA | H1: RV | I1: CODIGO PDV | J1: NOMBRE COMERCIAL | K1: CODIGO EAN | L1: TIPO PUNTO VENTA | M1: CONSECUTIVO ENCUESTA | N1: NOMBRE ENCUESTA | O1: PREGUNTA | P1: RESPUESTA | Q1: CODIGO FOTO | R1: OBSERVACION | S1: FECHA VISITA | T1: FECHA INICIO VISITA | U1: FECHA CREACIÓN RESPUESTA | V1: CODIGO RUTA | W1: CLIENTE | X1: CODIGO EXHIBICION | Y1: NOMBRE EXHIBICION | Z1: NOMBRE USUARIO | AA1: USUARIO | AB1: NOMBRE SUPERVISOR | AC1: USUARIO SUPERVISOR
A2: NESTLE PURINA | B2: CENTRO | C2: BOGOTA | D2: ESPECIALIZADO | E2: JUMBO | F2: JUMBO TITAN | G2: BOGOTA | H2: =VALUE(Tabla2[[#This Row],[CODIGO PDV]]) -> 424858 | I2: 424858 | J2: 424858 - AGROCAMPO S.A.S. | K2: 0 | L2: JUMBO TITAN | M2: 1 | N2: GESTION IMPULSO - FEBRERO 2026 | O2: SE LOGRA REALIZAR EL MYSTERY? | P2: SI | S2: 12/02/2026 00:00:00 | T2: 12/02/2026 17:22:47 | U2: 12/02/2026 17:31:58 | V2: 30182843 | W2: PRODUCTIVIDAD | Z2: User 1 | AA2: NestleP.1 | AB2: CAMILO MONTAÑO RESTREPO | AC2: camilo.montano
A3: NESTLE PURINA | B3: CENTRO | C3: BOGOTA | D3: ESPECIALIZADO | E3: JUMBO | F3: JUMBO TITAN | G3: BOGOTA | H3: =VALUE(Tabla2[[#This Row],[CODIGO PDV]]) -> 424858 | I3: 424858 | J3: 424858 - AGROCAMPO S.A.S. | K3: 0 | L3: JUMBO TITAN | M3: 1 | N3: GESTION IMPULSO - FEBRERO 2026 | O3: ¿CUMPLE HORARIO DE ENTRADA O SALIDA DE LA TIENDA? | P3: SI | S3: 12/02/2026 00:00:00 | T3: 12/02/2026 17:22:47 | U3: 12/02/2026 17:31:58 | V3: 30182843 | W3: PRODUCTIVIDAD | Z3: User 1 | AA3: NestleP.1 | AB3: CAMILO MONTAÑO RESTREPO | AC3: camilo.montano
A4: NESTLE PURINA | B4: CENTRO | C4: BOGOTA | D4: ESPECIALIZADO | E4: JUMBO | F4: JUMBO TITAN | G4: BOGOTA | H4: =VALUE(Tabla2[[#This Row],[CODIGO PDV]]) -> 424858 | I4: 424858 | J4: 424858 - AGROCAMPO S.A.S. | K4: 0 | L4: JUMBO TITAN | M4: 1 | N4: GESTION IMPULSO - FEBRERO 2026 | O4: CUENTA CON PANTALON DEL UNIFORME SEGÚN EL CARGO (NEGRO / ROJO / TURQUESA / JEAN) | P4: SI | S4: 12/02/2026 00:00:00 | T4: 12/02/2026 17:22:47 | U4: 12/02/2026 17:31:58 | V4: 30182843 | W4: PRODUCTIVIDAD | Z4: User 1 | AA4: NestleP.1 | AB4: CAMILO MONTAÑO RESTREPO | AC4: camilo.montano
A5: NESTLE PURINA | B5: CENTRO | C5: BOGOTA | D5: ESPECIALIZADO | E5: JUMBO | F5: JUMBO TITAN | G5: BOGOTA | H5: =VALUE(Tabla2[[#This Row],[CODIGO PDV]]) -> 424858 | I5: 424858 | J5: 424858 - AGROCAMPO S.A.S. | K5: 0 | L5: JUMBO TITAN | M5: 1 | N5: GESTION IMPULSO - FEBRERO 2026 | O5: CUENTA CON CAMISA DEL UNIFORME Y LOGOS SEGÚN EL CARGO (NEGRA / GRIS / ROJA / TURQUESA) (Es permitido usar debajo de la camisa buso manga larga Negro) | P5: SI | S5: 12/02/2026 00:00:00 | T5: 12/02/2026 17:22:47 | U5: 12/02/2026 17:31:58 | V5: 30182843 | W5: PRODUCTIVIDAD | Z5: User 1 | AA5: NestleP.1 | AB5: CAMILO MONTAÑO RESTREPO | AC5: camilo.montano
A6: NESTLE PURINA | B6: CENTRO | C6: BOGOTA | D6: ESPECIALIZADO | E6: JUMBO | F6: JUMBO TITAN | G6: BOGOTA | H6: =VALUE(Tabla2[[#This Row],[CODIGO PDV]]) -> 424858 | I6: 424858 | J6: 424858 - AGROCAMPO S.A.S. | K6: 0 | L6: JUMBO TITAN | M6: 1 | N6: GESTION IMPULSO - FEBRERO 2026 | O6: CUENTA CON CALZADO DE ACUERDO AL UNIFORME | P6: SI | S6: 12/02/2026 00:00:00 | T6: 12/02/2026 17:22:47 | U6: 12/02/2026 17:31:58 | V6: 30182843 | W6: PRODUCTIVIDAD | Z6: User 1 | AA6: NestleP.1 | AB6: CAMILO MONTAÑO RESTREPO | AC6: camilo.montano
A7: NESTLE PURINA | B7: CENTRO | C7: BOGOTA | D7: ESPECIALIZADO | E7: JUMBO | F7: JUMBO TITAN | G7: BOGOTA | H7: =VALUE(Tabla2[[#This Row],[CODIGO PDV]]) -> 424858 | I7: 424858 | J7: 424858 - AGROCAMPO S.A.S. | K7: 0 | L7: JUMBO TITAN | M7: 1 | N7: GESTION IMPULSO - FEBRERO 2026 | O7: POSEE ALGUNA PRENDA ENCIMA DEL UNIFORME NO AUTORIZADA POR LA MARCA (Unicamente esta permitido chaleco de Sodimac y Easy) | P7: NO | S7: 12/02/2026 00:00:00 | T7: 12/02/2026 17:22:47 | U7: 12/02/2026 17:31:58 | V7: 30182843 | W7: PRODUCTIVIDAD | Z7: User 1 | AA7: NestleP.1 | AB7: CAMILO MONTAÑO RESTREPO | AC7: camilo.montano
A8: NESTLE PURINA | B8: CENTRO | C8: BOGOTA | D8: ESPECIALIZADO | E8: JUMBO | F8: JUMBO TITAN | G8: BOGOTA | H8: =VALUE(Tabla2[[#This Row],[CODIGO PDV]]) -> 424858 | I8: 424858 | J8: 424858 - AGROCAMPO S.A.S. | K8: 0 | L8: JUMBO TITAN | M8: 1 | N8: GESTION IMPULSO - FEBRERO 2026 | O8: EL UNIFORME Y ZAPATOS SE ENCUENTRAN LIMPIOS Y EN BUEN ESTADO | P8: SI | S8: 12/02/2026 00:00:00 | T8: 12/02/2026 17:22:47 | U8: 12/02/2026 17:31:58 | V8: 30182843 | W8: PRODUCTIVIDAD | Z8: User 1 | AA8: NestleP.1 | AB8: CAMILO MONTAÑO RESTREPO | AC8: camilo.montano
A9: NESTLE PURINA | B9: CENTRO | C9: BOGOTA | D9: ESPECIALIZADO | E9: JUMBO | F9: JUMBO TITAN | G9: BOGOTA | H9: =VALUE(Tabla2[[#This Row],[CODIGO PDV]]) -> 424858 | I9: 424858 | J9: 424858 - AGROCAMPO S.A.S. | K9: 0 | L9: JUMBO TITAN | M9: 1 | N9: GESTION IMPULSO - FEBRERO 2026 | O9: SU CABELLO LUCE LIMPIO, ORGANIZADO O RECOGIDO | P9: SI | S9: 12/02/2026 00:00:00 | T9: 12/02/2026 17:22:47 | U9: 12/02/2026 17:31:58 | V9: 30182843 | W9: PRODUCTIVIDAD | Z9: User 1 | AA9: NestleP.1 | AB9: CAMILO MONTAÑO RESTREPO | AC9: camilo.montano
A10: NESTLE PURINA | B10: CENTRO | C10: BOGOTA | D10: ESPECIALIZADO | E10: JUMBO | F10: JUMBO TITAN | G10: BOGOTA | H10: =VALUE(Tabla2[[#This Row],[CODIGO PDV]]) -> 424858 | I10: 424858 | J10: 424858 - AGROCAMPO S.A.S. | K10: 0 | L10: JUMBO TITAN | M10: 1 | N10: GESTION IMPULSO - FEBRERO 2026 | O10: PRESENTA EXCESO DE MAQUILLAJE QUE NO CUMPLE CON EL CODIGO DE VESTIMENTA | P10: NO | S10: 12/02/2026 00:00:00 | T10: 12/02/2026 17:22:47 | U10: 12/02/2026 17:31:58 | V10: 30182843 | W10: PRODUCTIVIDAD | Z10: User 1 | AA10: NestleP.1 | AB10: CAMILO MONTAÑO RESTREPO | AC10: camilo.montano
A11: NESTLE PURINA | B11: CENTRO | C11: BOGOTA | D11: ESPECIALIZADO | E11: JUMBO | F11: JUMBO TITAN | G11: BOGOTA | H11: =VALUE(Tabla2[[#This Row],[CODIGO PDV]]) -> 424858 | I11: 424858 | J11: 424858 - AGROCAMPO S.A.S. | K11: 0 | L11: JUMBO TITAN | M11: 1 | N11: GESTION IMPULSO - FEBRERO 2026 | O11: TIENE TATUAJES O PIERCINGS VISIBLES QUE NO CUMPLE CON EL CODIGO DE VESTIMENTA | P11: NO | S11: 12/02/2026 00:00:00 | T11: 12/02/2026 17:22:47 | U11: 12/02/2026 17:31:58 | V11: 30182843 | W11: PRODUCTIVIDAD | Z11: User 1 | AA11: NestleP.1 | AB11: CAMILO MONTAÑO RESTREPO | AC11: camilo.montano
A12: NESTLE PURINA | B12: CENTRO | C12: BOGOTA | D12: ESPECIALIZADO | E12: JUMBO | F12: JUMBO TITAN | G12: BOGOTA | H12: =VALUE(Tabla2[[#This Row],[CODIGO PDV]]) -> 424858 | I12: 424858 | J12: 424858 - AGROCAMPO S.A.S. | K12: 0 | L12: JUMBO TITAN | M12: 1 | N12: GESTION IMPULSO - FEBRERO 2026 | O12: TIENE UÑAS LLAMATIVAS Y/O LARGAS QUE NO CUMPLE CON EL CODIGO DE VESTIMENTA | P12: NO | S12: 12/02/2026 00:00:00 | T12: 12/02/2026 17:22:47 | U12: 12/02/2026 17:31:58 | V12: 30182843 | W12: PRODUCTIVIDAD | Z12: User 1 | AA12: NestleP.1 | AB12: CAMILO MONTAÑO RESTREPO | AC12: camilo.montano
A13: NESTLE PURINA | B13: CENTRO | C13: BOGOTA | D13: ESPECIALIZADO | E13: JUMBO | F13: JUMBO TITAN | G13: BOGOTA | H13: =VALUE(Tabla2[[#This Row],[CODIGO PDV]]) -> 424858 | I13: 424858 | J13: 424858 - AGROCAMPO S.A.S. | K13: 0 | L13: JUMBO TITAN | M13: 1 | N13: GESTION IMPULSO - FEBRERO 2026 | O13: USA ACCESORIOS QUE NO CUMPLE CON EL CODIGO DE VESTIMENTA | P13: NO | S13: 12/02/2026 00:00:00 | T13: 12/02/2026 17:22:47 | U13: 12/02/2026 17:31:58 | V13: 30182843 | W13: PRODUCTIVIDAD | Z13: User 1 | AA13: NestleP.1 | AB13: CAMILO MONTAÑO RESTREPO | AC13: camilo.montano
... A147: NESTLE PURINA | B147: COSTA | C147: BARRANQUILLA | D147: ESPECIALIZADO | E147: OLIMPICA | F147: OLIMPICA | G147: COSTA | H147: =VALUE(Tabla2[[#This Row],[CODIGO PDV]]) -> 421609 | I147: 421609 | J147: 421609 - LA FAVORITA DE LA 14 | K147: 0 | L147: STO 039 CHIQUINQUIRA | M147: 1 | N147: GESTION IMPULSO - FEBRERO 2026 | O147: DESEA AÑADIR ALGUNA OBSERVACION Y/O NOVEDAD DEL MYSTERY REALIZADO? | P147: NO | S147: 26/02/2026 15:59:17 | T147: 26/02/2026 15:59:22 | U147: 26/02/2026 16:07:59 | V147: 30281524 | W147: PRODUCTIVIDAD | Z147: User 5 | AA147: NestleP.5 | AB147: CAMILO MONTAÑO RESTREPO | AC147: camilo.montano

Sheet ENCUESTA
A1: TRADICIONAL | B1: ESPECIALIZADO | C1: MODERNO | D1: CLUSTER | E1: PESO | F1: TIPO | G1: PREGUNTA | H1: RTA CORRECTA | J1: CLUSTER | K1: PESO CLUSTER
A2: 0 | B2: 0 | C2: 0 | D2: N/A | E2: 0 | F2: UNICA | G2: SE LOGRA REALIZAR EL MYSTERY? | J2: HORARIO | K2: 0.2
A3: 20 | B3: 20 | C3: 20 | D3: HORARIO | E3: 20 | F3: UNICA | G3: ¿CUMPLE HORARIO DE ENTRADA O SALIDA DE LA TIENDA? | H3: SI | J3: UNIFORME | K3: 0.15
A4: =15/10 -> 1.5 | B4: =15/10 -> 1.5 | C4: =15/10 -> 1.5 | D4: UNIFORME | E4: =15/10 -> 1.5 | F4: UNICA | G4: CUENTA CON PANTALON DEL UNIFORME SEGÚN EL CARGO (NEGRO / ROJO / TURQUESA / JEAN) | H4: SI | J4: ABORDAJE | K4: 0.2
A5: =15/10 -> 1.5 | B5: =15/10 -> 1.5 | C5: =15/10 -> 1.5 | D5: UNIFORME | E5: =15/10 -> 1.5 | F5: UNICA | G5: CUENTA CON CAMISA DEL UNIFORME Y LOGOS SEGÚN EL CARGO (NEGRA / GRIS / ROJA / TURQUESA) (Es permitido usar debajo de la camisa buso manga larga Negro) | H5: SI | J5: PORTAFOLIO Y MANEJO DE OBJECIONES | K5: 0.3
A6: =15/10 -> 1.5 | B6: =15/10 -> 1.5 | C6: =15/10 -> 1.5 | D6: UNIFORME | E6: =15/10 -> 1.5 | F6: UNICA | G6: CUENTA CON CALZADO DE ACUERDO AL UNIFORME | H6: SI | J6: LABOR DE VENTA | K6: 0.15
A7: =15/10 -> 1.5 | B7: =15/10 -> 1.5 | C7: =15/10 -> 1.5 | D7: UNIFORME | E7: =15/10 -> 1.5 | F7: UNICA | G7: POSEE ALGUNA PRENDA ENCIMA DEL UNIFORME NO AUTORIZADA POR LA MARCA (Unicamente esta permitido chaleco de Sodimac y Easy) | H7: NO | J7: TOTAL GENERAL | K7: =SUM(K2:K6) -> 1
A8: =15/10 -> 1.5 | B8: =15/10 -> 1.5 | C8: =15/10 -> 1.5 | D8: UNIFORME | E8: =15/10 -> 1.5 | F8: UNICA | G8: EL UNIFORME Y ZAPATOS SE ENCUENTRAN LIMPIOS Y EN BUEN ESTADO | H8: SI
A9: =15/10 -> 1.5 | B9: =15/10 -> 1.5 | C9: =15/10 -> 1.5 | D9: UNIFORME | E9: =15/10 -> 1.5 | F9: UNICA | G9: SU CABELLO LUCE LIMPIO, ORGANIZADO O RECOGIDO | H9: SI
A10: =15/10 -> 1.5 | B10: =15/10 -> 1.5 | C10: =15/10 -> 1.5 | D10: UNIFORME | E10: =15/10 -> 1.5 | F10: UNICA | G10: PRESENTA EXCESO DE MAQUILLAJE QUE NO CUMPLE CON EL CODIGO DE VESTIMENTA | H10: NO
A11: =15/10 -> 1.5 | B11: =15/10 -> 1.5 | C11: =15/10 -> 1.5 | D11: UNIFORME | E11: =15/10 -> 1.5 | F11: UNICA | G11: TIENE TATUAJES O PIERCINGS VISIBLES QUE NO CUMPLE CON EL CODIGO DE VESTIMENTA | H11: NO
A12: =15/10 -> 1.5 | B12: =15/10 -> 1.5 | C12: =15/10 -> 1.5 | D12: UNIFORME | E12: =15/10 -> 1.5 | F12: UNICA | G12: TIENE UÑAS LLAMATIVAS Y/O LARGAS QUE NO CUMPLE CON EL CODIGO DE VESTIMENTA | H12: NO
A13: =15/10 -> 1.5 | B13: =15/10 -> 1.5 | C13: =15/10 -> 1.5 | D13: UNIFORME | E13: =15/10 -> 1.5 | F13: UNICA | G13: USA ACCESORIOS QUE NO CUMPLE CON EL CODIGO DE VESTIMENTA | H13: NO
A14: 20 | B14: 20 | C14: 20 | D14: ABORDAJE | E14: 20 | F14: UNICA | G14: SE PRODUCE ABORDAJE PROACTIVO (antes de 1 min) | H14: SI
A15: 6 | B15: 6 | C15: =30/20 -> 1.5 | D15: PORTAFOLIO Y MANEJO DE OBJECIONES | E15: =30/20 -> 1.5 | F15: UNICA | G15: INDAGA SOBRE LAS NECESIDADES DEL CLIENTE CON RESPECTO A SU CONSUMO HABITUAL " MARCAS COMPETENCIA O PROPIAS" - OBJECIÓN DE PRECIOS. | H15: SI
A16: 6 | B16: 6 | C16: =30/20 -> 1.5 | D16: PORTAFOLIO Y MANEJO DE OBJECIONES | E16: =30/20 -> 1.5 | F16: UNICA | G16: OFRECE PURINA ONE: (APLICA SOLO EN CANAL MODERNO, CADENAS, SI EL PRODUCTO ESTA EN EL PDV) | H16: SI
A17: 0 | B17: 0 | C17: =30/20 -> 1.5 | D17: PORTAFOLIO Y MANEJO DE OBJECIONES | E17: =30/20 -> 1.5 | F17: UNICA | G17: MENCIONA QUE LOS RESULTADOS SON VISIBLES EN 28 DIAS? | H17: SI
A18: 0 | B18: 0 | C18: =30/20 -> 1.5 | D18: PORTAFOLIO Y MANEJO DE OBJECIONES | E18: =30/20 -> 1.5 | F18: UNICA | G18: MENCIONA QUE TIENE CARNE DE VERDAD COMO INGREDIENTE NO.1 E INGREDIENTES NATURALES Y FUNCIONALES? | H18: SI
A19: 0 | B19: 0 | C19: =30/20 -> 1.5 | D19: PORTAFOLIO Y MANEJO DE OBJECIONES | E19: =30/20 -> 1.5 | F19: UNICA | G19: MENCIONA QUE PURINA ONE CUENTA CON ALIMENTO HUMEDO Y MENCIONA LAS 3 VARIADADES QUE TIENE ( SUPER FOODS, SUPER NUTRIENTES Y MULTI PROTEINAS); APLICA TANTO PARA PERRO COMO PARA GATO? | H19: SI
A20: 0 | B20: 0 | C20: =30/20 -> 1.5 | D20: PORTAFOLIO Y MANEJO DE OBJECIONES | E20: =30/20 -> 1.5 | F20: UNICA | G20: ABORDA AL SHOPPER CON EL VERBATIM Y MANEJA LAS OBJECIONES SEGÚN COMUNICADO ENVIADO. | H20: SI
A21: 0 | B21: 0 | C21: =30/20 -> 1.5 | D21: PORTAFOLIO Y MANEJO DE OBJECIONES | E21: =30/20 -> 1.5 | F21: UNICA | G21: MENCIONA LA REDUCCION DE PRECIOS QUE TENEMOS DESDE EL MES DE DICIEMBRE (la unica referencia que no aplica es Gato adult carne 500gr) | H21: SI
A22: 0 | B22: 0 | C22: =30/20 -> 1.5 | D22: PORTAFOLIO Y MANEJO DE OBJECIONES | E22: =30/20 -> 1.5 | F22: UNICA | G22: (OFRECE EL OBSEQUIO APLICA VIERNES, SABADO Y DOMINGO) Y EXPLICA COMO HACER LA TRANSICIÓN DEL PRODUCTO Y BENEFICIOS? | H22: SI
A23: 0 | B23: 0 | C23: 0 | D23: N/A | E23: 0 | F23: UNICA | G23: SELECCIONE EL CANAL DEL PDV QUE EVALUA
A24: 0 | B24: 0 | C24: =18/3 -> 6 | D24: PORTAFOLIO Y MANEJO DE OBJECIONES | E24: =30/20 -> 1.5 | F24: UNICA | G24: CM - OFRECE DOG CHOW O CAT CHOW COMO PRIMERA OPCION | H24: SI
A25: 0 | B25: 0 | C25: =18/3 -> 6 | D25: PORTAFOLIO Y MANEJO DE OBJECIONES | E25: =30/20 -> 1.5 | F25: UNICA | G25: CM - OFRECE ALIMENTO HUMEDO DE DOG CHOW Y FELIX | H25: SI
A26: 0 | B26: 0 | C26: =18/3 -> 6 | D26: PORTAFOLIO Y MANEJO DE OBJECIONES | E26: =30/20 -> 1.5 | F26: UNICA | G26: CM - CONOCE LAS DINAMICAS COMERCIALES DEL PDV | H26: SI
A27: 0 | B27: =18/6 -> 3 | C27: 0 | D27: PORTAFOLIO Y MANEJO DE OBJECIONES | E27: =30/20 -> 1.5 | F27: UNICA | G27: CE - LO PRIMERO QUE OFRECE EL ASESOR ES LA MARCA PRO PLAN? (ENFOQUE EN GATOS) | H27: SI
A28: 0 | B28: =18/6 -> 3 | C28: 0 | D28: PORTAFOLIO Y MANEJO DE OBJECIONES | E28: =30/20 -> 1.5 | F28: UNICA | G28: CE - EL ASESOR COMUNICA LOS BENEFICIOS Y CARACTERISTICAS DE LA MARCA PRO PLAN? (ENFOQUE EN GATOS) | H28: SI
A29: 0 | B29: =18/6 -> 3 | C29: 0 | D29: PORTAFOLIO Y MANEJO DE OBJECIONES | E29: =30/20 -> 1.5 | F29: UNICA | G29: CE - LUEGO DE REALIZAR LA OBJECIÓN DE PRECIO, OFRECE LA MARCA EXCELLENT? (ENFOQUE EN GATOS) | H29: SI
A30: 0 | B30: =18/6 -> 3 | C30: 0 | D30: PORTAFOLIO Y MANEJO DE OBJECIONES | E30: =30/20 -> 1.5 | F30: UNICA | G30: CE - EL ASESOR COMUNICA QUE LA MARCA EXCELLENT ESTA DENTRO DE LA CATEGORIA SUPERPREMIUM PERO A UN COSTO MAS ACCESIBLE. | H30: SI
A31: 0 | B31: =18/6 -> 3 | C31: 0 | D31: PORTAFOLIO Y MANEJO DE OBJECIONES | E31: =30/20 -> 1.5 | F31: UNICA | G31: CE - EL ASESOR COMUNICA LOS BENEFICIOS Y CARACTERISTICAS DEL PRODUCTO EXCELLENT? (ENFOQUE EN GATOS) | H31: SI
A32: 0 | B32: =18/6 -> 3 | C32: 0 | D32: PORTAFOLIO Y MANEJO DE OBJECIONES | E32: =30/20 -> 1.5 | F32: UNICA | G32: CE - OFRECE PRODUCTO HUMEDO Y ENFATIZA EN LOS PACKS POR TEMAS DE PRECIO? (GATOS Y PERROS) | H32: SI
A33: =18/3 -> 6 | B33: 0 | C33: 0 | D33: PORTAFOLIO Y MANEJO DE OBJECIONES | E33: =30/20 -> 1.5 | F33: UNICA | G33: CT - OFRECIO ALGUN PRODUCTO DEL PORTAFOLIO PURINA DE PRODUCTOS SECOS COMUNICANDO LOS BENEFICIOS DEL PRODUCTO (DOG CHOW, CAT CHOW, ALPO, GATSY, FELIX O NINGUNO) | H33: SI
A34: =18/3 -> 6 | B34: 0 | C34: 0 | D34: PORTAFOLIO Y MANEJO DE OBJECIONES | E34: =30/20 -> 1.5 | F34: UNICA | G34: CT - OFRECIO ALGUN PRODUCTO PORTAFOLIO PURINA DE PRODUCTOS HUMEDOS COMUNICANDO LOS BENEFICIOS DEL PRODUCTO (Dog chow húmedo, Cat chow húmedo, Fancy Feast, Felix, Proplan Húmedo, One Húmedo, Snacks (Abrazzos, Dentalife), Arenilla (Tidy Cat) | H34: SI
A35: =18/3 -> 6 | B35: 0 | C35: 0 | D35: PORTAFOLIO Y MANEJO DE OBJECIONES | E35: =30/20 -> 1.5 | F35: UNICA | G35: CT - MENCIONA ALGUNA DE LAS INNOVACIONES QUE TENEMOS EN EL CANAL (CAT 200GR FELIX TRIPLE DELI Y MEGA MIX DE WET Y DOG CHOW ALTA PROTEINA DE 350GR 475GR ) | H35: SI
A36: 0 | B36: 0 | C36: 0 | D36: N/A | E36: 0 | F36: UNICA | G36: INDIQUE QUE TIPO DE OBJECION / DUDA MANIFESTÓ
A37: =15/4 -> 3.75 | B37: =15/4 -> 3.75 | C37: =15/4 -> 3.75 | D37: LABOR DE VENTA | E37: =15/4 -> 3.75 | F37: UNICA | G37: RESUELVE LA OBJECION SATISFACTORIAMENTE? | H37: SI
A38: =15/4 -> 3.75 | B38: =15/4 -> 3.75 | C38: =15/4 -> 3.75 | D38: LABOR DE VENTA | E38: =15/4 -> 3.75 | F38: UNICA | G38: SE ENCUENTRA LIMPIA EL AREA DE DEMOSTRACION "REVISION DE PRODUCTO SIN POLVO Y EN OPTIMAS CONDICIONES" | H38: SI
A39: =15/4 -> 3.75 | B39: =15/4 -> 3.75 | C39: =15/4 -> 3.75 | D39: LABOR DE VENTA | E39: =15/4 -> 3.75 | F39: UNICA | G39: REALIZA CIERRE DE VENTA | H39: SI
A40: =15/4 -> 3.75 | B40: =15/4 -> 3.75 | C40: =15/4 -> 3.75 | D40: LABOR DE VENTA | E40: =15/4 -> 3.75 | F40: UNICA | G40: CONSIDERO QUE INDEPENDIENTEMENTE DEL SPEECH, LA LABOR DE VENTA ES BUENA | H40: SI
A41: 0 | B41: 0 | C41: 0 | D41: N/A | E41: 0 | F41: UNICA | G41: DESEA AÑADIR ALGUNA OBSERVACION Y/O NOVEDAD DEL MYSTERY REALIZADO?
A42: 0 | B42: 0 | C42: 0 | D42: N/A | E42: 0 | F42: ABIERTA | G42: INDIQUE OBSERVACION Y/O NOVEDAD DEL MYSTERY REALIZADO
