Workbook
Name SegmentaciónDeDatos_CIUDAD: #N/A
Name SegmentaciónDeDatos_NOMBRE_COMERCIAL: #N/A

Sheet INFORME
A1: INFORME MYSTERY JUNIO
D3: EJECUCION DEL PLAN
D4: CIUDAD | E4: #PDV Obj. | F4: #PDV Eje. | G4: .% Ejecucion | H4: Obj Mystery | I4: Mystery Eje. | J4: % Efectividad.
D5: BARRANQUILLA | E5: 4 | F5: 4 | G5: 1 | H5: 4 | I5: 4 | J5: 1
D6: MEDELLIN | E6: 1 | F6: 1 | G6: 1 | H6: 1 | I6: 1 | J6: 1
D7: BOGOTA | E7: 9 | F7: 9 | G7: 1 | H7: 9 | I7: 6 | J7: 0.66666667
D8: CALI | E8: 4 | F8: 4 | G8: 1 | H8: 4 | I8: 2 | J8: 0.5
D9: Total general | E9: 18 | F9: 18 | G9: 1 | H9: 18 | I9: 13 | J9: 0.72222222
D15: MYSTERY POR CLUSTER
D16: Suma de % MYSTERY | E16: Etiquetas de columna
D17: CLUSTER | E17: MODERNO | F17: ESPECIALIZADO | G17: % MYSTERY
D18: HORARIO | E18: 1 | F18: 1 | G18: 1
D19: UNIFORME | E19: 1 | F19: 1 | G19: 1
D20: LABOR DE VENTA | E20: 0.75 | F20: 0.92857143 | G20: 0.84615385
D21: ABORDAJE | E21: 0.66666667 | F21: 1 | G21: 0.84615385
D22: PORTAFOLIO Y MANEJO DE OBJECIONES | E22: 0.62962963 | F22: 0.73469388 | G22: 0.67961165
D23: ACTIVIDADES DEL MES | E23: 0.33333333 | F23: 0.57142857 | G23: 0.46153846
D24: % MYSTERY | E24: 0.78751804 | F24: 0.92921204 | G24: 0.86257211
D29: MYSTERY POR CLUSTER - CIUDAD
D30: Suma de % MYSTERY | E30: Etiquetas de columna
D31: CLUSTER | E31: BOGOTA | F31: CALI | G31: MEDELLIN | H31: BARRANQUILLA | I31: % MYSTERY
D32: HORARIO | E32: 1 | F32: 1 | G32: 1 | H32: 1 | I32: 1
D33: UNIFORME | E33: 1 | F33: 1 | G33: 1 | H33: 1 | I33: 1
D34: LABOR DE VENTA | E34: 0.66666667 | F34: 1 | G34: 1 | H34: 1 | I34: 0.84615385
D35: ABORDAJE | E35: 0.83333333 | F35: 1 | G35: 0 | H35: 1 | I35: 0.84615385
D36: PORTAFOLIO Y MANEJO DE OBJECIONES | E36: 0.8125 | F36: 0.5 | G36: 0.77777778 | H36: 0.53125 | I36: 0.67961165
D37: ACTIVIDADES DEL MES | E37: 0.33333333 | F37: 0.5 | G37: 0 | H37: 0.75 | I37: 0.46153846
D38: % MYSTERY | E38: 0.83994126 | F38: 0.90807175 | G38: 0.68398268 | H38: 0.91960352 | I38: 0.86257211
D43: MYSTERY EFECTIVO | E43: (Todas)
D44: MYSTERY POR PDV
D45: Suma de % MYSTERY | G45: CLUSTER
D46: CIUDAD | E46: CANAL | F46: NOMBRE COMERCIAL | G46: ACTIVIDADES DEL MES | H46: HORARIO | I46: LABOR DE VENTA | J46: PORTAFOLIO Y MANEJO DE OBJECIONES | K46: UNIFORME | L46: % MYSTERY
D47: BOGOTA | E47: MODERNO | F47: 442719-EXITO COLINA | G47: 0 | H47: 1 | I47: 1 | J47: 1 | K47: 1 | L47: 0.9273743
D48: BOGOTA | E48: MODERNO | F48: 12565-JUMBO SANTA ANA | G48: 1 | H48: 1 | I48: 0.5 | J48: 1 | K48: 1 | L48: 0.89106145
D49: BOGOTA | E49: MODERNO | F49: 406974-JUMBO 170 | G49: 0 | H49: 1 | I49: 0 | J49: 0.33333333 | K49: 1 | L49: 0.57541899
D50: BOGOTA | E50: ESPECIALIZADO | F50: 108903-LA RES CENTRO | G50: 0 | H50: 1 | I50: 1 | J50: 1 | K50: 1 | L50: 0.92397661
D51: BOGOTA | E51: ESPECIALIZADO | F51: MUNDO MASCOTAS TABORA | G51: 0 | H51: 1 | I51: 1 | J51: 0.71428571 | K51: 1 | L51: 0.87719298
D52: BOGOTA | E52: ESPECIALIZADO | F52: KUMPET 94 | G52: 1 | H52: 1 | I52: 0.5 | J52: 0.85714286 | K52: 1 | L52: 0.8625731
D53: CALI | E53: ESPECIALIZADO | F53: SUPERMASCOTAS CIUDAD JARDIN | G53: 1 | H53: 1 | I53: 1 | J53: 0.57142857 | K53: 1 | L53: 0.92982456
D54: CALI | E54: ESPECIALIZADO | F54: 356625-AGRO LA HACIENDA SAS SUR | G54: 0 | H54: 1 | I54: 1 | J54: 0.42857143 | K54: 1 | L54: 0.83040936
D55: MEDELLIN | E55: MODERNO | F55: 428025-CARULLA RINCON DE OVIEDO | G55: 0 | H55: 1 | I55: 1 | J55: 0.77777778 | K55: 1 | L55: 0.88268156
D56: BARRANQUILLA | E56: MODERNO | F56: 126325-OLIMPICA STO 039 CHIQUINQUIRA | G56: 1 | H56: 1 | I56: 1 | J56: 0.44444444 | K56: 1 | L56: 0.88826816
D57: BARRANQUILLA | E57: MODERNO | F57: 447964-MAKRO BARRANQUILLA | G57: 0 | H57: 1 | I57: 1 | J57: 0.22222222 | K57: 1 | L57: 0.77094972
D58: BARRANQUILLA | E58: ESPECIALIZADO | F58: DISTRIBUCIONES MILENA | G58: 1 | H58: 1 | I58: 1 | J58: 1 | K58: 1 | L58: 1
D59: BARRANQUILLA | E59: ESPECIALIZADO | F59: CLINICA VETERINARIA SHARPEY | G59: 1 | H59: 1 | I59: 1 | J59: 0.57142857 | K59: 1 | L59: 0.92982456
D60: % MYSTERY | G60: 0.46153846 | H60: 1 | I60: 0.84615385 | J60: 0.67961165 | K60: 1 | L60: 0.86745927

Sheet Videos
A1: CIUDAD | B1: NOMBRE COMERCIAL | C1: VIDEO 1 | D1: VIDEO 2 | E1: VIDEO 3 | F1: VIDEO 4 | G1: VIDEO 5 | H1: VIDEO 6
A2: BARRANQUILLA | B2: CLINICA VETERINARIA SHARPEY | C2: CLINICA SHARPEY.mp4 - Google Drive | D2: - | E2: - | F2: - | G2: - | H2: -
A3: BARRANQUILLA | B3: 126325-OLIMPICA STO 039 CHIQUINQUIRA | C3: OLIMPICA CHIQUINQUIRA.mp4 - Google Drive | D3: - | E3: - | F3: - | G3: - | H3: -
A4: BARRANQUILLA | B4: 447964-MAKRO BARRANQUILLA | C4: MAKRO VILLA SANTOS.mp4 - Google Drive | D4: - | E4: - | F4: - | G4: - | H4: -
A5: BARRANQUILLA | B5: DISTRIBUCIONES MILENA | C5: DISTRIBUCIONES MILENA.mp4 - Google Drive | D5: - | E5: - | F5: - | G5: - | H5: -
A6: BOGOTA | B6: MUNDO MASCOTAS TABORA | C6: MISTERY MUNDO MASCOTAS TABORA.avi - Google Drive | D6: - | E6: - | F6: - | G6: - | H6: -
A7: BOGOTA | B7: KUMPET 94 | C7: MYSTERY KUMPET LA 94 PARTE 1.avi - Google Drive | D7: - | E7: - | F7: - | G7: - | H7: -
A8: BOGOTA | B8: 12394-EXITO CALLE 80 | C8: MYSTERY PURINA PRIMER VIDEO EXITO CALLE 80.avi - Google Drive | D8: MYSTERY PURINA SEGUNDO VIDEO EXITO CALLE 80.avi - Google Drive | E8: - | F8: - | G8: - | H8: -
A9: BOGOTA | B9: 108903-LA RES CENTRO | C9: MYSTERY PURINA LA RES CENTRO PARTE 1.avi - Google Drive | D9: MYSTERY PURINA LA RES CENTRO PARTE 2.avi - Google Drive | E9: MYSTERY PURINA LA RES CENTRO PARTE 3.avi - Google Drive | F9: MYSTERY PURINA LA RES CENTRO PARTE 4.avi - Google Drive | G9: MYSTERY PURINA LA RES CENTRO PARTE 5.avi - Google Drive | H9: MYSTERY PURINA LA RES CENTRO PARTE 6.avi - Google Drive | I9: -
A10: BOGOTA | B10: 454996-LAIKA 116 | C10: MYSTERY PURINA LAIKA 116 .avi - Google Drive | D10: - | E10: - | F10: - | G10: - | H10: -
A11: BOGOTA | B11: 12565-JUMBO SANTA ANA | C11: MYSTERY PURINA JUMBO SANTA ANA PARTE 1.avi - Google Drive | D11: MYSTERY PURINA JUMBO SANTA ANA PARTE 2.avi - Google Drive | E11: MYSTERY PURINA JUMBO SANTA ANA PARTE 3.avi - Google Drive | F11: MYSTERY PURINA JUMBO SANTA ANA PARTE 4.avi - Google Drive | G11: - | H11: -
A12: BOGOTA | B12: 12662-JUMBO TITAN BOGOTA | C12: MYSTERY PURINA JUMBO TITAN.avi - Google Drive | D12: - | E12: - | F12: - | G12: - | H12: -
A13: BOGOTA | B13: 406974-JUMBO 170 | C13: MYSTERY PURINA JUMBO CALLE 170 PARTE 1.avi - Google Drive | D13: MYSTERY PURINA JUMBO CALLE 170 PARTE 2.avi - Google Drive | E13: MYSTERY PURINA JUMBO CALLE 170 PARTE 3.avi - Google Drive | F13: MYSTERY PURINA JUMBO CALLE 170 PARTE 4.avi - Google Drive | G13: - | H13: -
A14: CALI | B14: SUPERMASCOTAS CIUDAD JARDIN | C14: MISTER SUPERMASCOTAS.mp4 - Google Drive | D14: - | E14: - | F14: - | G14: - | H14: -
A15: CALI | B15: 356625-AGRO LA HACIENDA SAS SUR | C15: MISTERY AGRO LA HACIENDA.mp4 - Google Drive | D15: - | E15: - | F15: - | G15: - | H15: -
A16: CALI | B16: 365377-Su Papa Lopez | C16: SU PAPA LOPEZ MISTERY PURINA.mp4 - Google Drive | D16: - | E16: - | F16: - | G16: - | H16: -
A17: CALI | B17: 13555-OLIMPICA STO 137 VILLA COLOMBIA | C17: mistery OLIMPICA VILLA COLOMBIA.mp4 - Google Drive | D17: - | E17: - | F17: - | G17: - | H17: -
A18: BOGOTA | B18: 442719-EXITO COLINA | C18: MYSTERY PURINA EXITO COLINA PARTE 1.avi - Google Drive | D18: MYSTERY PURINA EXITO COLINA PARTE 2.avi - Google Drive | E18: MYSTERY PURINA EXITO COLINA PARTE 3.avi - Google Drive | F18: MYSTERY PURINA EXITO COLINA PARTE 4.avi - Google Drive | G18: - | H18: -
A19: MEDELLIN | B19: 428025-CARULLA RINCON DE OVIEDO | C19: CARULLA RINCON DE OVIEDO.mp4 - Google Drive | D19: - | E19: - | F19: - | G19: - | H19: -

Sheet PUNTAJES
A1: ACTIVIDAD | B1: CIUDAD | C1: CANAL | D1: CADENA | E1: CODIGO PDV | F1: NOMBRE COMERCIAL | G1: PREGUNTA | H1: RTA | I1: FECHA VISITA | J1: CODIGO RUTA | K1: USUARIO | L1: MYSTERY EFECTIVO | M1: CLUSTER | N1: TOTAL PUNTAJE | O1: RTA CORRECTA | P1: PUNTAJE OBTENIDO | Q1: Columna1 | R1: Columna2 | T1: SI(O(G17="Dog Chow";G17="Cat Chow";G17="Alpo";G17="Gatsy";G17="Feliz");N17;0) | U1: SI(O(G29="Dog Chow húmedo";G29="Cat Chow húmedo";G29="Fancy Feast";G29="Felix";G29="Proplan húmedo";G29="One húmedo";G29="Snack Abrazzos";G29="Snak Dentalife";G29="Arenilla Tidy Cat");N29;0)
A2: NESTLE PURINA | B2: CALI | C2: MODERNO | D2: MERCA Z | E2: 365377 | F2: 365377-Su Papa Lopez | G2: OFRECIO ALGUN PRODUCTO PORTAFOLIO PURINA DE PRODUCTOS HUMEDOS, SNACK U OTROS COMUNICANDO LOS BENEFICIOS DEL PRODUCTO (Dog chow húmedo, Cat chow húmedo, Fancy Feast, Felix, Proplan Húmedo, One Húmedo) Snacks (Abrazzos, Dentalife) Arenilla (Tidy Cat) | H2: NO | J2: 27685551 | K2: NestleP.7 | L2: =_xlfn.XLOOKUP(Tabla2__2[[#This Row],[CODIGO RUTA]],'DATA INFORME'!I:I,'DATA INFORME'!K:K) -> NO | M2: =IF(Tabla2__2[[#This Row],[MYSTERY EFECTIVO]]="SI",_xlfn.XLOOKUP(Tabla2__2[[#This Row],[PREGUNTA]],ENCUESTA!G:G,ENCUESTA!D:D),"N/A") -> N/A | N2: =IF(Tabla2__2[[#This Row],[MYSTERY EFECTIVO]]="SI",(IF(Tabla2__2[[#This Row],[CANAL]]="TRADICIONAL",_xlfn.XLOOKUP(Tabla2__2[[#This Row],[PREGUNTA]],ENCUESTA!G:G,ENCUESTA!A:A),IF(Tabla2__2[[#This Row],[CANAL]]="ESPECIALIZADO",_xlfn.XLOOKUP(Tabla2__2[[#This Row],[PREGUNTA]],ENCUESTA!G:G,ENCUESTA!B:B),IF(Tabla2__2[[#This Row],[CANAL]]="MODERNO",_xlfn.XLOOKUP(Tabla2__2[[#This Row],[PREGUNTA]],ENCUESTA!G:G,ENCUESTA!C:C))))),0) -> 0 | O2: =_xlfn.XLOOKUP(Tabla2__2[[#This Row],[PREGUNTA]],ENCUESTA!G:G,ENCUESTA!H:H) -> SI | P2: =IF(Tabla2__2[[#This Row],[RTA]]=Tabla2__2[[#This Row],[RTA CORRECTA]],Tabla2__2[[#This Row],[TOTAL PUNTAJE]],0) -> 0 | Q2: =IF(OR(H2="Dog Chow húmedo",H2="Cat Chow húmedo",H2="Fancy Feast",H2="Felix",H2="Proplan húmedo",H2="One húmedo",H2="Snack Abrazzos",H2="Snak Dentalife",H2="Arenilla Tidy Cat"),N2,0) -> 0
A3: NESTLE PURINA | B3: CALI | C3: MODERNO | D3: MERCA Z | E3: 365377 | F3: 365377-Su Papa Lopez | G3: CONSIDERO QUE INDEPENDIENTEMENTE DEL SPEECH, LA LABOR DE VENTA ES BUENA | H3: NO | J3: 27685551 | K3: NestleP.7 | L3: =_xlfn.XLOOKUP(Tabla2__2[[#This Row],[CODIGO RUTA]],'DATA INFORME'!I:I,'DATA INFORME'!K:K) -> NO | M3: =IF(Tabla2__2[[#This Row],[MYSTERY EFECTIVO]]="SI",_xlfn.XLOOKUP(Tabla2__2[[#This Row],[PREGUNTA]],ENCUESTA!G:G,ENCUESTA!D:D),"N/A") -> N/A | N3: =IF(Tabla2__2[[#This Row],[MYSTERY EFECTIVO]]="SI",(IF(Tabla2__2[[#This Row],[CANAL]]="TRADICIONAL",_xlfn.XLOOKUP(Tabla2__2[[#This Row],[PREGUNTA]],ENCUESTA!G:G,ENCUESTA!A:A),IF(Tabla2__2[[#This Row],[CANAL]]="ESPECIALIZADO",_xlfn.XLOOKUP(Tabla2__2[[#This Row],[PREGUNTA]],ENCUESTA!G:G,ENCUESTA!B:B),IF(Tabla2__2[[#This Row],[CANAL]]="MODERNO",_xlfn.XLOOKUP(Tabla2__2[[#This Row],[PREGUNTA]],ENCUESTA!G:G,ENCUESTA!C:C))))),0) -> 0 | O3: =_xlfn.XLOOKUP(Tabla2__2[[#This Row],[PREGUNTA]],ENCUESTA!G:G,ENCUESTA!H:H) -> SI | P3: =IF(Tabla2__2[[#This Row],[RTA]]=Tabla2__2[[#This Row],[RTA CORRECTA]],Tabla2__2[[#This Row],[TOTAL PUNTAJE]],0) -> 0 | Q3: =IF(OR(H3="Dog Chow húmedo",H3="Cat Chow húmedo",H3="Fancy Feast",H3="Felix",H3="Proplan húmedo",H3="One húmedo",H3="Snack Abrazzos",H3="Snak Dentalife",H3="Arenilla Tidy Cat"),N3,0) -> 0
A4: NESTLE PURINA | B4: CALI | C4: MODERNO | D4: MERCA Z | E4: 365377 | F4: 365377-Su Papa Lopez | G4: REALIZA CIERRE DE VENTA | H4: NO | J4: 27685551 | K4: NestleP.7 | L4: =_xlfn.XLOOKUP(Tabla2__2[[#This Row],[CODIGO RUTA]],'DATA INFORME'!I:I,'DATA INFORME'!K:K) -> NO | M4: =IF(Tabla2__2[[#This Row],[MYSTERY EFECTIVO]]="SI",_xlfn.XLOOKUP(Tabla2__2[[#This Row],[PREGUNTA]],ENCUESTA!G:G,ENCUESTA!D:D),"N/A") -> N/A | N4: =IF(Tabla2__2[[#This Row],[MYSTERY EFECTIVO]]="SI",(IF(Tabla2__2[[#This Row],[CANAL]]="TRADICIONAL",_xlfn.XLOOKUP(Tabla2__2[[#This Row],[PREGUNTA]],ENCUESTA!G:G,ENCUESTA!A:A),IF(Tabla2__2[[#This Row],[CANAL]]="ESPECIALIZADO",_xlfn.XLOOKUP(Tabla2__2[[#This Row],[PREGUNTA]],ENCUESTA!G:G,ENCUESTA!B:B),IF(Tabla2__2[[#This Row],[CANAL]]="MODERNO",_xlfn.XLOOKUP(Tabla2__2[[#This Row],[PREGUNTA]],ENCUESTA!G:G,ENCUESTA!C:C))))),0) -> 0 | O4: =_xlfn.XLOOKUP(Tabla2__2[[#This Row],[PREGUNTA]],ENCUESTA!G:G,ENCUESTA!H:H) -> SI | P4: =IF(Tabla2__2[[#This Row],[RTA]]=Tabla2__2[[#This Row],[RTA CORRECTA]],Tabla2__2[[#This Row],[TOTAL PUNTAJE]],0) -> 0 | Q4: =IF(OR(H4="Dog Chow húmedo",H4="Cat Chow húmedo",H4="Fancy Feast",H4="Felix",H4="Proplan húmedo",H4="One húmedo",H4="Snack Abrazzos",H4="Snak Dentalife",H4="Arenilla Tidy Cat"),N4,0) -> 0
A5: NESTLE PURINA | B5: CALI | C5: MODERNO | D5: MERCA Z | E5: 365377 | F5: 365377-Su Papa Lopez | G5: SE ENCUENTRA LIMPIA EL AREA DE DEMOSTRACION | H5: NO | J5: 27685551 | K5: NestleP.7 | L5: =_xlfn.XLOOKUP(Tabla2__2[[#This Row],[CODIGO RUTA]],'DATA INFORME'!I:I,'DATA INFORME'!K:K) -> NO | M5: =IF(Tabla2__2[[#This Row],[MYSTERY EFECTIVO]]="SI",_xlfn.XLOOKUP(Tabla2__2[[#This Row],[PREGUNTA]],ENCUESTA!G:G,ENCUESTA!D:D),"N/A") -> N/A | N5: =IF(Tabla2__2[[#This Row],[MYSTERY EFECTIVO]]="SI",(IF(Tabla2__2[[#This Row],[CANAL]]="TRADICIONAL",_xlfn.XLOOKUP(Tabla2__2[[#This Row],[PREGUNTA]],ENCUESTA!G:G,ENCUESTA!A:A),IF(Tabla2__2[[#This Row],[CANAL]]="ESPECIALIZADO",_xlfn.XLOOKUP(Tabla2__2[[#This Row],[PREGUNTA]],ENCUESTA!G:G,ENCUESTA!B:B),IF(Tabla2__2[[#This Row],[CANAL]]="MODERNO",_xlfn.XLOOKUP(Tabla2__2[[#This Row],[PREGUNTA]],ENCUESTA!G:G,ENCUESTA!C:C))))),0) -> 0 | O5: =_xlfn.XLOOKUP(Tabla2__2[[#This Row],[PREGUNTA]],ENCUESTA!G:G,ENCUESTA!H:H) -> SI | P5: =IF(Tabla2__2[[#This Row],[RTA]]=Tabla2__2[[#This Row],[RTA CORRECTA]],Tabla2__2[[#This Row],[TOTAL PUNTAJE]],0) -> 0 | Q5: =IF(OR(H5="Dog Chow húmedo",H5="Cat Chow húmedo",H5="Fancy Feast",H5="Felix",H5="Proplan húmedo",H5="One húmedo",H5="Snack Abrazzos",H5="Snak Dentalife",H5="Arenilla Tidy Cat"),N5,0) -> 0
A6: NESTLE PURINA | B6: CALI | C6: MODERNO | D6: MERCA Z | E6: 365377 | F6: 365377-Su Papa Lopez | G6: RESUELVE LA OBJECION SATISFACTORIAMENTE? | H6: NO | J6: 27685551 | K6: NestleP.7 | L6: =_xlfn.XLOOKUP(Tabla2__2[[#This Row],[CODIGO RUTA]],'DATA INFORME'!I:I,'DATA INFORME'!K:K) -> NO | M6: =IF(Tabla2__2[[#This Row],[MYSTERY EFECTIVO]]="SI",_xlfn.XLOOKUP(Tabla2__2[[#This Row],[PREGUNTA]],ENCUESTA!G:G,ENCUESTA!D:D),"N/A") -> N/A | N6: =IF(Tabla2__2[[#This Row],[MYSTERY EFECTIVO]]="SI",(IF(Tabla2__2[[#This Row],[CANAL]]="TRADICIONAL",_xlfn.XLOOKUP(Tabla2__2[[#This Row],[PREGUNTA]],ENCUESTA!G:G,ENCUESTA!A:A),IF(Tabla2__2[[#This Row],[CANAL]]="ESPECIALIZADO",_xlfn.XLOOKUP(Tabla2__2[[#This Row],[PREGUNTA]],ENCUESTA!G:G,ENCUESTA!B:B),IF(Tabla2__2[[#This Row],[CANAL]]="MODERNO",_xlfn.XLOOKUP(Tabla2__2[[#This Row],[PREGUNTA]],ENCUESTA!G:G,ENCUESTA!C:C))))),0) -> 0 | O6: =_xlfn.XLOOKUP(Tabla2__2[[#This Row],[PREGUNTA]],ENCUESTA!G:G,ENCUESTA!H:H) -> SI | P6: =IF(Tabla2__2[[#This Row],[RTA]]=Tabla2__2[[#This Row],[RTA CORRECTA]],Tabla2__2[[#This Row],[TOTAL PUNTAJE]],0) -> 0 | Q6: =IF(OR(H6="Dog Chow húmedo",H6="Cat Chow húmedo",H6="Fancy Feast",H6="Felix",H6="Proplan húmedo",H6="One húmedo",H6="Snack Abrazzos",H6="Snak Dentalife",H6="Arenilla Tidy Cat"),N6,0) -> 0
A7: NESTLE PURINA | B7: CALI | C7: MODERNO | D7: MERCA Z | E7: 365377 | F7: 365377-Su Papa Lopez | G7: INDIQUE QUE TIPO DE OBJECION / DUDA MANIFESTÓ | H7: NO LE INTERESA EL PRODUCTO | J7: 27685551 | K7: NestleP.7 | L7: =_xlfn.XLOOKUP(Tabla2__2[[#This Row],[CODIGO RUTA]],'DATA INFORME'!I:I,'DATA INFORME'!K:K) -> NO | M7: =IF(Tabla2__2[[#This Row],[MYSTERY EFECTIVO]]="SI",_xlfn.XLOOKUP(Tabla2__2[[#This Row],[PREGUNTA]],ENCUESTA!G:G,ENCUESTA!D:D),"N/A") -> N/A | N7: =IF(Tabla2__2[[#This Row],[MYSTERY EFECTIVO]]="SI",(IF(Tabla2__2[[#This Row],[CANAL]]="TRADICIONAL",_xlfn.XLOOKUP(Tabla2__2[[#This Row],[PREGUNTA]],ENCUESTA!G:G,ENCUESTA!A:A),IF(Tabla2__2[[#This Row],[CANAL]]="ESPECIALIZADO",_xlfn.XLOOKUP(Tabla2__2[[#This Row],[PREGUNTA]],ENCUESTA!G:G,ENCUESTA!B:B),IF(Tabla2__2[[#This Row],[CANAL]]="MODERNO",_xlfn.XLOOKUP(Tabla2__2[[#This Row],[PREGUNTA]],ENCUESTA!G:G,ENCUESTA!C:C))))),0) -> 0 | O7: =_xlfn.XLOOKUP(Tabla2__2[[#This Row],[PREGUNTA]],ENCUESTA!G:G,ENCUESTA!H:H) -> FALTA DE PRODUCTO, NO LE INTERESA EL PRODUCTO, NO TIENE DINERO, PREFIERE LA COMPETENCIA | P7: =IF(Tabla2__2[[#This Row],[RTA]]=Tabla2__2[[#This Row],[RTA CORRECTA]],Tabla2__2[[#This Row],[TOTAL PUNTAJE]],0) -> 0 | Q7: =IF(OR(H7="Dog Chow húmedo",H7="Cat Chow húmedo",H7="Fancy Feast",H7="Felix",H7="Proplan húmedo",H7="One húmedo",H7="Snack Abrazzos",H7="Snak Dentalife",H7="Arenilla Tidy Cat"),N7,0) -> 0
A8: NESTLE PURINA | B8: CALI | C8: MODERNO | D8: MERCA Z | E8: 365377 | F8: 365377-Su Papa Lopez | G8: CM - Dan a conocer al cliente la actividad del "EVENTO CORPORATIVO DE OLIMPICA JUNIO"? | H8: NO | J8: 27685551 | K8: NestleP.7 | L8: =_xlfn.XLOOKUP(Tabla2__2[[#This Row],[CODIGO RUTA]],'DATA INFORME'!I:I,'DATA INFORME'!K:K) -> NO | M8: =IF(Tabla2__2[[#This Row],[MYSTERY EFECTIVO]]="SI",_xlfn.XLOOKUP(Tabla2__2[[#This Row],[PREGUNTA]],ENCUESTA!G:G,ENCUESTA!D:D),"N/A") -> N/A | N8: =IF(Tabla2__2[[#This Row],[MYSTERY EFECTIVO]]="SI",(IF(Tabla2__2[[#This Row],[CANAL]]="TRADICIONAL",_xlfn.XLOOKUP(Tabla2__2[[#This Row],[PREGUNTA]],ENCUESTA!G:G,ENCUESTA!A:A),IF(Tabla2__2[[#This Row],[CANAL]]="ESPECIALIZADO",_xlfn.XLOOKUP(Tabla2__2[[#This Row],[PREGUNTA]],ENCUESTA!G:G,ENCUESTA!B:B),IF(Tabla2__2[[#This Row],[CANAL]]="MODERNO",_xlfn.XLOOKUP(Tabla2__2[[#This Row],[PREGUNTA]],ENCUESTA!G:G,ENCUESTA!C:C))))),0) -> 0 | O8: =_xlfn.XLOOKUP(Tabla2__2[[#This Row],[PREGUNTA]],ENCUESTA!G:G,ENCUESTA!H:H) -> SI | P8: =IF(Tabla2__2[[#This Row],[RTA]]=Tabla2__2[[#This Row],[RTA CORRECTA]],Tabla2__2[[#This Row],[TOTAL PUNTAJE]],0) -> 0 | Q8: =IF(OR(H8="Dog Chow húmedo",H8="Cat Chow húmedo",H8="Fancy Feast",H8="Felix",H8="Proplan húmedo",H8="One húmedo",H8="Snack Abrazzos",H8="Snak Dentalife",H8="Arenilla Tidy Cat"),N8,0) -> 0
A9: NESTLE PURINA | B9: CALI | C9: MODERNO | D9: MERCA Z | E9: 365377 | F9: 365377-Su Papa Lopez | G9: CM - Bajo la objeción de "precio muy costoso", el asesor ofrece productos en el orden de la segmentación: Perros: Purina One - Dog Chow - Alpo y Gatos: Purina One - Cat Chow - Felix - Gatsy (cuando enuncia Gatsy menciona que "ahora es mas sabroso") | H9: NO | J9: 27685551 | K9: NestleP.7 | L9: =_xlfn.XLOOKUP(Tabla2__2[[#This Row],[CODIGO RUTA]],'DATA INFORME'!I:I,'DATA INFORME'!K:K) -> NO | M9: =IF(Tabla2__2[[#This Row],[MYSTERY EFECTIVO]]="SI",_xlfn.XLOOKUP(Tabla2__2[[#This Row],[PREGUNTA]],ENCUESTA!G:G,ENCUESTA!D:D),"N/A") -> N/A | N9: =IF(Tabla2__2[[#This Row],[MYSTERY EFECTIVO]]="SI",(IF(Tabla2__2[[#This Row],[CANAL]]="TRADICIONAL",_xlfn.XLOOKUP(Tabla2__2[[#This Row],[PREGUNTA]],ENCUESTA!G:G,ENCUESTA!A:A),IF(Tabla2__2[[#This Row],[CANAL]]="ESPECIALIZADO",_xlfn.XLOOKUP(Tabla2__2[[#This Row],[PREGUNTA]],ENCUESTA!G:G,ENCUESTA!B:B),IF(Tabla2__2[[#This Row],[CANAL]]="MODERNO",_xlfn.XLOOKUP(Tabla2__2[[#This Row],[PREGUNTA]],ENCUESTA!G:G,ENCUESTA!C:C))))),0) -> 0 | O9: =_xlfn.XLOOKUP(Tabla2__2[[#This Row],[PREGUNTA]],ENCUESTA!G:G,ENCUESTA!H:H) -> SI | P9: =IF(Tabla2__2[[#This Row],[RTA]]=Tabla2__2[[#This Row],[RTA CORRECTA]],Tabla2__2[[#This Row],[TOTAL PUNTAJE]],0) -> 0 | Q9: =IF(OR(H9="Dog Chow húmedo",H9="Cat Chow húmedo",H9="Fancy Feast",H9="Felix",H9="Proplan húmedo",H9="One húmedo",H9="Snack Abrazzos",H9="Snak Dentalife",H9="Arenilla Tidy Cat"),N9,0) -> 0
A10: NESTLE PURINA | B10: CALI | C10: MODERNO | D10: MERCA Z | E10: 365377 | F10: 365377-Su Papa Lopez | G10: CM - Maneja la objeción de alto precio en las marcas Purina, comunicando la baja de precios de las marcas o las ofertas disponibles en el punto de venta. | H10: NO | J10: 27685551 | K10: NestleP.7 | L10: =_xlfn.XLOOKUP(Tabla2__2[[#This Row],[CODIGO RUTA]],'DATA INFORME'!I:I,'DATA INFORME'!K:K) -> NO | M10: =IF(Tabla2__2[[#This Row],[MYSTERY EFECTIVO]]="SI",_xlfn.XLOOKUP(Tabla2__2[[#This Row],[PREGUNTA]],ENCUESTA!G:G,ENCUESTA!D:D),"N/A") -> N/A | N10: =IF(Tabla2__2[[#This Row],[MYSTERY EFECTIVO]]="SI",(IF(Tabla2__2[[#This Row],[CANAL]]="TRADICIONAL",_xlfn.XLOOKUP(Tabla2__2[[#This Row],[PREGUNTA]],ENCUESTA!G:G,ENCUESTA!A:A),IF(Tabla2__2[[#This Row],[CANAL]]="ESPECIALIZADO",_xlfn.XLOOKUP(Tabla2__2[[#This Row],[PREGUNTA]],ENCUESTA!G:G,ENCUESTA!B:B),IF(Tabla2__2[[#This Row],[CANAL]]="MODERNO",_xlfn.XLOOKUP(Tabla2__2[[#This Row],[PREGUNTA]],ENCUESTA!G:G,ENCUESTA!C:C))))),0) -> 0 | O10: =_xlfn.XLOOKUP(Tabla2__2[[#This Row],[PREGUNTA]],ENCUESTA!G:G,ENCUESTA!H:H) -> SI | P10: =IF(Tabla2__2[[#This Row],[RTA]]=Tabla2__2[[#This Row],[RTA CORRECTA]],Tabla2__2[[#This Row],[TOTAL PUNTAJE]],0) -> 0 | Q10: =IF(OR(H10="Dog Chow húmedo",H10="Cat Chow húmedo",H10="Fancy Feast",H10="Felix",H10="Proplan húmedo",H10="One húmedo",H10="Snack Abrazzos",H10="Snak Dentalife",H10="Arenilla Tidy Cat"),N10,0) -> 0
A11: NESTLE PURINA | B11: CALI | C11: MODERNO | D11: MERCA Z | E11: 365377 | F11: 365377-Su Papa Lopez | G11: CM - MENCIONA QUE PURINA ONE CUENTA CON ALIMENTO HUMEDO Y MENCIONA LAS 3 VARIADADES QUE TIENE ( SUPER FOODS, SUPER NUTRIENTES Y MULTI PROTEINAS); APLICA TANTO PARA PERRO COMO PARA GATO | H11: NO | J11: 27685551 | K11: NestleP.7 | L11: =_xlfn.XLOOKUP(Tabla2__2[[#This Row],[CODIGO RUTA]],'DATA INFORME'!I:I,'DATA INFORME'!K:K) -> NO | M11: =IF(Tabla2__2[[#This Row],[MYSTERY EFECTIVO]]="SI",_xlfn.XLOOKUP(Tabla2__2[[#This Row],[PREGUNTA]],ENCUESTA!G:G,ENCUESTA!D:D),"N/A") -> N/A | N11: =IF(Tabla2__2[[#This Row],[MYSTERY EFECTIVO]]="SI",(IF(Tabla2__2[[#This Row],[CANAL]]="TRADICIONAL",_xlfn.XLOOKUP(Tabla2__2[[#This Row],[PREGUNTA]],ENCUESTA!G:G,ENCUESTA!A:A),IF(Tabla2__2[[#This Row],[CANAL]]="ESPECIALIZADO",_xlfn.XLOOKUP(Tabla2__2[[#This Row],[PREGUNTA]],ENCUESTA!G:G,ENCUESTA!B:B),IF(Tabla2__2[[#This Row],[CANAL]]="MODERNO",_xlfn.XLOOKUP(Tabla2__2[[#This Row],[PREGUNTA]],ENCUESTA!G:G,ENCUESTA!C:C))))),0) -> 0 | O11: =_xlfn.XLOOKUP(Tabla2__2[[#This Row],[PREGUNTA]],ENCUESTA!G:G,ENCUESTA!H:H) -> SI | P11: =IF(Tabla2__2[[#This Row],[RTA]]=Tabla2__2[[#This Row],[RTA CORRECTA]],Tabla2__2[[#This Row],[TOTAL PUNTAJE]],0) -> 0 | Q11: =IF(OR(H11="Dog Chow húmedo",H11="Cat Chow húmedo",H11="Fancy Feast",H11="Felix",H11="Proplan húmedo",H11="One húmedo",H11="Snack Abrazzos",H11="Snak Dentalife",H11="Arenilla Tidy Cat"),N11,0) -> 0
A12: NESTLE PURINA | B12: CALI | C12: MODERNO | D12: MERCA Z | E12: 365377 | F12: 365377-Su Papa Lopez | G12: CM - MENCIONA QUE TIENE CARNE DE VERDAD COMO INGREDIENTE NO.1 E INGREDIENTES NATURALES Y FUNCIONALES? | H12: NO | J12: 27685551 | K12: NestleP.7 | L12: =_xlfn.XLOOKUP(Tabla2__2[[#This Row],[CODIGO RUTA]],'DATA INFORME'!I:I,'DATA INFORME'!K:K) -> NO | M12: =IF(Tabla2__2[[#This Row],[MYSTERY EFECTIVO]]="SI",_xlfn.XLOOKUP(Tabla2__2[[#This Row],[PREGUNTA]],ENCUESTA!G:G,ENCUESTA!D:D),"N/A") -> N/A | N12: =IF(Tabla2__2[[#This Row],[MYSTERY EFECTIVO]]="SI",(IF(Tabla2__2[[#This Row],[CANAL]]="TRADICIONAL",_xlfn.XLOOKUP(Tabla2__2[[#This Row],[PREGUNTA]],ENCUESTA!G:G,ENCUESTA!A:A),IF(Tabla2__2[[#This Row],[CANAL]]="ESPECIALIZADO",_xlfn.XLOOKUP(Tabla2__2[[#This Row],[PREGUNTA]],ENCUESTA!G:G,ENCUESTA!B:B),IF(Tabla2__2[[#This Row],[CANAL]]="MODERNO",_xlfn.XLOOKUP(Tabla2__2[[#This Row],[PREGUNTA]],ENCUESTA!G:G,ENCUESTA!C:C))))),0) -> 0 | O12: =_xlfn.XLOOKUP(Tabla2__2[[#This Row],[PREGUNTA]],ENCUESTA!G:G,ENCUESTA!H:H) -> SI | P12: =IF(Tabla2__2[[#This Row],[RTA]]=Tabla2__2[[#This Row],[RTA CORRECTA]],Tabla2__2[[#This Row],[TOTAL PUNTAJE]],0) -> 0 | Q12: =IF(OR(H12="Dog Chow húmedo",H12="Cat Chow húmedo",H12="Fancy Feast",H12="Felix",H12="Proplan húmedo",H12="One húmedo",H12="Snack Abrazzos",H12="Snak Dentalife",H12="Arenilla Tidy Cat"),N12,0) -> 0
A13: NESTLE PURINA | B13: CALI | C13: MODERNO | D13: MERCA Z | E13: 365377 | F13: 365377-Su Papa Lopez | G13: CM - MENCIONA QUE LOS RESULTADOS DE PURINA ONE SON VISIBLES EN 28 DIAS? | H13: NO | J13: 27685551 | K13: NestleP.7 | L13: =_xlfn.XLOOKUP(Tabla2__2[[#This Row],[CODIGO RUTA]],'DATA INFORME'!I:I,'DATA INFORME'!K:K) -> NO | M13: =IF(Tabla2__2[[#This Row],[MYSTERY EFECTIVO]]="SI",_xlfn.XLOOKUP(Tabla2__2[[#This Row],[PREGUNTA]],ENCUESTA!G:G,ENCUESTA!D:D),"N/A") -> N/A | N13: =IF(Tabla2__2[[#This Row],[MYSTERY EFECTIVO]]="SI",(IF(Tabla2__2[[#This Row],[CANAL]]="TRADICIONAL",_xlfn.XLOOKUP(Tabla2__2[[#This Row],[PREGUNTA]],ENCUESTA!G:G,ENCUESTA!A:A),IF(Tabla2__2[[#This Row],[CANAL]]="ESPECIALIZADO",_xlfn.XLOOKUP(Tabla2__2[[#This Row],[PREGUNTA]],ENCUESTA!G:G,ENCUESTA!B:B),IF(Tabla2__2[[#This Row],[CANAL]]="MODERNO",_xlfn.XLOOKUP(Tabla2__2[[#This Row],[PREGUNTA]],ENCUESTA!G:G,ENCUESTA!C:C))))),0) -> 0 | O13: =_xlfn.XLOOKUP(Tabla2__2[[#This Row],[PREGUNTA]],ENCUESTA!G:G,ENCUESTA!H:H) -> SI | P13: =IF(Tabla2__2[[#This Row],[RTA]]=Tabla2__2[[#This Row],[RTA CORRECTA]],Tabla2__2[[#This Row],[TOTAL PUNTAJE]],0) -> 0 | Q13: =IF(OR(H13="Dog Chow húmedo",H13="Cat Chow húmedo",H13="Fancy Feast",H13="Felix",H13="Proplan húmedo",H13="One húmedo",H13="Snack Abrazzos",H13="Snak Dentalife",H13="Arenilla Tidy Cat"),N13,0) -> 0
... A514: NESTLE PURINA | B514: BOGOTA | C514: MODERNO | D514: JUMBO | E514: 12565 | F514: 12565-JUMBO SANTA ANA | G514: DESEA AÑADIR ALGUNA OBSERVACION Y/O NOVEDAD DEL MYSTERY REALIZADO? | H514: NO | J514: 27689425 | K514: NestleP.1 | L514: =_xlfn.XLOOKUP(Tabla2__2[[#This Row],[CODIGO RUTA]],'DATA INFORME'!I:I,'DATA INFORME'!K:K) -> SI | M514: =IF(Tabla2__2[[#This Row],[MYSTERY EFECTIVO]]="SI",_xlfn.XLOOKUP(Tabla2__2[[#This Row],[PREGUNTA]],ENCUESTA!G:G,ENCUESTA!D:D),"N/A") -> N/A | N514: =IF(Tabla2__2[[#This Row],[MYSTERY EFECTIVO]]="SI",(IF(Tabla2__2[[#This Row],[CANAL]]="TRADICIONAL",_xlfn.XLOOKUP(Tabla2__2[[#This Row],[PREGUNTA]],ENCUESTA!G:G,ENCUESTA!A:A),IF(Tabla2__2[[#This Row],[CANAL]]="ESPECIALIZADO",_xlfn.XLOOKUP(Tabla2__2[[#This Row],[PREGUNTA]],ENCUESTA!G:G,ENCUESTA!B:B),IF(Tabla2__2[[#This Row],[CANAL]]="MODERNO",_xlfn.XLOOKUP(Tabla2__2[[#This Row],[PREGUNTA]],ENCUESTA!G:G,ENCUESTA!C:C))))),0) -> 0 | O514: =_xlfn.XLOOKUP(Tabla2__2[[#This Row],[PREGUNTA]],ENCUESTA!G:G,ENCUESTA!H:H) -> 0 | P514: =IF(Tabla2__2[[#This Row],[RTA]]=Tabla2__2[[#This Row],[RTA CORRECTA]],Tabla2__2[[#This Row],[TOTAL PUNTAJE]],0) -> 0 | Q514: =IF(OR(H514="Dog Chow húmedo",H514="Cat Chow húmedo",H514="Fancy Feast",H514="Felix",H514="Proplan húmedo",H514="One húmedo",H514="Snack Abrazzos",H514="Snak Dentalife",H514="Arenilla Tidy Cat"),N514,0) -> 0

Sheet Panel
A1: CANAL | B1: CIUDAD | C1: CODIGO PDV | D1: NOMBRE COMERCIAL | E1: Objetivo Mystery | F1: #PDV Objetivos | G1: #PDV Ejecutados | H1: # Visitas | I1: Mystery Ejecutado
A2: ESPECIALIZADO | B2: BARRANQUILLA | C2: 191495 | D2: CLINICA VETERINARIA SHARPEY | E2: 1 | F2: 1 | G2: =IF(COUNTIFS(Export!I:I,Tabla1[[#This Row],[CODIGO PDV]])>0,1,0) -> 1 | H2: =COUNTIFS('DATA INFORME'!D:D,Tabla1[[#This Row],[CODIGO PDV]]) -> 1 | I2: =COUNTIFS('DATA INFORME'!D:D,Tabla1[[#This Row],[CODIGO PDV]],'DATA INFORME'!K:K,"SI") -> 1
A3: MODERNO | B3: BARRANQUILLA | C3: 126325 | D3: 126325-OLIMPICA STO 039 CHIQUINQUIRA | E3: 1 | F3: 1 | G3: =IF(COUNTIFS(Export!I:I,Tabla1[[#This Row],[CODIGO PDV]])>0,1,0) -> 1 | H3: =COUNTIFS('DATA INFORME'!D:D,Tabla1[[#This Row],[CODIGO PDV]]) -> 1 | I3: =COUNTIFS('DATA INFORME'!D:D,Tabla1[[#This Row],[CODIGO PDV]],'DATA INFORME'!K:K,"SI") -> 1
A4: MODERNO | B4: BARRANQUILLA | C4: 447964 | D4: 447964-MAKRO BARRANQUILLA | E4: 1 | F4: 1 | G4: =IF(COUNTIFS(Export!I:I,Tabla1[[#This Row],[CODIGO PDV]])>0,1,0) -> 1 | H4: =COUNTIFS('DATA INFORME'!D:D,Tabla1[[#This Row],[CODIGO PDV]]) -> 1 | I4: =COUNTIFS('DATA INFORME'!D:D,Tabla1[[#This Row],[CODIGO PDV]],'DATA INFORME'!K:K,"SI") -> 1
A5: ESPECIALIZADO | B5: BARRANQUILLA | C5: 65453 | D5: DISTRIBUCIONES MILENA | E5: 1 | F5: 1 | G5: =IF(COUNTIFS(Export!I:I,Tabla1[[#This Row],[CODIGO PDV]])>0,1,0) -> 1 | H5: =COUNTIFS('DATA INFORME'!D:D,Tabla1[[#This Row],[CODIGO PDV]]) -> 1 | I5: =COUNTIFS('DATA INFORME'!D:D,Tabla1[[#This Row],[CODIGO PDV]],'DATA INFORME'!K:K,"SI") -> 1
A6: ESPECIALIZADO | B6: BOGOTA | C6: 355955 | D6: MUNDO MASCOTAS TABORA | E6: 1 | F6: 1 | G6: =IF(COUNTIFS(Export!I:I,Tabla1[[#This Row],[CODIGO PDV]])>0,1,0) -> 1 | H6: =COUNTIFS('DATA INFORME'!D:D,Tabla1[[#This Row],[CODIGO PDV]]) -> 1 | I6: =COUNTIFS('DATA INFORME'!D:D,Tabla1[[#This Row],[CODIGO PDV]],'DATA INFORME'!K:K,"SI") -> 1
A7: ESPECIALIZADO | B7: BOGOTA | C7: 435142 | D7: KUMPET 94 | E7: 1 | F7: 1 | G7: =IF(COUNTIFS(Export!I:I,Tabla1[[#This Row],[CODIGO PDV]])>0,1,0) -> 1 | H7: =COUNTIFS('DATA INFORME'!D:D,Tabla1[[#This Row],[CODIGO PDV]]) -> 1 | I7: =COUNTIFS('DATA INFORME'!D:D,Tabla1[[#This Row],[CODIGO PDV]],'DATA INFORME'!K:K,"SI") -> 1
A8: MODERNO | B8: BOGOTA | C8: 12394 | D8: 12394-EXITO CALLE 80 | E8: 1 | F8: 1 | G8: =IF(COUNTIFS(Export!I:I,Tabla1[[#This Row],[CODIGO PDV]])>0,1,0) -> 1 | H8: =COUNTIFS('DATA INFORME'!D:D,Tabla1[[#This Row],[CODIGO PDV]]) -> 1 | I8: =COUNTIFS('DATA INFORME'!D:D,Tabla1[[#This Row],[CODIGO PDV]],'DATA INFORME'!K:K,"SI") -> 0
A9: ESPECIALIZADO | B9: BOGOTA | C9: 108903 | D9: 108903-LA RES CENTRO | E9: 1 | F9: 1 | G9: =IF(COUNTIFS(Export!I:I,Tabla1[[#This Row],[CODIGO PDV]])>0,1,0) -> 1 | H9: =COUNTIFS('DATA INFORME'!D:D,Tabla1[[#This Row],[CODIGO PDV]]) -> 1 | I9: =COUNTIFS('DATA INFORME'!D:D,Tabla1[[#This Row],[CODIGO PDV]],'DATA INFORME'!K:K,"SI") -> 1
A10: ESPECIALIZADO | B10: BOGOTA | C10: 454996 | D10: 454996-LAIKA 116 | E10: 1 | F10: 1 | G10: =IF(COUNTIFS(Export!I:I,Tabla1[[#This Row],[CODIGO PDV]])>0,1,0) -> 1 | H10: =COUNTIFS('DATA INFORME'!D:D,Tabla1[[#This Row],[CODIGO PDV]]) -> 1 | I10: =COUNTIFS('DATA INFORME'!D:D,Tabla1[[#This Row],[CODIGO PDV]],'DATA INFORME'!K:K,"SI") -> 0
A11: MODERNO | B11: BOGOTA | C11: 12565 | D11: 12565-JUMBO SANTA ANA | E11: 1 | F11: 1 | G11: =IF(COUNTIFS(Export!I:I,Tabla1[[#This Row],[CODIGO PDV]])>0,1,0) -> 1 | H11: =COUNTIFS('DATA INFORME'!D:D,Tabla1[[#This Row],[CODIGO PDV]]) -> 1 | I11: =COUNTIFS('DATA INFORME'!D:D,Tabla1[[#This Row],[CODIGO PDV]],'DATA INFORME'!K:K,"SI") -> 1
A12: MODERNO | B12: BOGOTA | C12: 12662 | D12: 12662-JUMBO TITAN BOGOTA | E12: 1 | F12: 1 | G12: =IF(COUNTIFS(Export!I:I,Tabla1[[#This Row],[CODIGO PDV]])>0,1,0) -> 1 | H12: =COUNTIFS('DATA INFORME'!D:D,Tabla1[[#This Row],[CODIGO PDV]]) -> 1 | I12: =COUNTIFS('DATA INFORME'!D:D,Tabla1[[#This Row],[CODIGO PDV]],'DATA INFORME'!K:K,"SI") -> 0
A13: MODERNO | B13: BOGOTA | C13: 406974 | D13: 406974-JUMBO 170 | E13: 1 | F13: 1 | G13: =IF(COUNTIFS(Export!I:I,Tabla1[[#This Row],[CODIGO PDV]])>0,1,0) -> 1 | H13: =COUNTIFS('DATA INFORME'!D:D,Tabla1[[#This Row],[CODIGO PDV]]) -> 1 | I13: =COUNTIFS('DATA INFORME'!D:D,Tabla1[[#This Row],[CODIGO PDV]],'DATA INFORME'!K:K,"SI") -> 1
... A19: MODERNO | B19: MEDELLIN | C19: 428025 | D19: 428025-CARULLA RINCON DE OVIEDO | E19: 1 | F19: 1 | G19: =IF(COUNTIFS(Export!I:I,Tabla1[[#This Row],[CODIGO PDV]])>0,1,0) -> 1 | H19: =COUNTIFS('DATA INFORME'!D:D,Tabla1[[#This Row],[CODIGO PDV]]) -> 1 | I19: =COUNTIFS('DATA INFORME'!D:D,Tabla1[[#This Row],[CODIGO PDV]],'DATA INFORME'!K:K,"SI") -> 1
A31: CANAL | B31: CIUDAD | C31: VUM | D31: NOMBRE PDV | E31: NOVEDAD
A32: MODERNO | B32: BOGOTA | C32: 12394 | D32: 12394-EXITO CALLE 80 | E32: SE RETRASO EN LA RUTA Y NO HABIA ALCANZADO A LLEGAR ESTABA EN OTRO PUNTO
A33: ESPECIALIZADO | B33: BOGOTA | C33: 454996 | D33: 454996-LAIKA 116 | E33: TENIA INCAPACIDAD
A34: MODERNO | B34: BOGOTA | C34: 12662 | D34: 12662-JUMBO TITAN BOGOTA | E34: EL ASESOR ESTABA EN EVENTO EN OTRO PUNTO
A35: MODERNO | B35: CALI | C35: 365377 | D35: 365377-Su Papa Lopez | E35: YA HABIA SALIDO DEL PUNTO PARA OTRO
A36: MODERNO | B36: CALI | C36: 13555 | D36: 13555-OLIMPICA STO 137 VILLA COLOMBIA | E36: SE RETRASO EN LA RUTA Y NO HABIA ALCANZADO A LLEGAR ESTABA EN OTRO PUNTO

Sheet DATA INFORME
A1: ACTIVIDAD | B1: CIUDAD | C1: CADENA | D1: CODIGO PDV | E1: NOMBRE COMERCIAL | F1: CONSECUTIVO ENCUESTA | G1: NOMBRE ENCUESTA | H1: FECHA VISITA | I1: CODIGO RUTA | J1: USUARIO | K1: SE LOGRA REALIZAR EL MYSTERY? | L1: ¿CUMPLE HORARIO DE ENTRADA O SALIDA DE LA TIENDA? | M1: CUENTA CON PANTALON DEL UNIFORME SEGÚN EL CARGO (NEGRO / ROJO / TURQUESA / JEAN) | N1: CUENTA CON CAMISA DEL UNIFORME Y LOGOS SEGÚN EL CARGO (NEGRA / GRIS / ROJA / TURQUESA) (Es permitido usar debajo de la camisa buso manga larga Negro) | O1: CUENTA CON CALZADO DE ACUERDO AL UNIFORME | P1: POSEE ALGUNA PRENDA ENCIMA DEL UNIFORME NO AUTORIZADA POR LA MARCA (Unicamente esta permitido chaleco de Sodimac y Easy) | Q1: EL UNIFORME Y ZAPATOS SE ENCUENTRAN LIMPIOS Y EN BUEN ESTADO | R1: SU CABELLO LUCE LIMPIO, ORGANIZADO O RECOGIDO | S1: PRESENTA EXCESO DE MAQUILLAJE QUE NO CUMPLE CON EL CODIGO DE VESTIMENTA | T1: TIENE TATUAJES O PIERCINGS VISIBLES QUE NO CUMPLE CON EL CODIGO DE VESTIMENTA | U1: TIENE UÑAS LLAMATIVAS Y/O LARGAS QUE NO CUMPLE CON EL CODIGO DE VESTIMENTA | V1: USA ACCESORIOS QUE NO CUMPLE CON EL CODIGO DE VESTIMENTA | W1: SE PRODUCE ABORDO PROACTIVO (antes de los 3 min) | X1: OFRECIO ALGUN PRODUCTO DEL PORTAFOLIO PURINA DE PRODUCTOS SECOS COMUNICANDO LOS BENEFICIOS DEL PRODUCTO (DOG CHOW, CAT CHOW, ALPO, GATSY,FELIX) | Y1: OFRECIO ALGUN PRODUCTO PORTAFOLIO PURINA DE PRODUCTOS HUMEDOS, SNACK U OTROS COMUNICANDO LOS BENEFICIOS DEL PRODUCTO (Dog chow húmedo, Cat chow húmedo, Fancy Feast, Felix, Proplan Húmedo, One Húmedo) Snacks (Abrazzos, Dentalife) Arenilla (Tidy Cat) | Z1: SELECCIONE EL CANAL DEL PDV QUE EVALUA | AA1: CE - Lo primero que ofrece el asesor es la marca Pro Plan? | AB1: CE - Ofrece la marca Excellent? | AC1: CE - El asesor comunica que la marca Excellent esta dentro de la categoria SuperPremium pero a un costo mas accesible. | AD1: CE - El asesor comunica los beneficios o caracteristicas del producto Excellent e informa que el producto cambio de imagen pero continua con la misma formula? | AE1: CE - Ofrece producto humedo y comunica la dinamica de multiprice (por la compra de mas cantidades tiene descuento) | AF1: INDIQUE QUE TIPO DE OBJECION / DUDA MANIFESTÓ | AG1: RESUELVE LA OBJECION SATISFACTORIAMENTE? | AH1: SE ENCUENTRA LIMPIA EL AREA DE DEMOSTRACION | AI1: REALIZA CIERRE DE VENTA | AJ1: CONSIDERO QUE INDEPENDIENTEMENTE DEL SPEECH, LA LABOR DE VENTA ES BUENA | AK1: DESEA AÑADIR ALGUNA OBSERVACION Y/O NOVEDAD DEL MYSTERY REALIZADO? | AL1: CM - OFRECE PURINA ONE? | AM1: CM - MENCIONA QUE LOS RESULTADOS DE PURINA ONE SON VISIBLES EN 28 DIAS? | AN1: CM - MENCIONA QUE TIENE CARNE DE VERDAD COMO INGREDIENTE NO.1 E INGREDIENTES NATURALES Y FUNCIONALES? | AO1: CM - MENCIONA QUE PURINA ONE CUENTA CON ALIMENTO HUMEDO Y MENCIONA LAS 3 VARIADADES QUE TIENE ( SUPER FOODS, SUPER NUTRIENTES Y MULTI PROTEINAS); APLICA TANTO PARA PERRO COMO PARA GATO | AP1: CM - Maneja la objeción de alto precio en las marcas Purina, comunicando la baja de precios de las marcas o las ofertas disponibles en el punto de venta. | AQ1: CM - Bajo la objeción de "precio muy costoso", el asesor ofrece productos en el orden de la segmentación: Perros: Purina One - Dog Chow - Alpo y Gatos: Purina One - Cat Chow - Felix - Gatsy (cuando enuncia Gatsy menciona que "ahora es mas sabroso") | AR1: CM - Dan a conocer al cliente la actividad del "EVENTO CORPORATIVO DE OLIMPICA JUNIO"? | AS1: INDIQUE OBSERVACION Y/O NOVEDAD DEL MYSTERY REALIZADO
A2: NESTLE PURINA | B2: BARRANQUILLA | C2: AGRO/PSHOP/VET | D2: 191495 | E2: CLINICA VETERINARIA SHARPEY | F2: 1 | G2: GESTION IMPULSO - JUNIO 2025 | H2: 45825 | I2: 27498086 | J2: NestleP.5 | K2: SI | L2: SI | M2: SI | N2: SI | O2: SI | P2: NO | Q2: SI | R2: SI | S2: NO | T2: NO | U2: NO | V2: NO | W2: SI | X2: SI | Y2: SI | Z2: ESPECIALIZADO | AA2: SI | AB2: NO | AC2: NO | AD2: NO | AE2: SI | AF2: NO TIENE DINERO | AG2: SI | AH2: SI | AI2: SI | AJ2: SI | AK2: NO
A3: NESTLE PURINA | B3: BARRANQUILLA | C3: OLIMPICA | D3: 126325 | E3: 126325-OLIMPICA STO 039 CHIQUINQUIRA | F3: 1 | G3: GESTION IMPULSO - JUNIO 2025 | H3: 45834.417 | I3: 27531935 | J3: NestleP.5 | K3: SI | L3: SI | M3: SI | N3: SI | O3: SI | P3: NO | Q3: SI | R3: SI | S3: NO | T3: NO | U3: NO | V3: NO | W3: SI | X3: SI | Y3: NO | Z3: MODERNO | AF3: NO TIENE DINERO | AG3: SI | AH3: SI | AI3: SI | AJ3: SI | AK3: NO | AL3: NO | AM3: NO | AN3: NO | AO3: NO | AP3: SI | AQ3: SI | AR3: SI
A4: NESTLE PURINA | B4: BARRANQUILLA | C4: OLIMPICA | D4: 447964 | E4: 447964-MAKRO BARRANQUILLA | F4: 1 | G4: GESTION IMPULSO - JUNIO 2025 | H4: 45825 | I4: 27521942 | J4: NestleP.5 | K4: SI | L4: SI | M4: SI | N4: SI | O4: SI | P4: NO | Q4: SI | R4: SI | S4: NO | T4: NO | U4: NO | V4: NO | W4: SI | X4: SI | Y4: NO | Z4: MODERNO | AF4: NO LE INTERESA EL PRODUCTO | AG4: SI | AH4: SI | AI4: SI | AJ4: SI | AK4: NO | AL4: NO | AM4: NO | AN4: NO | AO4: NO | AP4: NO | AQ4: NO | AR4: NO
A5: NESTLE PURINA | B5: BARRANQUILLA | C5: SUPERETE | D5: 65453 | E5: DISTRIBUCIONES MILENA | F5: 1 | G5: GESTION IMPULSO - JUNIO 2025 | H5: 45826 | I5: 27498090 | J5: NestleP.5 | K5: SI | L5: SI | M5: SI | N5: SI | O5: SI | P5: NO | Q5: SI | R5: SI | S5: NO | T5: NO | U5: NO | V5: NO | W5: SI | X5: SI | Y5: SI | Z5: ESPECIALIZADO | AA5: SI | AB5: SI | AC5: SI | AD5: SI | AE5: SI | AF5: NO TIENE DINERO | AG5: SI | AH5: SI | AI5: SI | AJ5: SI | AK5: NO
A6: NESTLE PURINA | B6: BOGOTA | C6: AGRO/PSHOP/VET | D6: 355955 | E6: MUNDO MASCOTAS TABORA | F6: 1 | G6: GESTION IMPULSO - JUNIO 2025 | H6: 45815 | I6: 27420844 | J6: NestleP.1 | K6: SI | L6: SI | M6: SI | N6: SI | O6: SI | P6: NO | Q6: SI | R6: SI | S6: NO | T6: NO | U6: NO | V6: NO | W6: SI | X6: NO | Y6: SI | Z6: ESPECIALIZADO | AA6: SI | AB6: SI | AC6: SI | AD6: NO | AE6: NO | AF6: NO TIENE DINERO | AG6: SI | AH6: SI | AI6: SI | AJ6: SI | AK6: NO
A7: NESTLE PURINA | B7: BOGOTA | C7: AGRO/PSHOP/VET | D7: 435142 | E7: KUMPET 94 | F7: 1 | G7: GESTION IMPULSO - JUNIO 2025 | H7: 45835 | I7: 27593677 | J7: NestleP.1 | K7: SI | L7: SI | M7: SI | N7: SI | O7: SI | P7: NO | Q7: SI | R7: SI | S7: NO | T7: NO | U7: NO | V7: NO | W7: SI | X7: NO | Y7: SI | Z7: ESPECIALIZADO | AA7: SI | AB7: SI | AC7: SI | AD7: SI | AE7: SI | AF7: NO TIENE DINERO | AG7: SI | AH7: SI | AI7: NO | AJ7: SI | AK7: SI | AS7: La asesora tuvo una atención inpecable ya que resolvió todas mis dudas y me dio consejos para llevar un mejor manejo con mi animal
A8: NESTLE PURINA | B8: BOGOTA | C8: EXITO | D8: 12394 | E8: 12394-EXITO CALLE 80 | F8: 1 | G8: GESTION IMPULSO - JUNIO 2025 | H8: 45815 | I8: 27444590 | J8: NestleP.2 | K8: NO | L8: NO | M8: NO | N8: NO | O8: NO | P8: NO | Q8: NO | R8: NO | S8: NO | T8: NO | U8: NO | V8: NO | W8: NO | X8: NO | Y8: NO | Z8: MODERNO | AF8: NO LE INTERESA EL PRODUCTO | AG8: NO | AH8: NO | AI8: NO | AJ8: NO | AK8: SI | AL8: NO | AM8: NO | AN8: NO | AO8: NO | AP8: NO | AQ8: NO | AR8: NO | AS8: Se visita el pdv en horario asignado, se espera pero nunca llegó, de graba video 1 y 2
A9: NESTLE PURINA | B9: BOGOTA | C9: EXITO | D9: 108903 | E9: 108903-LA RES CENTRO | F9: 1 | G9: GESTION IMPULSO - JUNIO 2025 | H9: 45818 | I9: 27450345 | J9: NestleP.2 | K9: SI | L9: SI | M9: SI | N9: SI | O9: SI | P9: NO | Q9: SI | R9: SI | S9: NO | T9: NO | U9: NO | V9: NO | W9: SI | X9: SI | Y9: SI | Z9: ESPECIALIZADO | AA9: SI | AB9: SI | AC9: SI | AD9: SI | AE9: NO | AF9: NO TIENE DINERO | AG9: SI | AH9: SI | AI9: SI | AJ9: SI | AK9: NO
A10: NESTLE PURINA | B10: BOGOTA | C10: EXITO | D10: 442719 | E10: 442719-EXITO COLINA | F10: 1 | G10: GESTION IMPULSO - JUNIO 2025 | H10: 45821 | I10: 27486785 | J10: NestleP.2 | K10: SI | L10: SI | M10: SI | N10: SI | O10: SI | P10: NO | Q10: SI | R10: SI | S10: NO | T10: NO | U10: NO | V10: NO | W10: SI | X10: SI | Y10: SI | Z10: MODERNO | AF10: NO TIENE DINERO | AG10: SI | AH10: SI | AI10: SI | AJ10: SI | AK10: NO | AL10: SI | AM10: SI | AN10: SI | AO10: SI | AP10: SI | AQ10: SI | AR10: NO
A11: NESTLE PURINA | B11: BOGOTA | C11: EXITO | D11: 454996 | E11: 454996-LAIKA 116 | F11: 1 | G11: GESTION IMPULSO - JUNIO 2025 | H11: 45819 | I11: 27453760 | J11: NestleP.2 | K11: NO | L11: NO | M11: NO | N11: NO | O11: NO | P11: NO | Q11: NO | R11: NO | S11: NO | T11: NO | U11: NO | V11: NO | W11: NO | X11: NO | Y11: NO | Z11: ESPECIALIZADO | AA11: NO | AB11: NO | AC11: NO | AD11: NO | AE11: NO | AF11: FALTA DE PRODUCTO | AG11: NO | AH11: NO | AI11: NO | AJ11: NO | AK11: SI | AS11: Se visita pdv en el tiempo indicado , no se encuentra asesor
A12: NESTLE PURINA | B12: BOGOTA | C12: JUMBO | D12: 12565 | E12: 12565-JUMBO SANTA ANA | F12: 1 | G12: GESTION IMPULSO - JUNIO 2025 | H12: 45826 | I12: 27689425 | J12: NestleP.1 | K12: SI | L12: SI | M12: SI | N12: SI | O12: SI | P12: NO | Q12: SI | R12: SI | S12: NO | T12: NO | U12: NO | V12: NO | W12: SI | X12: SI | Y12: SI | Z12: MODERNO | AF12: NO TIENE DINERO | AG12: SI | AH12: SI | AI12: NO | AJ12: SI | AK12: NO | AL12: SI | AM12: SI | AN12: SI | AO12: SI | AP12: SI | AQ12: SI | AR12: SI
A13: NESTLE PURINA | B13: BOGOTA | C13: JUMBO | D13: 12662 | E13: 12662-JUMBO TITAN BOGOTA | F13: 1 | G13: GESTION IMPULSO - JUNIO 2025 | H13: 45822 | I13: 27484800 | J13: NestleP.2 | K13: NO | L13: NO | M13: NO | N13: NO | O13: NO | P13: NO | Q13: NO | R13: NO | S13: NO | T13: NO | U13: NO | V13: NO | W13: NO | X13: NO | Y13: NO | Z13: MODERNO | AF13: FALTA DE PRODUCTO | AG13: NO | AH13: NO | AI13: NO | AJ13: NO | AK13: SI | AL13: NO | AM13: NO | AN13: NO | AO13: NO | AP13: NO | AQ13: NO | AR13: NO | AS13: Se visita pdv en horario establecido no se encuentra asesor
A14: NESTLE PURINA | B14: BOGOTA | C14: JUMBO | D14: 406974 | E14: 406974-JUMBO 170 | F14: 1 | G14: GESTION IMPULSO - JUNIO 2025 | H14: 45833 | I14: 27684336 | J14: NestleP.2 | K14: SI | L14: SI | M14: SI | N14: SI | O14: SI | P14: NO | Q14: SI | R14: SI | S14: NO | T14: NO | U14: NO | V14: NO | W14: NO | X14: SI | Y14: NO | Z14: MODERNO | AF14: NO LE INTERESA EL PRODUCTO | AG14: NO | AH14: SI | AI14: NO | AJ14: NO | AK14: SI | AL14: SI | AM14: NO | AN14: NO | AO14: NO | AP14: SI | AQ14: NO | AR14: NO | AS14: No me indica información.clara, me toco abordarlo por que no aborda,
A15: NESTLE PURINA | B15: CALI | C15: AGRO/PSHOP/VET | D15: 356594 | E15: SUPERMASCOTAS CIUDAD JARDIN | F15: 1 | G15: GESTION IMPULSO - JUNIO 2025 | H15: 45822 | I15: 27480859 | J15: NestleP.7 | K15: SI | L15: SI | M15: SI | N15: SI | O15: SI | P15: NO | Q15: SI | R15: SI | S15: NO | T15: NO | U15: NO | V15: NO | W15: SI | X15: SI | Y15: SI | Z15: ESPECIALIZADO | AA15: SI | AB15: NO | AC15: NO | AD15: NO | AE15: SI | AF15: NO TIENE DINERO | AG15: SI | AH15: SI | AI15: SI | AJ15: SI | AK15: NO
A16: NESTLE PURINA | B16: CALI | C16: AGROPECUARIA LA HACIENDA Y CIA S.A.S | D16: 356625 | E16: 356625-AGRO LA HACIENDA SAS SUR | F16: 1 | G16: GESTION IMPULSO - JUNIO 2025 | H16: 45825 | I16: 27493887 | J16: NestleP.7 | K16: SI | L16: SI | M16: SI | N16: SI | O16: SI | P16: NO | Q16: SI | R16: SI | S16: NO | T16: NO | U16: NO | V16: NO | W16: SI | X16: SI | Y16: SI | Z16: ESPECIALIZADO | AA16: NO | AB16: NO | AC16: NO | AD16: NO | AE16: NO | AF16: NO LE INTERESA EL PRODUCTO | AG16: SI | AH16: SI | AI16: SI | AJ16: SI | AK16: NO
A17: NESTLE PURINA | B17: CALI | C17: MERCA Z | D17: 365377 | E17: 365377-Su Papa Lopez | F17: 2 | G17: GESTION IMPULSO - JUNIO 2025 | H17: 45834 | I17: 27685551 | J17: NestleP.7 | K17: NO | L17: NO | M17: NO | N17: NO | O17: NO | P17: NO | Q17: NO | R17: NO | S17: NO | T17: NO | U17: NO | V17: NO | W17: NO | X17: NO | Y17: NO | Z17: MODERNO | AF17: NO LE INTERESA EL PRODUCTO | AG17: NO | AH17: NO | AI17: NO | AJ17: NO | AK17: SI | AL17: NO | AM17: NO | AN17: NO | AO17: NO | AP17: NO | AQ17: NO | AR17: NO
A18: NESTLE PURINA | B18: CALI | C18: OLIMPICA | D18: 13555 | E18: 13555-OLIMPICA STO 137 VILLA COLOMBIA | F18: 1 | G18: GESTION IMPULSO - JUNIO 2025 | H18: 45821 | I18: 27476525 | J18: NestleP.7 | K18: NO | L18: NO | M18: NO | N18: NO | O18: NO | P18: NO | Q18: NO | R18: NO | S18: NO | T18: NO | U18: NO | V18: NO | W18: NO | X18: NO | Y18: NO | Z18: MODERNO | AF18: NO LE INTERESA EL PRODUCTO | AG18: NO | AH18: NO | AI18: NO | AJ18: NO | AK18: SI | AL18: NO | AM18: NO | AN18: NO | AO18: NO | AP18: NO | AQ18: NO | AR18: NO | AS18: En el pdv no se encuentra la activadora se informa y la supervisora indica que esta retrazada en la ruta
A19: NESTLE PURINA | B19: MEDELLIN | C19: CARULLA | D19: 428025 | E19: 428025-CARULLA RINCON DE OVIEDO | F19: 1 | G19: GESTION IMPULSO - JUNIO 2025 | H19: 45818 | I19: 27444155 | J19: NestleP.11 | K19: SI | L19: SI | M19: SI | N19: SI | O19: SI | P19: NO | Q19: SI | R19: SI | S19: NO | T19: NO | U19: NO | V19: NO | W19: NO | X19: SI | Y19: SI | Z19: MODERNO | AF19: NO TIENE DINERO | AG19: SI | AH19: SI | AI19: SI | AJ19: SI | AK19: SI | AL19: SI | AM19: NO | AN19: SI | AO19: NO | AP19: SI | AQ19: SI | AR19: NO | AS19: La chica no aborda inmediatamente, se veía que estaba capturando información del punto de venta por lo que le pido ayuda, da una asesoría completa, ofrece beneficios, busca satisfacer o cumplir con las necesidades que tengo ofreciendo un producto acorde, cuando se indica que es costoso, dice que hay otra presentación, me enseña la ofertas disponibles, me indica promociones entre otros.

Sheet Export
A1: ACTIVIDAD | B1: REGIONAL | C1: CIUDAD | D1: CANAL | E1: CADENA | F1: SUBCADENA | G1: ZONA | H1: RV | I1: CODIGO PDV | J1: NOMBRE COMERCIAL | K1: CODIGO EAN | L1: TIPO PUNTO VENTA | M1: CONSECUTIVO ENCUESTA | N1: NOMBRE ENCUESTA | O1: PREGUNTA | P1: RESPUESTA | Q1: CODIGO FOTO | R1: OBSERVACION | S1: FECHA VISITA | T1: FECHA INICIO VISITA | U1: FECHA CREACIÓN RESPUESTA | V1: CODIGO RUTA | W1: CLIENTE | X1: CODIGO EXHIBICION | Y1: NOMBRE EXHIBICION | Z1: NOMBRE USUARIO | AA1: USUARIO | AB1: NOMBRE SUPERVISOR | AC1: USUARIO SUPERVISOR
A2: NESTLE PURINA | B2: CENTRO | C2: BOGOTA | D2: ESPECIALIZADO | E2: AGRO/PSHOP/VET | F2: AGRO/PSHOP/VET | G2: CENTRO | I2: 355955 | J2: MUNDO MASCOTAS TABORA | L2: Impulso | M2: 1 | N2: GESTION IMPULSO - JUNIO 2025 | O2: SE LOGRA REALIZAR EL MYSTERY? | P2: SI | S2: 07/06/2025 00:00:00 | T2: 07/06/2025 11:22:14 | U2: 10/06/2025 08:54:47 | V2: 27420844 | W2: PRODUCTIVIDAD | Z2: User 1 | AA2: NestleP.1 | AB2: CAMILO MONTAÑO RESTREPO | AC2: camilo.montano
A3: NESTLE PURINA | B3: CENTRO | C3: BOGOTA | D3: ESPECIALIZADO | E3: AGRO/PSHOP/VET | F3: AGRO/PSHOP/VET | G3: CENTRO | I3: 355955 | J3: MUNDO MASCOTAS TABORA | L3: Impulso | M3: 1 | N3: GESTION IMPULSO - JUNIO 2025 | O3: ¿CUMPLE HORARIO DE ENTRADA O SALIDA DE LA TIENDA? | P3: SI | S3: 07/06/2025 00:00:00 | T3: 07/06/2025 11:22:14 | U3: 10/06/2025 08:54:47 | V3: 27420844 | W3: PRODUCTIVIDAD | Z3: User 1 | AA3: NestleP.1 | AB3: CAMILO MONTAÑO RESTREPO | AC3: camilo.montano
A4: NESTLE PURINA | B4: CENTRO | C4: BOGOTA | D4: ESPECIALIZADO | E4: AGRO/PSHOP/VET | F4: AGRO/PSHOP/VET | G4: CENTRO | I4: 355955 | J4: MUNDO MASCOTAS TABORA | L4: Impulso | M4: 1 | N4: GESTION IMPULSO - JUNIO 2025 | O4: CUENTA CON PANTALON DEL UNIFORME SEGÚN EL CARGO (NEGRO / ROJO / TURQUESA / JEAN) | P4: SI | S4: 07/06/2025 00:00:00 | T4: 07/06/2025 11:22:14 | U4: 10/06/2025 08:54:47 | V4: 27420844 | W4: PRODUCTIVIDAD | Z4: User 1 | AA4: NestleP.1 | AB4: CAMILO MONTAÑO RESTREPO | AC4: camilo.montano
A5: NESTLE PURINA | B5: CENTRO | C5: BOGOTA | D5: ESPECIALIZADO | E5: AGRO/PSHOP/VET | F5: AGRO/PSHOP/VET | G5: CENTRO | I5: 355955 | J5: MUNDO MASCOTAS TABORA | L5: Impulso | M5: 1 | N5: GESTION IMPULSO - JUNIO 2025 | O5: CUENTA CON CAMISA DEL UNIFORME Y LOGOS SEGÚN EL CARGO (NEGRA / GRIS / ROJA / TURQUESA) (Es permitido usar debajo de la camisa buso manga larga Negro) | P5: SI | S5: 07/06/2025 00:00:00 | T5: 07/06/2025 11:22:14 | U5: 10/06/2025 08:54:47 | V5: 27420844 | W5: PRODUCTIVIDAD | Z5: User 1 | AA5: NestleP.1 | AB5: CAMILO MONTAÑO RESTREPO | AC5: camilo.montano
A6: NESTLE PURINA | B6: CENTRO | C6: BOGOTA | D6: ESPECIALIZADO | E6: AGRO/PSHOP/VET | F6: AGRO/PSHOP/VET | G6: CENTRO | I6: 355955 | J6: MUNDO MASCOTAS TABORA | L6: Impulso | M6: 1 | N6: GESTION IMPULSO - JUNIO 2025 | O6: CUENTA CON CALZADO DE ACUERDO AL UNIFORME | P6: SI | S6: 07/06/2025 00:00:00 | T6: 07/06/2025 11:22:14 | U6: 10/06/2025 08:54:47 | V6: 27420844 | W6: PRODUCTIVIDAD | Z6: User 1 | AA6: NestleP.1 | AB6: CAMILO MONTAÑO RESTREPO | AC6: camilo.montano
A7: NESTLE PURINA | B7: CENTRO | C7: BOGOTA | D7: ESPECIALIZADO | E7: AGRO/PSHOP/VET | F7: AGRO/PSHOP/VET | G7: CENTRO | I7: 355955 | J7: MUNDO MASCOTAS TABORA | L7: Impulso | M7: 1 | N7: GESTION IMPULSO - JUNIO 2025 | O7: POSEE ALGUNA PRENDA ENCIMA DEL UNIFORME NO AUTORIZADA POR LA MARCA (Unicamente esta permitido chaleco de Sodimac y Easy) | P7: NO | S7: 07/06/2025 00:00:00 | T7: 07/06/2025 11:22:14 | U7: 10/06/2025 08:54:47 | V7: 27420844 | W7: PRODUCTIVIDAD | Z7: User 1 | AA7: NestleP.1 | AB7: CAMILO MONTAÑO RESTREPO | AC7: camilo.montano
A8: NESTLE PURINA | B8: CENTRO | C8: BOGOTA | D8: ESPECIALIZADO | E8: AGRO/PSHOP/VET | F8: AGRO/PSHOP/VET | G8: CENTRO | I8: 355955 | J8: MUNDO MASCOTAS TABORA | L8: Impulso | M8: 1 | N8: GESTION IMPULSO - JUNIO 2025 | O8: EL UNIFORME Y ZAPATOS SE ENCUENTRAN LIMPIOS Y EN BUEN ESTADO | P8: SI | S8: 07/06/2025 00:00:00 | T8: 07/06/2025 11:22:14 | U8: 10/06/2025 08:54:47 | V8: 27420844 | W8: PRODUCTIVIDAD | Z8: User 1 | AA8: NestleP.1 | AB8: CAMILO MONTAÑO RESTREPO | AC8: camilo.montano
A9: NESTLE PURINA | B9: CENTRO | C9: BOGOTA | D9: ESPECIALIZADO | E9: AGRO/PSHOP/VET | F9: AGRO/PSHOP/VET | G9: CENTRO | I9: 355955 | J9: MUNDO MASCOTAS TABORA | L9: Impulso | M9: 1 | N9: GESTION IMPULSO - JUNIO 2025 | O9: SU CABELLO LUCE LIMPIO, ORGANIZADO O RECOGIDO | P9: SI | S9: 07/06/2025 00:00:00 | T9: 07/06/2025 11:22:14 | U9: 10/06/2025 08:54:47 | V9: 27420844 | W9: PRODUCTIVIDAD | Z9: User 1 | AA9: NestleP.1 | AB9: CAMILO MONTAÑO RESTREPO | AC9: camilo.montano
A10: NESTLE PURINA | B10: CENTRO | C10: BOGOTA | D10: ESPECIALIZADO | E10: AGRO/PSHOP/VET | F10: AGRO/PSHOP/VET | G10: CENTRO | I10: 355955 | J10: MUNDO MASCOTAS TABORA | L10: Impulso | M10: 1 | N10: GESTION IMPULSO - JUNIO 2025 | O10: PRESENTA EXCESO DE MAQUILLAJE QUE NO CUMPLE CON EL CODIGO DE VESTIMENTA | P10: NO | S10: 07/06/2025 00:00:00 | T10: 07/06/2025 11:22:14 | U10: 10/06/2025 08:54:47 | V10: 27420844 | W10: PRODUCTIVIDAD | Z10: User 1 | AA10: NestleP.1 | AB10: CAMILO MONTAÑO RESTREPO | AC10: camilo.montano
A11: NESTLE PURINA | B11: CENTRO | C11: BOGOTA | D11: ESPECIALIZADO | E11: AGRO/PSHOP/VET | F11: AGRO/PSHOP/VET | G11: CENTRO | I11: 355955 | J11: MUNDO MASCOTAS TABORA | L11: Impulso | M11: 1 | N11: GESTION IMPULSO - JUNIO 2025 | O11: TIENE TATUAJES O PIERCINGS VISIBLES QUE NO CUMPLE CON EL CODIGO DE VESTIMENTA | P11: NO | S11: 07/06/2025 00:00:00 | T11: 07/06/2025 11:22:14 | U11: 10/06/2025 08:54:47 | V11: 27420844 | W11: PRODUCTIVIDAD | Z11: User 1 | AA11: NestleP.1 | AB11: CAMILO MONTAÑO RESTREPO | AC11: camilo.montano
A12: NESTLE PURINA | B12: CENTRO | C12: BOGOTA | D12: ESPECIALIZADO | E12: AGRO/PSHOP/VET | F12: AGRO/PSHOP/VET | G12: CENTRO | I12: 355955 | J12: MUNDO MASCOTAS TABORA | L12: Impulso | M12: 1 | N12: GESTION IMPULSO - JUNIO 2025 | O12: TIENE UÑAS LLAMATIVAS Y/O LARGAS QUE NO CUMPLE CON EL CODIGO DE VESTIMENTA | P12: NO | S12: 07/06/2025 00:00:00 | T12: 07/06/2025 11:22:14 | U12: 10/06/2025 08:54:47 | V12: 27420844 | W12: PRODUCTIVIDAD | Z12: User 1 | AA12: NestleP.1 | AB12: CAMILO MONTAÑO RESTREPO | AC12: camilo.montano
A13: NESTLE PURINA | B13: CENTRO | C13: BOGOTA | D13: ESPECIALIZADO | E13: AGRO/PSHOP/VET | F13: AGRO/PSHOP/VET | G13: CENTRO | I13: 355955 | J13: MUNDO MASCOTAS TABORA | L13: Impulso | M13: 1 | N13: GESTION IMPULSO - JUNIO 2025 | O13: USA ACCESORIOS QUE NO CUMPLE CON EL CODIGO DE VESTIMENTA | P13: NO | S13: 07/06/2025 00:00:00 | T13: 07/06/2025 11:22:14 | U13: 10/06/2025 08:54:47 | V13: 27420844 | W13: PRODUCTIVIDAD | Z13: User 1 | AA13: NestleP.1 | AB13: CAMILO MONTAÑO RESTREPO | AC13: camilo.montano
... A58: NESTLE PURINA | B58: ANTIOQUIA | C58: MEDELLIN | D58: MODERNO | E58: CARULLA | F58: 338 CARULLA OVIEDO | G58: MEDELLIN | I58: 428025 | J58: 428025-CARULLA RINCON DE OVIEDO | L58: CARULLA OVIEDO | M58: 1 | N58: GESTION IMPULSO - JUNIO 2025 | O58: INDIQUE OBSERVACION Y/O NOVEDAD DEL MYSTERY REALIZADO | P58: La chica no aborda inmediatamente, se veía que estaba capturando información del punto de venta por lo que le pido ayuda, da una asesoría completa, ofrece beneficios, busca satisfacer o cumplir con las necesidades que tengo ofreciendo un producto acorde, cuando se indica que es costoso, dice que hay otra presentación, me enseña la ofertas disponibles, me indica promociones entre otros. | S58: 10/06/2025 00:00:00 | T58: 10/06/2025 17:42:44 | U58: 10/06/2025 17:57:53 | V58: 27444155 | W58: PRODUCTIVIDAD | Z58: User 11 | AA58: NestleP.11 | AB58: CAMILO MONTAÑO RESTREPO | AC58: camilo.montano
A59: NESTLE PURINA | B59: CENTRO | C59: BOGOTA | D59: MODERNO | E59: EXITO | F59: EXITO | G59: BOGOTA | I59: 12394 | J59: 12394-EXITO CALLE 80 | K59: 7701001008615 | L59: EXITO CALLE 80 | M59: 1 | N59: GESTION IMPULSO - JUNIO 2025 | O59: SE LOGRA REALIZAR EL MYSTERY? | P59: NO | S59: 07/06/2025 00:00:00 | T59: 10/06/2025 22:25:32 | U59: 10/06/2025 22:27:59 | V59: 27444590 | W59: PRODUCTIVIDAD | Z59: User 2 | AA59: NestleP.2 | AB59: CAMILO MONTAÑO RESTREPO | AC59: camilo.montano
A60: NESTLE PURINA | B60: CENTRO | C60: BOGOTA | D60: MODERNO | E60: EXITO | F60: EXITO | G60: BOGOTA | I60: 12394 | J60: 12394-EXITO CALLE 80 | K60: 7701001008615 | L60: EXITO CALLE 80 | M60: 1 | N60: GESTION IMPULSO - JUNIO 2025 | O60: ¿CUMPLE HORARIO DE ENTRADA O SALIDA DE LA TIENDA? | P60: NO | S60: 07/06/2025 00:00:00 | T60: 10/06/2025 22:25:32 | U60: 10/06/2025 22:27:59 | V60: 27444590 | W60: PRODUCTIVIDAD | Z60: User 2 | AA60: NestleP.2 | AB60: CAMILO MONTAÑO RESTREPO | AC60: camilo.montano
A61: NESTLE PURINA | B61: CENTRO | C61: BOGOTA | D61: MODERNO | E61: EXITO | F61: EXITO | G61: BOGOTA | I61: 12394 | J61: 12394-EXITO CALLE 80 | K61: 7701001008615 | L61: EXITO CALLE 80 | M61: 1 | N61: GESTION IMPULSO - JUNIO 2025 | O61: CUENTA CON PANTALON DEL UNIFORME SEGÚN EL CARGO (NEGRO / ROJO / TURQUESA / JEAN) | P61: NO | S61: 07/06/2025 00:00:00 | T61: 10/06/2025 22:25:32 | U61: 10/06/2025 22:27:59 | V61: 27444590 | W61: PRODUCTIVIDAD | Z61: User 2 | AA61: NestleP.2 | AB61: CAMILO MONTAÑO RESTREPO | AC61: camilo.montano
A62: NESTLE PURINA | B62: CENTRO | C62: BOGOTA | D62: MODERNO | E62: EXITO | F62: EXITO | G62: BOGOTA | I62: 12394 | J62: 12394-EXITO CALLE 80 | K62: 7701001008615 | L62: EXITO CALLE 80 | M62: 1 | N62: GESTION IMPULSO - JUNIO 2025 | O62: CUENTA CON CAMISA DEL UNIFORME Y LOGOS SEGÚN EL CARGO (NEGRA / GRIS / ROJA / TURQUESA) (Es permitido usar debajo de la camisa buso manga larga Negro) | P62: NO | S62: 07/06/2025 00:00:00 | T62: 10/06/2025 22:25:32 | U62: 10/06/2025 22:27:59 | V62: 27444590 | W62: PRODUCTIVIDAD | Z62: User 2 | AA62: NestleP.2 | AB62: CAMILO MONTAÑO RESTREPO | AC62: camilo.montano
A63: NESTLE PURINA | B63: CENTRO | C63: BOGOTA | D63: MODERNO | E63: EXITO | F63: EXITO | G63: BOGOTA | I63: 12394 | J63: 12394-EXITO CALLE 80 | K63: 7701001008615 | L63: EXITO CALLE 80 | M63: 1 | N63: GESTION IMPULSO - JUNIO 2025 | O63: CUENTA CON CALZADO DE ACUERDO AL UNIFORME | P63: NO | S63: 07/06/2025 00:00:00 | T63: 10/06/2025 22:25:32 | U63: 10/06/2025 22:27:59 | V63: 27444590 | W63: PRODUCTIVIDAD | Z63: User 2 | AA63: NestleP.2 | AB63: CAMILO MONTAÑO RESTREPO | AC63: camilo.montano
A64: NESTLE PURINA | B64: CENTRO | C64: BOGOTA | D64: MODERNO | E64: EXITO | F64: EXITO | G64: BOGOTA | I64: 12394 | J64: 12394-EXITO CALLE 80 | K64: 7701001008615 | L64: EXITO CALLE 80 | M64: 1 | N64: GESTION IMPULSO - JUNIO 2025 | O64: POSEE ALGUNA PRENDA ENCIMA DEL UNIFORME NO AUTORIZADA POR LA MARCA (Unicamente esta permitido chaleco de Sodimac y Easy) | P64: NO | S64: 07/06/2025 00:00:00 | T64: 10/06/2025 22:25:32 | U64: 10/06/2025 22:27:59 | V64: 27444590 | W64: PRODUCTIVIDAD | Z64: User 2 | AA64: NestleP.2 | AB64: CAMILO MONTAÑO RESTREPO | AC64: camilo.montano
A65: NESTLE PURINA | B65: CENTRO | C65: BOGOTA | D65: MODERNO | E65: EXITO | F65: EXITO | G65: BOGOTA | I65: 12394 | J65: 12394-EXITO CALLE 80 | K65: 7701001008615 | L65: EXITO CALLE 80 | M65: 1 | N65: GESTION IMPULSO - JUNIO 2025 | O65: EL UNIFORME Y ZAPATOS SE ENCUENTRAN LIMPIOS Y EN BUEN ESTADO | P65: NO | S65: 07/06/2025 00:00:00 | T65: 10/06/2025 22:25:32 | U65: 10/06/2025 22:27:59 | V65: 27444590 | W65: PRODUCTIVIDAD | Z65: User 2 | AA65: NestleP.2 | AB65: CAMILO MONTAÑO RESTREPO | AC65: camilo.montano
A66: NESTLE PURINA | B66: CENTRO | C66: BOGOTA | D66: MODERNO | E66: EXITO | F66: EXITO | G66: BOGOTA | I66: 12394 | J66: 12394-EXITO CALLE 80 | K66: 7701001008615 | L66: EXITO CALLE 80 | M66: 1 | N66: GESTION IMPULSO - JUNIO 2025 | O66: SU CABELLO LUCE LIMPIO, ORGANIZADO O RECOGIDO | P66: NO | S66: 07/06/2025 00:00:00 | T66: 10/06/2025 22:25:32 | U66: 10/06/2025 22:27:59 | V66: 27444590 | W66: PRODUCTIVIDAD | Z66: User 2 | AA66: NestleP.2 | AB66: CAMILO MONTAÑO RESTREPO | AC66: camilo.montano
A67: NESTLE PURINA | B67: CENTRO | C67: BOGOTA | D67: MODERNO | E67: EXITO | F67: EXITO | G67: BOGOTA | I67: 12394 | J67: 12394-EXITO CALLE 80 | K67: 7701001008615 | L67: EXITO CALLE 80 | M67: 1 | N67: GESTION IMPULSO - JUNIO 2025 | O67: PRESENTA EXCESO DE MAQUILLAJE QUE NO CUMPLE CON EL CODIGO DE VESTIMENTA | P67: NO | S67: 07/06/2025 00:00:00 | T67: 10/06/2025 22:25:32 | U67: 10/06/2025 22:27:59 | V67: 27444590 | W67: PRODUCTIVIDAD | Z67: User 2 | AA67: NestleP.2 | AB67: CAMILO MONTAÑO RESTREPO | AC67: camilo.montano
A68: NESTLE PURINA | B68: CENTRO | C68: BOGOTA | D68: MODERNO | E68: EXITO | F68: EXITO | G68: BOGOTA | I68: 12394 | J68: 12394-EXITO CALLE 80 | K68: 7701001008615 | L68: EXITO CALLE 80 | M68: 1 | N68: GESTION IMPULSO - JUNIO 2025 | O68: TIENE TATUAJES O PIERCINGS VISIBLES QUE NO CUMPLE CON EL CODIGO DE VESTIMENTA | P68: NO | S68: 07/06/2025 00:00:00 | T68: 10/06/2025 22:25:32 | U68: 10/06/2025 22:27:59 | V68: 27444590 | W68: PRODUCTIVIDAD | Z68: User 2 | AA68: NestleP.2 | AB68: CAMILO MONTAÑO RESTREPO | AC68: camilo.montano
A69: NESTLE PURINA | B69: CENTRO | C69: BOGOTA | D69: MODERNO | E69: EXITO | F69: EXITO | G69: BOGOTA | I69: 12394 | J69: 12394-EXITO CALLE 80 | K69: 7701001008615 | L69: EXITO CALLE 80 | M69: 1 | N69: GESTION IMPULSO - JUNIO 2025 | O69: TIENE UÑAS LLAMATIVAS Y/O LARGAS QUE NO CUMPLE CON EL CODIGO DE VESTIMENTA | P69: NO | S69: 07/06/2025 00:00:00 | T69: 10/06/2025 22:25:32 | U69: 10/06/2025 22:27:59 | V69: 27444590 | W69: PRODUCTIVIDAD | Z69: User 2 | AA69: NestleP.2 | AB69: CAMILO MONTAÑO RESTREPO | AC69: camilo.montano
A70: NESTLE PURINA | B70: CENTRO | C70: BOGOTA | D70: MODERNO | E70: EXITO | F70: EXITO | G70: BOGOTA | I70: 12394 | J70: 12394-EXITO CALLE 80 | K70: 7701001008615 | L70: EXITO CALLE 80 | M70: 1 | N70: GESTION IMPULSO - JUNIO 2025 | O70: USA ACCESORIOS QUE NO CUMPLE CON EL CODIGO DE VESTIMENTA | P70: NO | S70: 07/06/2025 00:00:00 | T70: 10/06/2025 22:25:32 | U70: 10/06/2025 22:27:59 | V70: 27444590 | W70: PRODUCTIVIDAD | Z70: User 2 | AA70: NestleP.2 | AB70: CAMILO MONTAÑO RESTREPO | AC70: camilo.montano
... A115: NESTLE PURINA | B115: CENTRO | C115: BOGOTA | D115: ESPECIALIZADO | E115: EXITO | F115: EXITO | G115: BOGOTA | I115: 108903 | J115: 108903-LA RES CENTRO | K115: 0 | L115: EXITO CALLE 80 | M115: 1 | N115: GESTION IMPULSO - JUNIO 2025 | O115: DESEA AÑADIR ALGUNA OBSERVACION Y/O NOVEDAD DEL MYSTERY REALIZADO? | P115: NO | S115: 10/06/2025 00:00:00 | T115: 11/06/2025 16:34:25 | U115: 11/06/2025 16:37:15 | V115: 27450345 | W115: PRODUCTIVIDAD | Z115: User 2 | AA115: NestleP.2 | AB115: CAMILO MONTAÑO RESTREPO | AC115: camilo.montano
A116: NESTLE PURINA | B116: CENTRO | C116: BOGOTA | D116: ESPECIALIZADO | E116: EXITO | F116: EXITO | G116: BOGOTA | I116: 454996 | J116: 454996-LAIKA 116 | L116: EXITO CALLE 80 | M116: 1 | N116: GESTION IMPULSO - JUNIO 2025 | O116: SE LOGRA REALIZAR EL MYSTERY? | P116: NO | S116: 11/06/2025 00:00:00 | T116: 11/06/2025 18:06:17 | U116: 11/06/2025 18:10:02 | V116: 27453760 | W116: PRODUCTIVIDAD | Z116: User 2 | AA116: NestleP.2 | AB116: CAMILO MONTAÑO RESTREPO | AC116: camilo.montano
A117: NESTLE PURINA | B117: CENTRO | C117: BOGOTA | D117: ESPECIALIZADO | E117: EXITO | F117: EXITO | G117: BOGOTA | I117: 454996 | J117: 454996-LAIKA 116 | L117: EXITO CALLE 80 | M117: 1 | N117: GESTION IMPULSO - JUNIO 2025 | O117: ¿CUMPLE HORARIO DE ENTRADA O SALIDA DE LA TIENDA? | P117: NO | S117: 11/06/2025 00:00:00 | T117: 11/06/2025 18:06:17 | U117: 11/06/2025 18:10:02 | V117: 27453760 | W117: PRODUCTIVIDAD | Z117: User 2 | AA117: NestleP.2 | AB117: CAMILO MONTAÑO RESTREPO | AC117: camilo.montano
A118: NESTLE PURINA | B118: CENTRO | C118: BOGOTA | D118: ESPECIALIZADO | E118: EXITO | F118: EXITO | G118: BOGOTA | I118: 454996 | J118: 454996-LAIKA 116 | L118: EXITO CALLE 80 | M118: 1 | N118: GESTION IMPULSO - JUNIO 2025 | O118: CUENTA CON PANTALON DEL UNIFORME SEGÚN EL CARGO (NEGRO / ROJO / TURQUESA / JEAN) | P118: NO | S118: 11/06/2025 00:00:00 | T118: 11/06/2025 18:06:17 | U118: 11/06/2025 18:10:02 | V118: 27453760 | W118: PRODUCTIVIDAD | Z118: User 2 | AA118: NestleP.2 | AB118: CAMILO MONTAÑO RESTREPO | AC118: camilo.montano
A119: NESTLE PURINA | B119: CENTRO | C119: BOGOTA | D119: ESPECIALIZADO | E119: EXITO | F119: EXITO | G119: BOGOTA | I119: 454996 | J119: 454996-LAIKA 116 | L119: EXITO CALLE 80 | M119: 1 | N119: GESTION IMPULSO - JUNIO 2025 | O119: CUENTA CON CAMISA DEL UNIFORME Y LOGOS SEGÚN EL CARGO (NEGRA / GRIS / ROJA / TURQUESA) (Es permitido usar debajo de la camisa buso manga larga Negro) | P119: NO | S119: 11/06/2025 00:00:00 | T119: 11/06/2025 18:06:17 | U119: 11/06/2025 18:10:02 | V119: 27453760 | W119: PRODUCTIVIDAD | Z119: User 2 | AA119: NestleP.2 | AB119: CAMILO MONTAÑO RESTREPO | AC119: camilo.montano
A120: NESTLE PURINA | B120: CENTRO | C120: BOGOTA | D120: ESPECIALIZADO | E120: EXITO | F120: EXITO | G120: BOGOTA | I120: 454996 | J120: 454996-LAIKA 116 | L120: EXITO CALLE 80 | M120: 1 | N120: GESTION IMPULSO - JUNIO 2025 | O120: CUENTA CON CALZADO DE ACUERDO AL UNIFORME | P120: NO | S120: 11/06/2025 00:00:00 | T120: 11/06/2025 18:06:17 | U120: 11/06/2025 18:10:02 | V120: 27453760 | W120: PRODUCTIVIDAD | Z120: User 2 | AA120: NestleP.2 | AB120: CAMILO MONTAÑO RESTREPO | AC120: camilo.montano
A121: NESTLE PURINA | B121: CENTRO | C121: BOGOTA | D121: ESPECIALIZADO | E121: EXITO | F121: EXITO | G121: BOGOTA | I121: 454996 | J121: 454996-LAIKA 116 | L121: EXITO CALLE 80 | M121: 1 | N121: GESTION IMPULSO - JUNIO 2025 | O121: POSEE ALGUNA PRENDA ENCIMA DEL UNIFORME NO AUTORIZADA POR LA MARCA (Unicamente esta permitido chaleco de Sodimac y Easy) | P121: NO | S121: 11/06/2025 00:00:00 | T121: 11/06/2025 18:06:17 | U121: 11/06/2025 18:10:02 | V121: 27453760 | W121: PRODUCTIVIDAD | Z121: User 2 | AA121: NestleP.2 | AB121: CAMILO MONTAÑO RESTREPO | AC121: camilo.montano
A122: NESTLE PURINA | B122: CENTRO | C122: BOGOTA | D122: ESPECIALIZADO | E122: EXITO | F122: EXITO | G122: BOGOTA | I122: 454996 | J122: 454996-LAIKA 116 | L122: EXITO CALLE 80 | M122: 1 | N122: GESTION IMPULSO - JUNIO 2025 | O122: EL UNIFORME Y ZAPATOS SE ENCUENTRAN LIMPIOS Y EN BUEN ESTADO | P122: NO | S122: 11/06/2025 00:00:00 | T122: 11/06/2025 18:06:17 | U122: 11/06/2025 18:10:02 | V122: 27453760 | W122: PRODUCTIVIDAD | Z122: User 2 | AA122: NestleP.2 | AB122: CAMILO MONTAÑO RESTREPO | AC122: camilo.montano
A123: NESTLE PURINA | B123: CENTRO | C123: BOGOTA | D123: ESPECIALIZADO | E123: EXITO | F123: EXITO | G123: BOGOTA | I123: 454996 | J123: 454996-LAIKA 116 | L123: EXITO CALLE 80 | M123: 1 | N123: GESTION IMPULSO - JUNIO 2025 | O123: SU CABELLO LUCE LIMPIO, ORGANIZADO O RECOGIDO | P123: NO | S123: 11/06/2025 00:00:00 | T123: 11/06/2025 18:06:17 | U123: 11/06/2025 18:10:02 | V123: 27453760 | W123: PRODUCTIVIDAD | Z123: User 2 | AA123: NestleP.2 | AB123: CAMILO MONTAÑO RESTREPO | AC123: camilo.montano
A124: NESTLE PURINA | B124: CENTRO | C124: BOGOTA | D124: ESPECIALIZADO | E124: EXITO | F124: EXITO | G124: BOGOTA | I124: 454996 | J124: 454996-LAIKA 116 | L124: EXITO CALLE 80 | M124: 1 | N124: GESTION IMPULSO - JUNIO 2025 | O124: PRESENTA EXCESO DE MAQUILLAJE QUE NO CUMPLE CON EL CODIGO DE VESTIMENTA | P124: NO | S124: 11/06/2025 00:00:00 | T124: 11/06/2025 18:06:17 | U124: 11/06/2025 18:10:02 | V124: 27453760 | W124: PRODUCTIVIDAD | Z124: User 2 | AA124: NestleP.2 | AB124: CAMILO MONTAÑO RESTREPO | AC124: camilo.montano
A125: NESTLE PURINA | B125: CENTRO | C125: BOGOTA | D125: ESPECIALIZADO | E125: EXITO | F125: EXITO | G125: BOGOTA | I125: 454996 | J125: 454996-LAIKA 116 | L125: EXITO CALLE 80 | M125: 1 | N125: GESTION IMPULSO - JUNIO 2025 | O125: TIENE TATUAJES O PIERCINGS VISIBLES QUE NO CUMPLE CON EL CODIGO DE VESTIMENTA | P125: NO | S125: 11/06/2025 00:00:00 | T125: 11/06/2025 18:06:17 | U125: 11/06/2025 18:10:02 | V125: 27453760 | W125: PRODUCTIVIDAD | Z125: User 2 | AA125: NestleP.2 | AB125: CAMILO MONTAÑO RESTREPO | AC125: camilo.montano
A126: NESTLE PURINA | B126: CENTRO | C126: BOGOTA | D126: ESPECIALIZADO | E126: EXITO | F126: EXITO | G126: BOGOTA | I126: 454996 | J126: 454996-LAIKA 116 | L126: EXITO CALLE 80 | M126: 1 | N126: GESTION IMPULSO - JUNIO 2025 | O126: TIENE UÑAS LLAMATIVAS Y/O LARGAS QUE NO CUMPLE CON EL CODIGO DE VESTIMENTA | P126: NO | S126: 11/06/2025 00:00:00 | T126: 11/06/2025 18:06:17 | U126: 11/06/2025 18:10:02 | V126: 27453760 | W126: PRODUCTIVIDAD | Z126: User 2 | AA126: NestleP.2 | AB126: CAMILO MONTAÑO RESTREPO | AC126: camilo.montano
A127: NESTLE PURINA | B127: CENTRO | C127: BOGOTA | D127: ESPECIALIZADO | E127: EXITO | F127: EXITO | G127: BOGOTA | I127: 454996 | J127: 454996-LAIKA 116 | L127: EXITO CALLE 80 | M127: 1 | N127: GESTION IMPULSO - JUNIO 2025 | O127: USA ACCESORIOS QUE NO CUMPLE CON EL CODIGO DE VESTIMENTA | P127: NO | S127: 11/06/2025 00:00:00 | T127: 11/06/2025 18:06:17 | U127: 11/06/2025 18:10:02 | V127: 27453760 | W127: PRODUCTIVIDAD | Z127: User 2 | AA127: NestleP.2 | AB127: CAMILO MONTAÑO RESTREPO | AC127: camilo.montano
... A143: NESTLE PURINA | B143: CENTRO | C143: BOGOTA | D143: ESPECIALIZADO | E143: EXITO | F143: EXITO | G143: BOGOTA | I143: 454996 | J143: 454996-LAIKA 116 | L143: EXITO CALLE 80 | M143: 1 | N143: GESTION IMPULSO - JUNIO 2025 | O143: INDIQUE OBSERVACION Y/O NOVEDAD DEL MYSTERY REALIZADO | P143: Se visita pdv en el tiempo indicado , no se encuentra asesor | S143: 11/06/2025 00:00:00 | T143: 11/06/2025 18:06:17 | U143: 11/06/2025 18:10:02 | V143: 27453760 | W143: PRODUCTIVIDAD | Z143: User 2 | AA143: NestleP.2 | AB143: CAMILO MONTAÑO RESTREPO | AC143: camilo.montano
A144: NESTLE PURINA | B144: PACIFICO | C144: CALI | D144: MODERNO | E144: OLIMPICA | F144: OLIMPICA | G144: CALI | I144: 13555 | J144: 13555-OLIMPICA STO 137 VILLA COLOMBIA | K144: SAP993225 | L144: CADENA - OLIMPICA - CALI | M144: 1 | N144: GESTION IMPULSO - JUNIO 2025 | O144: SE LOGRA REALIZAR EL MYSTERY? | P144: NO | S144: 13/06/2025 00:00:00 | T144: 13/06/2025 21:30:09 | U144: 13/06/2025 21:37:38 | V144: 27476525 | W144: PRODUCTIVIDAD | Z144: User 7 | AA144: NestleP.7 | AB144: CAMILO MONTAÑO RESTREPO | AC144: camilo.montano
A145: NESTLE PURINA | B145: PACIFICO | C145: CALI | D145: MODERNO | E145: OLIMPICA | F145: OLIMPICA | G145: CALI | I145: 13555 | J145: 13555-OLIMPICA STO 137 VILLA COLOMBIA | K145: SAP993225 | L145: CADENA - OLIMPICA - CALI | M145: 1 | N145: GESTION IMPULSO - JUNIO 2025 | O145: ¿CUMPLE HORARIO DE ENTRADA O SALIDA DE LA TIENDA? | P145: NO | S145: 13/06/2025 00:00:00 | T145: 13/06/2025 21:30:09 | U145: 13/06/2025 21:37:38 | V145: 27476525 | W145: PRODUCTIVIDAD | Z145: User 7 | AA145: NestleP.7 | AB145: CAMILO MONTAÑO RESTREPO | AC145: camilo.montano
A146: NESTLE PURINA | B146: PACIFICO | C146: CALI | D146: MODERNO | E146: OLIMPICA | F146: OLIMPICA | G146: CALI | I146: 13555 | J146: 13555-OLIMPICA STO 137 VILLA COLOMBIA | K146: SAP993225 | L146: CADENA - OLIMPICA - CALI | M146: 1 | N146: GESTION IMPULSO - JUNIO 2025 | O146: CUENTA CON PANTALON DEL UNIFORME SEGÚN EL CARGO (NEGRO / ROJO / TURQUESA / JEAN) | P146: NO | S146: 13/06/2025 00:00:00 | T146: 13/06/2025 21:30:09 | U146: 13/06/2025 21:37:38 | V146: 27476525 | W146: PRODUCTIVIDAD | Z146: User 7 | AA146: NestleP.7 | AB146: CAMILO MONTAÑO RESTREPO | AC146: camilo.montano
A147: NESTLE PURINA | B147: PACIFICO | C147: CALI | D147: MODERNO | E147: OLIMPICA | F147: OLIMPICA | G147: CALI | I147: 13555 | J147: 13555-OLIMPICA STO 137 VILLA COLOMBIA | K147: SAP993225 | L147: CADENA - OLIMPICA - CALI | M147: 1 | N147: GESTION IMPULSO - JUNIO 2025 | O147: CUENTA CON CAMISA DEL UNIFORME Y LOGOS SEGÚN EL CARGO (NEGRA / GRIS / ROJA / TURQUESA) (Es permitido usar debajo de la camisa buso manga larga Negro) | P147: NO | S147: 13/06/2025 00:00:00 | T147: 13/06/2025 21:30:09 | U147: 13/06/2025 21:37:38 | V147: 27476525 | W147: PRODUCTIVIDAD | Z147: User 7 | AA147: NestleP.7 | AB147: CAMILO MONTAÑO RESTREPO | AC147: camilo.montano
A148: NESTLE PURINA | B148: PACIFICO | C148: CALI | D148: MODERNO | E148: OLIMPICA | F148: OLIMPICA | G148: CALI | I148: 13555 | J148: 13555-OLIMPICA STO 137 VILLA COLOMBIA | K148: SAP993225 | L148: CADENA - OLIMPICA - CALI | M148: 1 | N148: GESTION IMPULSO - JUNIO 2025 | O148: CUENTA CON CALZADO DE ACUERDO AL UNIFORME | P148: NO | S148: 13/06/2025 00:00:00 | T148: 13/06/2025 21:30:09 | U148: 13/06/2025 21:37:38 | V148: 27476525 | W148: PRODUCTIVIDAD | Z148: User 7 | AA148: NestleP.7 | AB148: CAMILO MONTAÑO RESTREPO | AC148: camilo.montano
A149: NESTLE PURINA | B149: PACIFICO | C149: CALI | D149: MODERNO | E149: OLIMPICA | F149: OLIMPICA | G149: CALI | I149: 13555 | J149: 13555-OLIMPICA STO 137 VILLA COLOMBIA | K149: SAP993225 | L149: CADENA - OLIMPICA - CALI | M149: 1 | N149: GESTION IMPULSO - JUNIO 2025 | O149: POSEE ALGUNA PRENDA ENCIMA DEL UNIFORME NO AUTORIZADA POR LA MARCA (Unicamente esta permitido chaleco de Sodimac y Easy) | P149: NO | S149: 13/06/2025 00:00:00 | T149: 13/06/2025 21:30:09 | U149: 13/06/2025 21:37:38 | V149: 27476525 | W149: PRODUCTIVIDAD | Z149: User 7 | AA149: NestleP.7 | AB149: CAMILO MONTAÑO RESTREPO | AC149: camilo.montano
A150: NESTLE PURINA | B150: PACIFICO | C150: CALI | D150: MODERNO | E150: OLIMPICA | F150: OLIMPICA | G150: CALI | I150: 13555 | J150: 13555-OLIMPICA STO 137 VILLA COLOMBIA | K150: SAP993225 | L150: CADENA - OLIMPICA - CALI | M150: 1 | N150: GESTION IMPULSO - JUNIO 2025 | O150: EL UNIFORME Y ZAPATOS SE ENCUENTRAN LIMPIOS Y EN BUEN ESTADO | P150: NO | S150: 13/06/2025 00:00:00 | T150: 13/06/2025 21:30:09 | U150: 13/06/2025 21:37:38 | V150: 27476525 | W150: PRODUCTIVIDAD | Z150: User 7 | AA150: NestleP.7 | AB150: CAMILO MONTAÑO RESTREPO | AC150: camilo.montano
A151: NESTLE PURINA | B151: PACIFICO | C151: CALI | D151: MODERNO | E151: OLIMPICA | F151: OLIMPICA | G151: CALI | I151: 13555 | J151: 13555-OLIMPICA STO 137 VILLA COLOMBIA | K151: SAP993225 | L151: CADENA - OLIMPICA - CALI | M151: 1 | N151: GESTION IMPULSO - JUNIO 2025 | O151: SU CABELLO LUCE LIMPIO, ORGANIZADO O RECOGIDO | P151: NO | S151: 13/06/2025 00:00:00 | T151: 13/06/2025 21:30:09 | U151: 13/06/2025 21:37:38 | V151: 27476525 | W151: PRODUCTIVIDAD | Z151: User 7 | AA151: NestleP.7 | AB151: CAMILO MONTAÑO RESTREPO | AC151: camilo.montano
A152: NESTLE PURINA | B152: PACIFICO | C152: CALI | D152: MODERNO | E152: OLIMPICA | F152: OLIMPICA | G152: CALI | I152: 13555 | J152: 13555-OLIMPICA STO 137 VILLA COLOMBIA | K152: SAP993225 | L152: CADENA - OLIMPICA - CALI | M152: 1 | N152: GESTION IMPULSO - JUNIO 2025 | O152: PRESENTA EXCESO DE MAQUILLAJE QUE NO CUMPLE CON EL CODIGO DE VESTIMENTA | P152: NO | S152: 13/06/2025 00:00:00 | T152: 13/06/2025 21:30:09 | U152: 13/06/2025 21:37:38 | V152: 27476525 | W152: PRODUCTIVIDAD | Z152: User 7 | AA152: NestleP.7 | AB152: CAMILO MONTAÑO RESTREPO | AC152: camilo.montano
A153: NESTLE PURINA | B153: PACIFICO | C153: CALI | D153: MODERNO | E153: OLIMPICA | F153: OLIMPICA | G153: CALI | I153: 13555 | J153: 13555-OLIMPICA STO 137 VILLA COLOMBIA | K153: SAP993225 | L153: CADENA - OLIMPICA - CALI | M153: 1 | N153: GESTION IMPULSO - JUNIO 2025 | O153: TIENE TATUAJES O PIERCINGS VISIBLES QUE NO CUMPLE CON EL CODIGO DE VESTIMENTA | P153: NO | S153: 13/06/2025 00:00:00 | T153: 13/06/2025 21:30:09 | U153: 13/06/2025 21:37:38 | V153: 27476525 | W153: PRODUCTIVIDAD | Z153: User 7 | AA153: NestleP.7 | AB153: CAMILO MONTAÑO RESTREPO | AC153: camilo.montano
A154: NESTLE PURINA | B154: PACIFICO | C154: CALI | D154: MODERNO | E154: OLIMPICA | F154: OLIMPICA | G154: CALI | I154: 13555 | J154: 13555-OLIMPICA STO 137 VILLA COLOMBIA | K154: SAP993225 | L154: CADENA - OLIMPICA - CALI | M154: 1 | N154: GESTION IMPULSO - JUNIO 2025 | O154: TIENE UÑAS LLAMATIVAS Y/O LARGAS QUE NO CUMPLE CON EL CODIGO DE VESTIMENTA | P154: NO | S154: 13/06/2025 00:00:00 | T154: 13/06/2025 21:30:09 | U154: 13/06/2025 21:37:38 | V154: 27476525 | W154: PRODUCTIVIDAD | Z154: User 7 | AA154: NestleP.7 | AB154: CAMILO MONTAÑO RESTREPO | AC154: camilo.montano
A155: NESTLE PURINA | B155: PACIFICO | C155: CALI | D155: MODERNO | E155: OLIMPICA | F155: OLIMPICA | G155: CALI | I155: 13555 | J155: 13555-OLIMPICA STO 137 VILLA COLOMBIA | K155: SAP993225 | L155: CADENA - OLIMPICA - CALI | M155: 1 | N155: GESTION IMPULSO - JUNIO 2025 | O155: USA ACCESORIOS QUE NO CUMPLE CON EL CODIGO DE VESTIMENTA | P155: NO | S155: 13/06/2025 00:00:00 | T155: 13/06/2025 21:30:09 | U155: 13/06/2025 21:37:38 | V155: 27476525 | W155: PRODUCTIVIDAD | Z155: User 7 | AA155: NestleP.7 | AB155: CAMILO MONTAÑO RESTREPO | AC155: camilo.montano
... A230: NESTLE PURINA | B230: CENTRO | C230: BOGOTA | D230: MODERNO | E230: JUMBO | F230: JUMBO TITAN | G230: BOGOTA | I230: 12662 | J230: 12662-JUMBO TITAN BOGOTA | K230: 7707185371675 | L230: JUMBO TITAN | M230: 1 | N230: GESTION IMPULSO - JUNIO 2025 | O230: INDIQUE OBSERVACION Y/O NOVEDAD DEL MYSTERY REALIZADO | P230: Se visita pdv en horario establecido no se encuentra asesor | S230: 14/06/2025 00:00:00 | T230: 16/06/2025 11:51:09 | U230: 16/06/2025 11:55:22 | V230: 27484800 | W230: PRODUCTIVIDAD | Z230: User 2 | AA230: NestleP.2 | AB230: CAMILO MONTAÑO RESTREPO | AC230: camilo.montano
A231: NESTLE PURINA | B231: ORIENTE | C231: BOGOTA | D231: MODERNO | E231: EXITO | F231: EXITO | G231: BOGOTA | I231: 442719 | J231: 442719-EXITO COLINA | L231: EXITO CALLE 80 | M231: 1 | N231: GESTION IMPULSO - JUNIO 2025 | O231: SE LOGRA REALIZAR EL MYSTERY? | P231: SI | S231: 13/06/2025 00:00:00 | T231: 16/06/2025 16:49:11 | U231: 16/06/2025 16:51:46 | V231: 27486785 | W231: PRODUCTIVIDAD | Z231: User 2 | AA231: NestleP.2 | AB231: CAMILO MONTAÑO RESTREPO | AC231: camilo.montano
A232: NESTLE PURINA | B232: ORIENTE | C232: BOGOTA | D232: MODERNO | E232: EXITO | F232: EXITO | G232: BOGOTA | I232: 442719 | J232: 442719-EXITO COLINA | L232: EXITO CALLE 80 | M232: 1 | N232: GESTION IMPULSO - JUNIO 2025 | O232: ¿CUMPLE HORARIO DE ENTRADA O SALIDA DE LA TIENDA? | P232: SI | S232: 13/06/2025 00:00:00 | T232: 16/06/2025 16:49:11 | U232: 16/06/2025 16:51:46 | V232: 27486785 | W232: PRODUCTIVIDAD | Z232: User 2 | AA232: NestleP.2 | AB232: CAMILO MONTAÑO RESTREPO | AC232: camilo.montano
A233: NESTLE PURINA | B233: ORIENTE | C233: BOGOTA | D233: MODERNO | E233: EXITO | F233: EXITO | G233: BOGOTA | I233: 442719 | J233: 442719-EXITO COLINA | L233: EXITO CALLE 80 | M233: 1 | N233: GESTION IMPULSO - JUNIO 2025 | O233: CUENTA CON PANTALON DEL UNIFORME SEGÚN EL CARGO (NEGRO / ROJO / TURQUESA / JEAN) | P233: SI | S233: 13/06/2025 00:00:00 | T233: 16/06/2025 16:49:11 | U233: 16/06/2025 16:51:46 | V233: 27486785 | W233: PRODUCTIVIDAD | Z233: User 2 | AA233: NestleP.2 | AB233: CAMILO MONTAÑO RESTREPO | AC233: camilo.montano
A234: NESTLE PURINA | B234: ORIENTE | C234: BOGOTA | D234: MODERNO | E234: EXITO | F234: EXITO | G234: BOGOTA | I234: 442719 | J234: 442719-EXITO COLINA | L234: EXITO CALLE 80 | M234: 1 | N234: GESTION IMPULSO - JUNIO 2025 | O234: CUENTA CON CAMISA DEL UNIFORME Y LOGOS SEGÚN EL CARGO (NEGRA / GRIS / ROJA / TURQUESA) (Es permitido usar debajo de la camisa buso manga larga Negro) | P234: SI | S234: 13/06/2025 00:00:00 | T234: 16/06/2025 16:49:11 | U234: 16/06/2025 16:51:46 | V234: 27486785 | W234: PRODUCTIVIDAD | Z234: User 2 | AA234: NestleP.2 | AB234: CAMILO MONTAÑO RESTREPO | AC234: camilo.montano
A235: NESTLE PURINA | B235: ORIENTE | C235: BOGOTA | D235: MODERNO | E235: EXITO | F235: EXITO | G235: BOGOTA | I235: 442719 | J235: 442719-EXITO COLINA | L235: EXITO CALLE 80 | M235: 1 | N235: GESTION IMPULSO - JUNIO 2025 | O235: CUENTA CON CALZADO DE ACUERDO AL UNIFORME | P235: SI | S235: 13/06/2025 00:00:00 | T235: 16/06/2025 16:49:11 | U235: 16/06/2025 16:51:46 | V235: 27486785 | W235: PRODUCTIVIDAD | Z235: User 2 | AA235: NestleP.2 | AB235: CAMILO MONTAÑO RESTREPO | AC235: camilo.montano
A236: NESTLE PURINA | B236: ORIENTE | C236: BOGOTA | D236: MODERNO | E236: EXITO | F236: EXITO | G236: BOGOTA | I236: 442719 | J236: 442719-EXITO COLINA | L236: EXITO CALLE 80 | M236: 1 | N236: GESTION IMPULSO - JUNIO 2025 | O236: POSEE ALGUNA PRENDA ENCIMA DEL UNIFORME NO AUTORIZADA POR LA MARCA (Unicamente esta permitido chaleco de Sodimac y Easy) | P236: NO | S236: 13/06/2025 00:00:00 | T236: 16/06/2025 16:49:11 | U236: 16/06/2025 16:51:46 | V236: 27486785 | W236: PRODUCTIVIDAD | Z236: User 2 | AA236: NestleP.2 | AB236: CAMILO MONTAÑO RESTREPO | AC236: camilo.montano
A237: NESTLE PURINA | B237: ORIENTE | C237: BOGOTA | D237: MODERNO | E237: EXITO | F237: EXITO | G237: BOGOTA | I237: 442719 | J237: 442719-EXITO COLINA | L237: EXITO CALLE 80 | M237: 1 | N237: GESTION IMPULSO - JUNIO 2025 | O237: EL UNIFORME Y ZAPATOS SE ENCUENTRAN LIMPIOS Y EN BUEN ESTADO | P237: SI | S237: 13/06/2025 00:00:00 | T237: 16/06/2025 16:49:11 | U237: 16/06/2025 16:51:46 | V237: 27486785 | W237: PRODUCTIVIDAD | Z237: User 2 | AA237: NestleP.2 | AB237: CAMILO MONTAÑO RESTREPO | AC237: camilo.montano
A238: NESTLE PURINA | B238: ORIENTE | C238: BOGOTA | D238: MODERNO | E238: EXITO | F238: EXITO | G238: BOGOTA | I238: 442719 | J238: 442719-EXITO COLINA | L238: EXITO CALLE 80 | M238: 1 | N238: GESTION IMPULSO - JUNIO 2025 | O238: SU CABELLO LUCE LIMPIO, ORGANIZADO O RECOGIDO | P238: SI | S238: 13/06/2025 00:00:00 | T238: 16/06/2025 16:49:11 | U238: 16/06/2025 16:51:46 | V238: 27486785 | W238: PRODUCTIVIDAD | Z238: User 2 | AA238: NestleP.2 | AB238: CAMILO MONTAÑO RESTREPO | AC238: camilo.montano
A239: NESTLE PURINA | B239: ORIENTE | C239: BOGOTA | D239: MODERNO | E239: EXITO | F239: EXITO | G239: BOGOTA | I239: 442719 | J239: 442719-EXITO COLINA | L239: EXITO CALLE 80 | M239: 1 | N239: GESTION IMPULSO - JUNIO 2025 | O239: PRESENTA EXCESO DE MAQUILLAJE QUE NO CUMPLE CON EL CODIGO DE VESTIMENTA | P239: NO | S239: 13/06/2025 00:00:00 | T239: 16/06/2025 16:49:11 | U239: 16/06/2025 16:51:46 | V239: 27486785 | W239: PRODUCTIVIDAD | Z239: User 2 | AA239: NestleP.2 | AB239: CAMILO MONTAÑO RESTREPO | AC239: camilo.montano
A240: NESTLE PURINA | B240: ORIENTE | C240: BOGOTA | D240: MODERNO | E240: EXITO | F240: EXITO | G240: BOGOTA | I240: 442719 | J240: 442719-EXITO COLINA | L240: EXITO CALLE 80 | M240: 1 | N240: GESTION IMPULSO - JUNIO 2025 | O240: TIENE TATUAJES O PIERCINGS VISIBLES QUE NO CUMPLE CON EL CODIGO DE VESTIMENTA | P240: NO | S240: 13/06/2025 00:00:00 | T240: 16/06/2025 16:49:11 | U240: 16/06/2025 16:51:46 | V240: 27486785 | W240: PRODUCTIVIDAD | Z240: User 2 | AA240: NestleP.2 | AB240: CAMILO MONTAÑO RESTREPO | AC240: camilo.montano
A241: NESTLE PURINA | B241: ORIENTE | C241: BOGOTA | D241: MODERNO | E241: EXITO | F241: EXITO | G241: BOGOTA | I241: 442719 | J241: 442719-EXITO COLINA | L241: EXITO CALLE 80 | M241: 1 | N241: GESTION IMPULSO - JUNIO 2025 | O241: TIENE UÑAS LLAMATIVAS Y/O LARGAS QUE NO CUMPLE CON EL CODIGO DE VESTIMENTA | P241: NO | S241: 13/06/2025 00:00:00 | T241: 16/06/2025 16:49:11 | U241: 16/06/2025 16:51:46 | V241: 27486785 | W241: PRODUCTIVIDAD | Z241: User 2 | AA241: NestleP.2 | AB241: CAMILO MONTAÑO RESTREPO | AC241: camilo.montano
A242: NESTLE PURINA | B242: ORIENTE | C242: BOGOTA | D242: MODERNO | E242: EXITO | F242: EXITO | G242: BOGOTA | I242: 442719 | J242: 442719-EXITO COLINA | L242: EXITO CALLE 80 | M242: 1 | N242: GESTION IMPULSO - JUNIO 2025 | O242: USA ACCESORIOS QUE NO CUMPLE CON EL CODIGO DE VESTIMENTA | P242: NO | S242: 13/06/2025 00:00:00 | T242: 16/06/2025 16:49:11 | U242: 16/06/2025 16:51:46 | V242: 27486785 | W242: PRODUCTIVIDAD | Z242: User 2 | AA242: NestleP.2 | AB242: CAMILO MONTAÑO RESTREPO | AC242: camilo.montano
... A259: NESTLE PURINA | B259: ORIENTE | C259: BOGOTA | D259: MODERNO | E259: EXITO | F259: EXITO | G259: BOGOTA | I259: 442719 | J259: 442719-EXITO COLINA | L259: EXITO CALLE 80 | M259: 1 | N259: GESTION IMPULSO - JUNIO 2025 | O259: DESEA AÑADIR ALGUNA OBSERVACION Y/O NOVEDAD DEL MYSTERY REALIZADO? | P259: NO | S259: 13/06/2025 00:00:00 | T259: 16/06/2025 16:49:11 | U259: 16/06/2025 16:51:46 | V259: 27486785 | W259: PRODUCTIVIDAD | Z259: User 2 | AA259: NestleP.2 | AB259: CAMILO MONTAÑO RESTREPO | AC259: camilo.montano
A260: NESTLE PURINA | B260: PACIFICO | C260: CALI | D260: ESPECIALIZADO | E260: AGROPECUARIA LA HACIENDA Y CIA S.A.S | F260: AGROPUNTO | G260: CALI | I260: 356625 | J260: 356625-AGRO LA HACIENDA SAS SUR | K260: 0 | L260: SUPERMERCADOS INDEPENDIENTES | M260: 1 | N260: GESTION IMPULSO - JUNIO 2025 | O260: SE LOGRA REALIZAR EL MYSTERY? | P260: SI | S260: 17/06/2025 00:00:00 | T260: 17/06/2025 17:53:28 | U260: 17/06/2025 17:58:39 | V260: 27493887 | W260: PRODUCTIVIDAD | Z260: User 7 | AA260: NestleP.7 | AB260: CAMILO MONTAÑO RESTREPO | AC260: camilo.montano
A261: NESTLE PURINA | B261: PACIFICO | C261: CALI | D261: ESPECIALIZADO | E261: AGROPECUARIA LA HACIENDA Y CIA S.A.S | F261: AGROPUNTO | G261: CALI | I261: 356625 | J261: 356625-AGRO LA HACIENDA SAS SUR | K261: 0 | L261: SUPERMERCADOS INDEPENDIENTES | M261: 1 | N261: GESTION IMPULSO - JUNIO 2025 | O261: ¿CUMPLE HORARIO DE ENTRADA O SALIDA DE LA TIENDA? | P261: SI | S261: 17/06/2025 00:00:00 | T261: 17/06/2025 17:53:28 | U261: 17/06/2025 17:58:39 | V261: 27493887 | W261: PRODUCTIVIDAD | Z261: User 7 | AA261: NestleP.7 | AB261: CAMILO MONTAÑO RESTREPO | AC261: camilo.montano
A262: NESTLE PURINA | B262: PACIFICO | C262: CALI | D262: ESPECIALIZADO | E262: AGROPECUARIA LA HACIENDA Y CIA S.A.S | F262: AGROPUNTO | G262: CALI | I262: 356625 | J262: 356625-AGRO LA HACIENDA SAS SUR | K262: 0 | L262: SUPERMERCADOS INDEPENDIENTES | M262: 1 | N262: GESTION IMPULSO - JUNIO 2025 | O262: CUENTA CON PANTALON DEL UNIFORME SEGÚN EL CARGO (NEGRO / ROJO / TURQUESA / JEAN) | P262: SI | S262: 17/06/2025 00:00:00 | T262: 17/06/2025 17:53:28 | U262: 17/06/2025 17:58:39 | V262: 27493887 | W262: PRODUCTIVIDAD | Z262: User 7 | AA262: NestleP.7 | AB262: CAMILO MONTAÑO RESTREPO | AC262: camilo.montano
A263: NESTLE PURINA | B263: PACIFICO | C263: CALI | D263: ESPECIALIZADO | E263: AGROPECUARIA LA HACIENDA Y CIA S.A.S | F263: AGROPUNTO | G263: CALI | I263: 356625 | J263: 356625-AGRO LA HACIENDA SAS SUR | K263: 0 | L263: SUPERMERCADOS INDEPENDIENTES | M263: 1 | N263: GESTION IMPULSO - JUNIO 2025 | O263: CUENTA CON CAMISA DEL UNIFORME Y LOGOS SEGÚN EL CARGO (NEGRA / GRIS / ROJA / TURQUESA) (Es permitido usar debajo de la camisa buso manga larga Negro) | P263: SI | S263: 17/06/2025 00:00:00 | T263: 17/06/2025 17:53:28 | U263: 17/06/2025 17:58:39 | V263: 27493887 | W263: PRODUCTIVIDAD | Z263: User 7 | AA263: NestleP.7 | AB263: CAMILO MONTAÑO RESTREPO | AC263: camilo.montano
A264: NESTLE PURINA | B264: PACIFICO | C264: CALI | D264: ESPECIALIZADO | E264: AGROPECUARIA LA HACIENDA Y CIA S.A.S | F264: AGROPUNTO | G264: CALI | I264: 356625 | J264: 356625-AGRO LA HACIENDA SAS SUR | K264: 0 | L264: SUPERMERCADOS INDEPENDIENTES | M264: 1 | N264: GESTION IMPULSO - JUNIO 2025 | O264: CUENTA CON CALZADO DE ACUERDO AL UNIFORME | P264: SI | S264: 17/06/2025 00:00:00 | T264: 17/06/2025 17:53:28 | U264: 17/06/2025 17:58:39 | V264: 27493887 | W264: PRODUCTIVIDAD | Z264: User 7 | AA264: NestleP.7 | AB264: CAMILO MONTAÑO RESTREPO | AC264: camilo.montano
A265: NESTLE PURINA | B265: PACIFICO | C265: CALI | D265: ESPECIALIZADO | E265: AGROPECUARIA LA HACIENDA Y CIA S.A.S | F265: AGROPUNTO | G265: CALI | I265: 356625 | J265: 356625-AGRO LA HACIENDA SAS SUR | K265: 0 | L265: SUPERMERCADOS INDEPENDIENTES | M265: 1 | N265: GESTION IMPULSO - JUNIO 2025 | O265: POSEE ALGUNA PRENDA ENCIMA DEL UNIFORME NO AUTORIZADA POR LA MARCA (Unicamente esta permitido chaleco de Sodimac y Easy) | P265: NO | S265: 17/06/2025 00:00:00 | T265: 17/06/2025 17:53:28 | U265: 17/06/2025 17:58:39 | V265: 27493887 | W265: PRODUCTIVIDAD | Z265: User 7 | AA265: NestleP.7 | AB265: CAMILO MONTAÑO RESTREPO | AC265: camilo.montano
A266: NESTLE PURINA | B266: PACIFICO | C266: CALI | D266: ESPECIALIZADO | E266: AGROPECUARIA LA HACIENDA Y CIA S.A.S | F266: AGROPUNTO | G266: CALI | I266: 356625 | J266: 356625-AGRO LA HACIENDA SAS SUR | K266: 0 | L266: SUPERMERCADOS INDEPENDIENTES | M266: 1 | N266: GESTION IMPULSO - JUNIO 2025 | O266: EL UNIFORME Y ZAPATOS SE ENCUENTRAN LIMPIOS Y EN BUEN ESTADO | P266: SI | S266: 17/06/2025 00:00:00 | T266: 17/06/2025 17:53:28 | U266: 17/06/2025 17:58:39 | V266: 27493887 | W266: PRODUCTIVIDAD | Z266: User 7 | AA266: NestleP.7 | AB266: CAMILO MONTAÑO RESTREPO | AC266: camilo.montano
A267: NESTLE PURINA | B267: PACIFICO | C267: CALI | D267: ESPECIALIZADO | E267: AGROPECUARIA LA HACIENDA Y CIA S.A.S | F267: AGROPUNTO | G267: CALI | I267: 356625 | J267: 356625-AGRO LA HACIENDA SAS SUR | K267: 0 | L267: SUPERMERCADOS INDEPENDIENTES | M267: 1 | N267: GESTION IMPULSO - JUNIO 2025 | O267: SU CABELLO LUCE LIMPIO, ORGANIZADO O RECOGIDO | P267: SI | S267: 17/06/2025 00:00:00 | T267: 17/06/2025 17:53:28 | U267: 17/06/2025 17:58:39 | V267: 27493887 | W267: PRODUCTIVIDAD | Z267: User 7 | AA267: NestleP.7 | AB267: CAMILO MONTAÑO RESTREPO | AC267: camilo.montano
A268: NESTLE PURINA | B268: PACIFICO | C268: CALI | D268: ESPECIALIZADO | E268: AGROPECUARIA LA HACIENDA Y CIA S.A.S | F268: AGROPUNTO | G268: CALI | I268: 356625 | J268: 356625-AGRO LA HACIENDA SAS SUR | K268: 0 | L268: SUPERMERCADOS INDEPENDIENTES | M268: 1 | N268: GESTION IMPULSO - JUNIO 2025 | O268: PRESENTA EXCESO DE MAQUILLAJE QUE NO CUMPLE CON EL CODIGO DE VESTIMENTA | P268: NO | S268: 17/06/2025 00:00:00 | T268: 17/06/2025 17:53:28 | U268: 17/06/2025 17:58:39 | V268: 27493887 | W268: PRODUCTIVIDAD | Z268: User 7 | AA268: NestleP.7 | AB268: CAMILO MONTAÑO RESTREPO | AC268: camilo.montano
A269: NESTLE PURINA | B269: PACIFICO | C269: CALI | D269: ESPECIALIZADO | E269: AGROPECUARIA LA HACIENDA Y CIA S.A.S | F269: AGROPUNTO | G269: CALI | I269: 356625 | J269: 356625-AGRO LA HACIENDA SAS SUR | K269: 0 | L269: SUPERMERCADOS INDEPENDIENTES | M269: 1 | N269: GESTION IMPULSO - JUNIO 2025 | O269: TIENE TATUAJES O PIERCINGS VISIBLES QUE NO CUMPLE CON EL CODIGO DE VESTIMENTA | P269: NO | S269: 17/06/2025 00:00:00 | T269: 17/06/2025 17:53:28 | U269: 17/06/2025 17:58:39 | V269: 27493887 | W269: PRODUCTIVIDAD | Z269: User 7 | AA269: NestleP.7 | AB269: CAMILO MONTAÑO RESTREPO | AC269: camilo.montano
A270: NESTLE PURINA | B270: PACIFICO | C270: CALI | D270: ESPECIALIZADO | E270: AGROPECUARIA LA HACIENDA Y CIA S.A.S | F270: AGROPUNTO | G270: CALI | I270: 356625 | J270: 356625-AGRO LA HACIENDA SAS SUR | K270: 0 | L270: SUPERMERCADOS INDEPENDIENTES | M270: 1 | N270: GESTION IMPULSO - JUNIO 2025 | O270: TIENE UÑAS LLAMATIVAS Y/O LARGAS QUE NO CUMPLE CON EL CODIGO DE VESTIMENTA | P270: NO | S270: 17/06/2025 00:00:00 | T270: 17/06/2025 17:53:28 | U270: 17/06/2025 17:58:39 | V270: 27493887 | W270: PRODUCTIVIDAD | Z270: User 7 | AA270: NestleP.7 | AB270: CAMILO MONTAÑO RESTREPO | AC270: camilo.montano
A271: NESTLE PURINA | B271: PACIFICO | C271: CALI | D271: ESPECIALIZADO | E271: AGROPECUARIA LA HACIENDA Y CIA S.A.S | F271: AGROPUNTO | G271: CALI | I271: 356625 | J271: 356625-AGRO LA HACIENDA SAS SUR | K271: 0 | L271: SUPERMERCADOS INDEPENDIENTES | M271: 1 | N271: GESTION IMPULSO - JUNIO 2025 | O271: USA ACCESORIOS QUE NO CUMPLE CON EL CODIGO DE VESTIMENTA | P271: NO | S271: 17/06/2025 00:00:00 | T271: 17/06/2025 17:53:28 | U271: 17/06/2025 17:58:39 | V271: 27493887 | W271: PRODUCTIVIDAD | Z271: User 7 | AA271: NestleP.7 | AB271: CAMILO MONTAÑO RESTREPO | AC271: camilo.montano
... A340: NESTLE PURINA | B340: COSTA | C340: BARRANQUILLA | D340: ESPECIALIZADO | E340: SUPERETE | F340: SUPERETES | G340: BARRANQUILLA | I340: 65453 | J340: DISTRIBUCIONES MILENA | K340: 0 | L340: Mercadeo | M340: 1 | N340: GESTION IMPULSO - JUNIO 2025 | O340: DESEA AÑADIR ALGUNA OBSERVACION Y/O NOVEDAD DEL MYSTERY REALIZADO? | P340: NO | S340: 18/06/2025 00:00:00 | T340: 18/06/2025 13:07:28 | U340: 18/06/2025 13:12:56 | V340: 27498090 | W340: PRODUCTIVIDAD | Z340: User 5 | AA340: NestleP.5 | AB340: CAMILO MONTAÑO RESTREPO | AC340: camilo.montano
A341: NESTLE PURINA | B341: COSTA | C341: BARRANQUILLA | D341: MODERNO | E341: OLIMPICA | F341: OLIMPICA | G341: COSTA | I341: 447964 | J341: 447964-MAKRO BARRANQUILLA | L341: STO 039 CHIQUINQUIRA | M341: 1 | N341: GESTION IMPULSO - JUNIO 2025 | O341: SE LOGRA REALIZAR EL MYSTERY? | P341: SI | S341: 17/06/2025 00:00:00 | T341: 24/06/2025 15:03:27 | U341: 24/06/2025 15:07:50 | V341: 27521942 | W341: PRODUCTIVIDAD | Z341: User 5 | AA341: NestleP.5 | AB341: CAMILO MONTAÑO RESTREPO | AC341: camilo.montano
A342: NESTLE PURINA | B342: COSTA | C342: BARRANQUILLA | D342: MODERNO | E342: OLIMPICA | F342: OLIMPICA | G342: COSTA | I342: 447964 | J342: 447964-MAKRO BARRANQUILLA | L342: STO 039 CHIQUINQUIRA | M342: 1 | N342: GESTION IMPULSO - JUNIO 2025 | O342: ¿CUMPLE HORARIO DE ENTRADA O SALIDA DE LA TIENDA? | P342: SI | S342: 17/06/2025 00:00:00 | T342: 24/06/2025 15:03:27 | U342: 24/06/2025 15:07:50 | V342: 27521942 | W342: PRODUCTIVIDAD | Z342: User 5 | AA342: NestleP.5 | AB342: CAMILO MONTAÑO RESTREPO | AC342: camilo.montano
A343: NESTLE PURINA | B343: COSTA | C343: BARRANQUILLA | D343: MODERNO | E343: OLIMPICA | F343: OLIMPICA | G343: COSTA | I343: 447964 | J343: 447964-MAKRO BARRANQUILLA | L343: STO 039 CHIQUINQUIRA | M343: 1 | N343: GESTION IMPULSO - JUNIO 2025 | O343: CUENTA CON PANTALON DEL UNIFORME SEGÚN EL CARGO (NEGRO / ROJO / TURQUESA / JEAN) | P343: SI | S343: 17/06/2025 00:00:00 | T343: 24/06/2025 15:03:27 | U343: 24/06/2025 15:07:50 | V343: 27521942 | W343: PRODUCTIVIDAD | Z343: User 5 | AA343: NestleP.5 | AB343: CAMILO MONTAÑO RESTREPO | AC343: camilo.montano
A344: NESTLE PURINA | B344: COSTA | C344: BARRANQUILLA | D344: MODERNO | E344: OLIMPICA | F344: OLIMPICA | G344: COSTA | I344: 447964 | J344: 447964-MAKRO BARRANQUILLA | L344: STO 039 CHIQUINQUIRA | M344: 1 | N344: GESTION IMPULSO - JUNIO 2025 | O344: CUENTA CON CAMISA DEL UNIFORME Y LOGOS SEGÚN EL CARGO (NEGRA / GRIS / ROJA / TURQUESA) (Es permitido usar debajo de la camisa buso manga larga Negro) | P344: SI | S344: 17/06/2025 00:00:00 | T344: 24/06/2025 15:03:27 | U344: 24/06/2025 15:07:50 | V344: 27521942 | W344: PRODUCTIVIDAD | Z344: User 5 | AA344: NestleP.5 | AB344: CAMILO MONTAÑO RESTREPO | AC344: camilo.montano
A345: NESTLE PURINA | B345: COSTA | C345: BARRANQUILLA | D345: MODERNO | E345: OLIMPICA | F345: OLIMPICA | G345: COSTA | I345: 447964 | J345: 447964-MAKRO BARRANQUILLA | L345: STO 039 CHIQUINQUIRA | M345: 1 | N345: GESTION IMPULSO - JUNIO 2025 | O345: CUENTA CON CALZADO DE ACUERDO AL UNIFORME | P345: SI | S345: 17/06/2025 00:00:00 | T345: 24/06/2025 15:03:27 | U345: 24/06/2025 15:07:50 | V345: 27521942 | W345: PRODUCTIVIDAD | Z345: User 5 | AA345: NestleP.5 | AB345: CAMILO MONTAÑO RESTREPO | AC345: camilo.montano
A346: NESTLE PURINA | B346: COSTA | C346: BARRANQUILLA | D346: MODERNO | E346: OLIMPICA | F346: OLIMPICA | G346: COSTA | I346: 447964 | J346: 447964-MAKRO BARRANQUILLA | L346: STO 039 CHIQUINQUIRA | M346: 1 | N346: GESTION IMPULSO - JUNIO 2025 | O346: POSEE ALGUNA PRENDA ENCIMA DEL UNIFORME NO AUTORIZADA POR LA MARCA (Unicamente esta permitido chaleco de Sodimac y Easy) | P346: NO | S346: 17/06/2025 00:00:00 | T346: 24/06/2025 15:03:27 | U346: 24/06/2025 15:07:50 | V346: 27521942 | W346: PRODUCTIVIDAD | Z346: User 5 | AA346: NestleP.5 | AB346: CAMILO MONTAÑO RESTREPO | AC346: camilo.montano
A347: NESTLE PURINA | B347: COSTA | C347: BARRANQUILLA | D347: MODERNO | E347: OLIMPICA | F347: OLIMPICA | G347: COSTA | I347: 447964 | J347: 447964-MAKRO BARRANQUILLA | L347: STO 039 CHIQUINQUIRA | M347: 1 | N347: GESTION IMPULSO - JUNIO 2025 | O347: EL UNIFORME Y ZAPATOS SE ENCUENTRAN LIMPIOS Y EN BUEN ESTADO | P347: SI | S347: 17/06/2025 00:00:00 | T347: 24/06/2025 15:03:27 | U347: 24/06/2025 15:07:50 | V347: 27521942 | W347: PRODUCTIVIDAD | Z347: User 5 | AA347: NestleP.5 | AB347: CAMILO MONTAÑO RESTREPO | AC347: camilo.montano
A348: NESTLE PURINA | B348: COSTA | C348: BARRANQUILLA | D348: MODERNO | E348: OLIMPICA | F348: OLIMPICA | G348: COSTA | I348: 447964 | J348: 447964-MAKRO BARRANQUILLA | L348: STO 039 CHIQUINQUIRA | M348: 1 | N348: GESTION IMPULSO - JUNIO 2025 | O348: SU CABELLO LUCE LIMPIO, ORGANIZADO O RECOGIDO | P348: SI | S348: 17/06/2025 00:00:00 | T348: 24/06/2025 15:03:27 | U348: 24/06/2025 15:07:50 | V348: 27521942 | W348: PRODUCTIVIDAD | Z348: User 5 | AA348: NestleP.5 | AB348: CAMILO MONTAÑO RESTREPO | AC348: camilo.montano
A349: NESTLE PURINA | B349: COSTA | C349: BARRANQUILLA | D349: MODERNO | E349: OLIMPICA | F349: OLIMPICA | G349: COSTA | I349: 447964 | J349: 447964-MAKRO BARRANQUILLA | L349: STO 039 CHIQUINQUIRA | M349: 1 | N349: GESTION IMPULSO - JUNIO 2025 | O349: PRESENTA EXCESO DE MAQUILLAJE QUE NO CUMPLE CON EL CODIGO DE VESTIMENTA | P349: NO | S349: 17/06/2025 00:00:00 | T349: 24/06/2025 15:03:27 | U349: 24/06/2025 15:07:50 | V349: 27521942 | W349: PRODUCTIVIDAD | Z349: User 5 | AA349: NestleP.5 | AB349: CAMILO MONTAÑO RESTREPO | AC349: camilo.montano
A350: NESTLE PURINA | B350: COSTA | C350: BARRANQUILLA | D350: MODERNO | E350: OLIMPICA | F350: OLIMPICA | G350: COSTA | I350: 447964 | J350: 447964-MAKRO BARRANQUILLA | L350: STO 039 CHIQUINQUIRA | M350: 1 | N350: GESTION IMPULSO - JUNIO 2025 | O350: TIENE TATUAJES O PIERCINGS VISIBLES QUE NO CUMPLE CON EL CODIGO DE VESTIMENTA | P350: NO | S350: 17/06/2025 00:00:00 | T350: 24/06/2025 15:03:27 | U350: 24/06/2025 15:07:50 | V350: 27521942 | W350: PRODUCTIVIDAD | Z350: User 5 | AA350: NestleP.5 | AB350: CAMILO MONTAÑO RESTREPO | AC350: camilo.montano
A351: NESTLE PURINA | B351: COSTA | C351: BARRANQUILLA | D351: MODERNO | E351: OLIMPICA | F351: OLIMPICA | G351: COSTA | I351: 447964 | J351: 447964-MAKRO BARRANQUILLA | L351: STO 039 CHIQUINQUIRA | M351: 1 | N351: GESTION IMPULSO - JUNIO 2025 | O351: TIENE UÑAS LLAMATIVAS Y/O LARGAS QUE NO CUMPLE CON EL CODIGO DE VESTIMENTA | P351: NO | S351: 17/06/2025 00:00:00 | T351: 24/06/2025 15:03:27 | U351: 24/06/2025 15:07:50 | V351: 27521942 | W351: PRODUCTIVIDAD | Z351: User 5 | AA351: NestleP.5 | AB351: CAMILO MONTAÑO RESTREPO | AC351: camilo.montano
A352: NESTLE PURINA | B352: COSTA | C352: BARRANQUILLA | D352: MODERNO | E352: OLIMPICA | F352: OLIMPICA | G352: COSTA | I352: 447964 | J352: 447964-MAKRO BARRANQUILLA | L352: STO 039 CHIQUINQUIRA | M352: 1 | N352: GESTION IMPULSO - JUNIO 2025 | O352: USA ACCESORIOS QUE NO CUMPLE CON EL CODIGO DE VESTIMENTA | P352: NO | S352: 17/06/2025 00:00:00 | T352: 24/06/2025 15:03:27 | U352: 24/06/2025 15:07:50 | V352: 27521942 | W352: PRODUCTIVIDAD | Z352: User 5 | AA352: NestleP.5 | AB352: CAMILO MONTAÑO RESTREPO | AC352: camilo.montano
... A369: NESTLE PURINA | B369: COSTA | C369: BARRANQUILLA | D369: MODERNO | E369: OLIMPICA | F369: OLIMPICA | G369: COSTA | I369: 447964 | J369: 447964-MAKRO BARRANQUILLA | L369: STO 039 CHIQUINQUIRA | M369: 1 | N369: GESTION IMPULSO - JUNIO 2025 | O369: DESEA AÑADIR ALGUNA OBSERVACION Y/O NOVEDAD DEL MYSTERY REALIZADO? | P369: NO | S369: 17/06/2025 00:00:00 | T369: 24/06/2025 15:03:27 | U369: 24/06/2025 15:07:50 | V369: 27521942 | W369: PRODUCTIVIDAD | Z369: User 5 | AA369: NestleP.5 | AB369: CAMILO MONTAÑO RESTREPO | AC369: camilo.montano
A370: NESTLE PURINA | B370: COSTA | C370: BARRANQUILLA | D370: MODERNO | E370: OLIMPICA | F370: OLIMPICA | G370: COSTA | I370: 126325 | J370: 126325-OLIMPICA STO 039 CHIQUINQUIRA | K370: 7701008000391 | L370: STO 039 CHIQUINQUIRA | M370: 1 | N370: GESTION IMPULSO - JUNIO 2025 | O370: SE LOGRA REALIZAR EL MYSTERY? | P370: SI | S370: 26/06/2025 10:00:01 | T370: 26/06/2025 10:00:06 | U370: 26/06/2025 10:00:10 | V370: 27531935 | W370: PRODUCTIVIDAD | Z370: User 5 | AA370: NestleP.5 | AB370: CAMILO MONTAÑO RESTREPO | AC370: camilo.montano
A371: NESTLE PURINA | B371: COSTA | C371: BARRANQUILLA | D371: MODERNO | E371: OLIMPICA | F371: OLIMPICA | G371: COSTA | I371: 126325 | J371: 126325-OLIMPICA STO 039 CHIQUINQUIRA | K371: 7701008000391 | L371: STO 039 CHIQUINQUIRA | M371: 1 | N371: GESTION IMPULSO - JUNIO 2025 | O371: ¿CUMPLE HORARIO DE ENTRADA O SALIDA DE LA TIENDA? | P371: SI | S371: 26/06/2025 10:00:01 | T371: 26/06/2025 10:00:06 | U371: 26/06/2025 10:00:12 | V371: 27531935 | W371: PRODUCTIVIDAD | Z371: User 5 | AA371: NestleP.5 | AB371: CAMILO MONTAÑO RESTREPO | AC371: camilo.montano
A372: NESTLE PURINA | B372: COSTA | C372: BARRANQUILLA | D372: MODERNO | E372: OLIMPICA | F372: OLIMPICA | G372: COSTA | I372: 126325 | J372: 126325-OLIMPICA STO 039 CHIQUINQUIRA | K372: 7701008000391 | L372: STO 039 CHIQUINQUIRA | M372: 1 | N372: GESTION IMPULSO - JUNIO 2025 | O372: CUENTA CON PANTALON DEL UNIFORME SEGÚN EL CARGO (NEGRO / ROJO / TURQUESA / JEAN) | P372: SI | S372: 26/06/2025 10:00:01 | T372: 26/06/2025 10:00:06 | U372: 26/06/2025 10:00:16 | V372: 27531935 | W372: PRODUCTIVIDAD | Z372: User 5 | AA372: NestleP.5 | AB372: CAMILO MONTAÑO RESTREPO | AC372: camilo.montano
A373: NESTLE PURINA | B373: COSTA | C373: BARRANQUILLA | D373: MODERNO | E373: OLIMPICA | F373: OLIMPICA | G373: COSTA | I373: 126325 | J373: 126325-OLIMPICA STO 039 CHIQUINQUIRA | K373: 7701008000391 | L373: STO 039 CHIQUINQUIRA | M373: 1 | N373: GESTION IMPULSO - JUNIO 2025 | O373: CUENTA CON CAMISA DEL UNIFORME Y LOGOS SEGÚN EL CARGO (NEGRA / GRIS / ROJA / TURQUESA) (Es permitido usar debajo de la camisa buso manga larga Negro) | P373: SI | S373: 26/06/2025 10:00:01 | T373: 26/06/2025 10:00:06 | U373: 26/06/2025 10:00:17 | V373: 27531935 | W373: PRODUCTIVIDAD | Z373: User 5 | AA373: NestleP.5 | AB373: CAMILO MONTAÑO RESTREPO | AC373: camilo.montano
A374: NESTLE PURINA | B374: COSTA | C374: BARRANQUILLA | D374: MODERNO | E374: OLIMPICA | F374: OLIMPICA | G374: COSTA | I374: 126325 | J374: 126325-OLIMPICA STO 039 CHIQUINQUIRA | K374: 7701008000391 | L374: STO 039 CHIQUINQUIRA | M374: 1 | N374: GESTION IMPULSO - JUNIO 2025 | O374: CUENTA CON CALZADO DE ACUERDO AL UNIFORME | P374: SI | S374: 26/06/2025 10:00:01 | T374: 26/06/2025 10:00:06 | U374: 26/06/2025 10:00:20 | V374: 27531935 | W374: PRODUCTIVIDAD | Z374: User 5 | AA374: NestleP.5 | AB374: CAMILO MONTAÑO RESTREPO | AC374: camilo.montano
A375: NESTLE PURINA | B375: COSTA | C375: BARRANQUILLA | D375: MODERNO | E375: OLIMPICA | F375: OLIMPICA | G375: COSTA | I375: 126325 | J375: 126325-OLIMPICA STO 039 CHIQUINQUIRA | K375: 7701008000391 | L375: STO 039 CHIQUINQUIRA | M375: 1 | N375: GESTION IMPULSO - JUNIO 2025 | O375: POSEE ALGUNA PRENDA ENCIMA DEL UNIFORME NO AUTORIZADA POR LA MARCA (Unicamente esta permitido chaleco de Sodimac y Easy) | P375: NO | S375: 26/06/2025 10:00:01 | T375: 26/06/2025 10:00:06 | U375: 26/06/2025 10:00:23 | V375: 27531935 | W375: PRODUCTIVIDAD | Z375: User 5 | AA375: NestleP.5 | AB375: CAMILO MONTAÑO RESTREPO | AC375: camilo.montano
A376: NESTLE PURINA | B376: COSTA | C376: BARRANQUILLA | D376: MODERNO | E376: OLIMPICA | F376: OLIMPICA | G376: COSTA | I376: 126325 | J376: 126325-OLIMPICA STO 039 CHIQUINQUIRA | K376: 7701008000391 | L376: STO 039 CHIQUINQUIRA | M376: 1 | N376: GESTION IMPULSO - JUNIO 2025 | O376: EL UNIFORME Y ZAPATOS SE ENCUENTRAN LIMPIOS Y EN BUEN ESTADO | P376: SI | S376: 26/06/2025 10:00:01 | T376: 26/06/2025 10:00:06 | U376: 26/06/2025 10:00:26 | V376: 27531935 | W376: PRODUCTIVIDAD | Z376: User 5 | AA376: NestleP.5 | AB376: CAMILO MONTAÑO RESTREPO | AC376: camilo.montano
A377: NESTLE PURINA | B377: COSTA | C377: BARRANQUILLA | D377: MODERNO | E377: OLIMPICA | F377: OLIMPICA | G377: COSTA | I377: 126325 | J377: 126325-OLIMPICA STO 039 CHIQUINQUIRA | K377: 7701008000391 | L377: STO 039 CHIQUINQUIRA | M377: 1 | N377: GESTION IMPULSO - JUNIO 2025 | O377: SU CABELLO LUCE LIMPIO, ORGANIZADO O RECOGIDO | P377: SI | S377: 26/06/2025 10:00:01 | T377: 26/06/2025 10:00:06 | U377: 26/06/2025 10:00:30 | V377: 27531935 | W377: PRODUCTIVIDAD | Z377: User 5 | AA377: NestleP.5 | AB377: CAMILO MONTAÑO RESTREPO | AC377: camilo.montano
...

Sheet ENCUESTA
A1: TRADICIONAL | B1: ESPECIALIZADO | C1: MODERNO | D1: CLUSTER | E1: PESO | F1: TIPO | G1: PREGUNTA | H1: RTA CORRECTA | K1: CLUSTER | L1: PESO CLUSTER
A2: 0 | B2: 0 | C2: 0 | D2: N/A | E2: 0 | F2: UNICA | G2: SE LOGRA REALIZAR EL MYSTERY? | K2: HORARIO | L2: 0.2
A3: 20 | B3: 20 | C3: 20 | D3: HORARIO | E3: 20 | F3: UNICA | G3: ¿CUMPLE HORARIO DE ENTRADA O SALIDA DE LA TIENDA? | H3: SI | K3: UNIFORME | L3: 0.15
A4: =15/11 -> 1.3636364 | B4: =15/11 -> 1.3636364 | C4: =15/11 -> 1.3636364 | D4: UNIFORME | E4: =15/11 -> 1.3636364 | F4: UNICA | G4: CUENTA CON PANTALON DEL UNIFORME SEGÚN EL CARGO (NEGRO / ROJO / TURQUESA / JEAN) | H4: SI | K4: ABORDAJE | L4: 0.2
A5: =15/11 -> 1.3636364 | B5: =15/11 -> 1.3636364 | C5: =15/11 -> 1.3636364 | D5: UNIFORME | E5: =15/11 -> 1.3636364 | F5: UNICA | G5: CUENTA CON CAMISA DEL UNIFORME Y LOGOS SEGÚN EL CARGO (NEGRA / GRIS / ROJA / TURQUESA) (Es permitido usar debajo de la camisa buso manga larga Negro) | H5: SI | K5: PORTAFOLIO Y MANEJO DE OBJECIONES | L5: 0.2
A6: =15/11 -> 1.3636364 | B6: =15/11 -> 1.3636364 | C6: =15/11 -> 1.3636364 | D6: UNIFORME | E6: =15/11 -> 1.3636364 | F6: UNICA | G6: CUENTA CON CALZADO DE ACUERDO AL UNIFORME | H6: SI | K6: LABOR DE VENTA | L6: 0.15
A7: =15/11 -> 1.3636364 | B7: =15/11 -> 1.3636364 | C7: =15/11 -> 1.3636364 | D7: UNIFORME | E7: =15/11 -> 1.3636364 | F7: UNICA | G7: POSEE ALGUNA PRENDA ENCIMA DEL UNIFORME NO AUTORIZADA POR LA MARCA (Unicamente esta permitido chaleco de Sodimac y Easy) | H7: NO | K7: ACTIVIDADES DEL MES | L7: 0.1
A8: =15/11 -> 1.3636364 | B8: =15/11 -> 1.3636364 | C8: =15/11 -> 1.3636364 | D8: UNIFORME | E8: =15/11 -> 1.3636364 | F8: UNICA | G8: EL UNIFORME Y ZAPATOS SE ENCUENTRAN LIMPIOS Y EN BUEN ESTADO | H8: SI | K8: TOTAL GENERAL | L8: =SUM(L2:L7) -> 1
A9: =15/11 -> 1.3636364 | B9: =15/11 -> 1.3636364 | C9: =15/11 -> 1.3636364 | D9: UNIFORME | E9: =15/11 -> 1.3636364 | F9: UNICA | G9: SU CABELLO LUCE LIMPIO, ORGANIZADO O RECOGIDO | H9: SI
A10: =15/11 -> 1.3636364 | B10: =15/11 -> 1.3636364 | C10: =15/11 -> 1.3636364 | D10: UNIFORME | E10: =15/11 -> 1.3636364 | F10: UNICA | G10: PRESENTA EXCESO DE MAQUILLAJE QUE NO CUMPLE CON EL CODIGO DE VESTIMENTA | H10: NO
A11: =15/11 -> 1.3636364 | B11: =15/11 -> 1.3636364 | C11: =15/11 -> 1.3636364 | D11: UNIFORME | E11: =15/11 -> 1.3636364 | F11: UNICA | G11: TIENE TATUAJES O PIERCINGS VISIBLES QUE NO CUMPLE CON EL CODIGO DE VESTIMENTA | H11: NO
A12: =15/11 -> 1.3636364 | B12: =15/11 -> 1.3636364 | C12: =15/11 -> 1.3636364 | D12: UNIFORME | E12: =15/11 -> 1.3636364 | F12: UNICA | G12: TIENE UÑAS LLAMATIVAS Y/O LARGAS QUE NO CUMPLE CON EL CODIGO DE VESTIMENTA | H12: NO
A13: =15/11 -> 1.3636364 | B13: =15/11 -> 1.3636364 | C13: =15/11 -> 1.3636364 | D13: UNIFORME | E13: =15/11 -> 1.3636364 | F13: UNICA | G13: USA ACCESORIOS QUE NO CUMPLE CON EL CODIGO DE VESTIMENTA | H13: NO
A14: 20 | B14: 20 | C14: 20 | D14: ABORDAJE | E14: 20 | F14: UNICA | G14: SE PRODUCE ABORDO PROACTIVO (antes de los 3 min) | H14: SI
A15: =20/13 -> 1.5384615 | B15: =20/13 -> 1.5384615 | C15: =20/13 -> 1.5384615 | D15: PORTAFOLIO Y MANEJO DE OBJECIONES | E15: =20/13 -> 1.5384615 | F15: UNICA | G15: OFRECIO ALGUN PRODUCTO DEL PORTAFOLIO PURINA DE PRODUCTOS SECOS COMUNICANDO LOS BENEFICIOS DEL PRODUCTO (DOG CHOW, CAT CHOW, ALPO, GATSY,FELIX) | H15: SI
A16: =20/13 -> 1.5384615 | B16: =20/13 -> 1.5384615 | C16: =20/13 -> 1.5384615 | D16: PORTAFOLIO Y MANEJO DE OBJECIONES | E16: =20/13 -> 1.5384615 | F16: UNICA | G16: OFRECIO ALGUN PRODUCTO PORTAFOLIO PURINA DE PRODUCTOS HUMEDOS, SNACK U OTROS COMUNICANDO LOS BENEFICIOS DEL PRODUCTO (Dog chow húmedo, Cat chow húmedo, Fancy Feast, Felix, Proplan Húmedo, One Húmedo) Snacks (Abrazzos, Dentalife) Arenilla (Tidy Cat) | H16: SI
A17: 0 | B17: 0 | C17: 0 | D17: N/A | E17: 0 | F17: UNICA | G17: SELECCIONE EL CANAL DEL PDV QUE EVALUA | H17: MODERNO, ESPECIALIZADO
A18: =20/13 -> 1.5384615 | B18: =20/13 -> 1.5384615 | C18: =20/13 -> 1.5384615 | D18: PORTAFOLIO Y MANEJO DE OBJECIONES | E18: =20/13 -> 1.5384615 | F18: UNICA | G18: CM - OFRECE PURINA ONE? | H18: SI
A19: =20/13 -> 1.5384615 | B19: =20/13 -> 1.5384615 | C19: =20/13 -> 1.5384615 | D19: PORTAFOLIO Y MANEJO DE OBJECIONES | E19: =20/13 -> 1.5384615 | F19: UNICA | G19: CM - MENCIONA QUE LOS RESULTADOS DE PURINA ONE SON VISIBLES EN 28 DIAS? | H19: SI
A20: =20/13 -> 1.5384615 | B20: =20/13 -> 1.5384615 | C20: =20/13 -> 1.5384615 | D20: PORTAFOLIO Y MANEJO DE OBJECIONES | E20: =20/13 -> 1.5384615 | F20: UNICA | G20: CM - MENCIONA QUE TIENE CARNE DE VERDAD COMO INGREDIENTE NO.1 E INGREDIENTES NATURALES Y FUNCIONALES? | H20: SI
A21: =20/13 -> 1.5384615 | B21: =20/13 -> 1.5384615 | C21: =20/13 -> 1.5384615 | D21: PORTAFOLIO Y MANEJO DE OBJECIONES | E21: =20/13 -> 1.5384615 | F21: UNICA | G21: CM - MENCIONA QUE PURINA ONE CUENTA CON ALIMENTO HUMEDO Y MENCIONA LAS 3 VARIADADES QUE TIENE ( SUPER FOODS, SUPER NUTRIENTES Y MULTI PROTEINAS); APLICA TANTO PARA PERRO COMO PARA GATO | H21: SI
A22: =20/13 -> 1.5384615 | B22: =20/13 -> 1.5384615 | C22: =20/13 -> 1.5384615 | D22: PORTAFOLIO Y MANEJO DE OBJECIONES | E22: =20/13 -> 1.5384615 | F22: UNICA | G22: CM - Maneja la objeción de alto precio en las marcas Purina, comunicando la baja de precios de las marcas o las ofertas disponibles en el punto de venta. | H22: SI
A23: =20/13 -> 1.5384615 | B23: =20/13 -> 1.5384615 | C23: =20/13 -> 1.5384615 | D23: PORTAFOLIO Y MANEJO DE OBJECIONES | E23: =20/13 -> 1.5384615 | F23: UNICA | G23: CM - Bajo la objeción de "precio muy costoso", el asesor ofrece productos en el orden de la segmentación: Perros: Purina One - Dog Chow - Alpo y Gatos: Purina One - Cat Chow - Felix - Gatsy (cuando enuncia Gatsy menciona que "ahora es mas sabroso") | H23: SI
A24: =10/2 -> 5 | B24: =10/2 -> 5 | C24: =10/2 -> 5 | D24: ACTIVIDADES DEL MES | E24: =10/2 -> 5 | F24: UNICA | G24: CM - Dan a conocer al cliente la actividad del "EVENTO CORPORATIVO DE OLIMPICA JUNIO"? | H24: SI
A25: =20/13 -> 1.5384615 | B25: =20/13 -> 1.5384615 | C25: =20/13 -> 1.5384615 | D25: PORTAFOLIO Y MANEJO DE OBJECIONES | E25: =20/13 -> 1.5384615 | F25: UNICA | G25: CE - Lo primero que ofrece el asesor es la marca Pro Plan? | H25: SI
A26: =20/13 -> 1.5384615 | B26: =20/13 -> 1.5384615 | C26: =20/13 -> 1.5384615 | D26: PORTAFOLIO Y MANEJO DE OBJECIONES | E26: =20/13 -> 1.5384615 | F26: UNICA | G26: CE - Ofrece la marca Excellent? | H26: SI
A27: =20/13 -> 1.5384615 | B27: =20/13 -> 1.5384615 | C27: =20/13 -> 1.5384615 | D27: PORTAFOLIO Y MANEJO DE OBJECIONES | E27: =20/13 -> 1.5384615 | F27: UNICA | G27: CE - El asesor comunica que la marca Excellent esta dentro de la categoria SuperPremium pero a un costo mas accesible. | H27: SI
A28: =20/13 -> 1.5384615 | B28: =20/13 -> 1.5384615 | C28: =20/13 -> 1.5384615 | D28: PORTAFOLIO Y MANEJO DE OBJECIONES | E28: =20/13 -> 1.5384615 | F28: UNICA | G28: CE - El asesor comunica los beneficios o caracteristicas del producto Excellent e informa que el producto cambio de imagen pero continua con la misma formula? | H28: SI
A29: =10/2 -> 5 | B29: =10/2 -> 5 | C29: =10/2 -> 5 | D29: ACTIVIDADES DEL MES | E29: =10/2 -> 5 | F29: UNICA | G29: CE - Ofrece producto humedo y comunica la dinamica de multiprice (por la compra de mas cantidades tiene descuento) | H29: SI
A30: 0 | B30: 0 | C30: 0 | D30: N/A | E30: 0 | F30: UNICA | G30: INDIQUE QUE TIPO DE OBJECION / DUDA MANIFESTÓ | H30: FALTA DE PRODUCTO, NO LE INTERESA EL PRODUCTO, NO TIENE DINERO, PREFIERE LA COMPETENCIA
A31: =20/13 -> 1.5384615 | B31: =20/13 -> 1.5384615 | C31: =20/13 -> 1.5384615 | D31: PORTAFOLIO Y MANEJO DE OBJECIONES | E31: =20/13 -> 1.5384615 | F31: UNICA | G31: RESUELVE LA OBJECION SATISFACTORIAMENTE? | H31: SI
A32: =15/11 -> 1.3636364 | B32: =15/11 -> 1.3636364 | C32: =15/11 -> 1.3636364 | D32: UNIFORME | E32: =15/11 -> 1.3636364 | F32: UNICA | G32: SE ENCUENTRA LIMPIA EL AREA DE DEMOSTRACION | H32: SI
A33: =15/2 -> 7.5 | B33: =15/2 -> 7.5 | C33: =15/2 -> 7.5 | D33: LABOR DE VENTA | E33: =15/2 -> 7.5 | F33: UNICA | G33: REALIZA CIERRE DE VENTA | H33: SI
A34: =15/2 -> 7.5 | B34: =15/2 -> 7.5 | C34: =15/2 -> 7.5 | D34: LABOR DE VENTA | E34: =15/2 -> 7.5 | F34: UNICA | G34: CONSIDERO QUE INDEPENDIENTEMENTE DEL SPEECH, LA LABOR DE VENTA ES BUENA | H34: SI
A35: 0 | B35: 0 | C35: 0 | D35: N/A | E35: 0 | F35: UNICA | G35: DESEA AÑADIR ALGUNA OBSERVACION Y/O NOVEDAD DEL MYSTERY REALIZADO?
A36: 0 | B36: 0 | C36: 0 | D36: N/A | E36: 0 | F36: ABIERTA | G36: INDIQUE OBSERVACION Y/O NOVEDAD DEL MYSTERY REALIZADO
